Workbook

Sheet Présentation
A1: Base MAS - INSEE mise à jour 2023
A3: Onget disponible | B3: Annee | D3: Description | E3: Lien vers le dictionnaire de données
A4: POP | B4: 2023 | D4: Contient des indicateurs détaillés sur la POPULATION de Roubaix selon le sexe, l'âge en tranches, la catégorie socio-professionnelle, en tenant compte de la population étrangère et de la population immigrée. | E4: https://www.insee.fr/fr/statistiques/9054332
A5: ACT RES | B5: 2023 | D5: Contient des indicateurs détaillés sur les caractéristiques des ACTIVITES DES RESIDENTS, des SALARIES et non-salariés selon le sexe, l’âge par tranches et la catégorie socio-professionnelles. | E5: https://www.insee.fr/fr/statistiques/9040859
A6: COU FAM MÉNAGES | B6: 2023 | D6: Contient des indicateurs détaillés sur lescaracteristiques des COUPLES, FAMILLES, MENAGES, (nombre d'enfants). | E6: https://www.insee.fr/fr/statistiques/9058978
A7: DIP FORMATION | B7: 2023 | D7: Contient des indicateurs détaillés les DIPLOMES ET FORMATION, la SCOLARISATION et les niveaux de DIPLOMES, les personnes non scolarisées de 15 à ou plus selon le sexe. | E7: https://www.insee.fr/fr/statistiques/9054820
A8: LOG | B8: 2023 | D8: Contient des indicateurs détaillés sur des LOGEMENTS, la possession d'une voiture ainsi que le parc de logements. | E8: https://www.insee.fr/fr/statistiques/9061333
A9: PETITE ENFANCE | B9: 2022 | D9: Contient des indicateurs du nombre d'enfants de 0 à 17 ans | E9: https://www.insee.fr/fr/statistiques/8647104
A10: CAF | B10: 2024 | C10: au 31/12/2024 | D10: Contient des indicateurs sur les bénéficiaires des prestations légales versées par les CAF à l'Iris | E10: https://www.insee.fr/fr/statistiques/8682393
A11: CNAM | B11: 2025 | C11: au 01/01/2025 | D11: Contient des indicateurs sur les bénéficiaires du régime général de l'assurance maladie ainsi que sur les bénéficiaires de la Complémentaire Santé Solidaire (C2S) issus des fichiers des Caisses Primaires d’Assurance Maladie (CPAM). | E11: https://www.insee.fr/fr/statistiques/8736938
A12: DEFM | B12: 2024 | C12: au 31/12/2024 | D12: Contient des indicateurs sur les demandeurs d'emploi à l'Iris (Pôle Emploi-Dares) | E12: https://www.insee.fr/fr/statistiques/8644875
A13: RPLS | B13: 2025 | C13: au 01/01/2025 | D13: Contient des indicateurs sur le Parc des Logements Locatifs des Bailleurs Sociaux à l'Iris | E13: https://www.insee.fr/fr/statistiques/9057420
A15: Précision
A16: # Les données INSEE sont à l'échelle des IRIS
A17: Dans les onglets, chaque iris correpond à une zone des découpages étudiés. Les differents zonages proposés ne se superposant pas au iris, il s 'agit donc d'une interprestation . Il a donc une marge d’erreur. Des indicateurs supplémentaires calculés sont disponibles à la fin des feuilles (tout à droite) sous fond orange
A18: L'ensemble des variables et définitions sont présentes sur le site de l'INSEE | E18: https://www.insee.fr/fr/information/2008354
A19: # Des applications dédiées sont également disponibles sur le portail SIG | E19: https://carto.ville-roubaix.fr
A20: https://carto.ville-roubaix.fr/portal/apps/MapSeries/index.html?appid=439897abe91f40e29fa8d4ca5483c55b
A21: # L'INSEE met également à disposition un dossier complet à l'échelle de la commune
A22: https://www.insee.fr/fr/statistiques/2011101?geo=COM-59512
A23: Pour toutes questions, contacter le service sig : sig@ville-roubaix.fr
A25: Mise a jour tous les ans entre octobre et decembre pour le recensement avec un decalage de 3 ans .
A26: Mise a jour annuelle pour caf cnam DEFEM RPLS

Sheet Portrait Roubaix
B2: Portrait de Roubaix · 2023
B3: Chiffres clés de Roubaix (ensemble des IRIS), toutes sources du classeur confondues. Chaque indicateur indique sa source et son année.
B5: DÉMOGRAPHIE | E5: EMPLOI ET FORMATION | H5: REVENUS ET PRESTATIONS | K5: LOGEMENT
B7: Population, densité, âges, sexe, nationalité, ménages et familles (monoparentales, nombreuses). | E7: Activité, emploi, chômage, diplômes de la population non scolarisée et demandeurs d'emploi. | H7: Revenus et pauvreté (Filosofi 2021, valeurs figées), allocataires CAF, RSA, AAH et complémentaire santé solidaire (CNAM). | K7: Parc, vacance, typologie, statut d'occupation, logements sociaux, ancienneté et suroccupation.
B8: Habitants | C8: =SUM('POP 2023'!$D$3:$D$40) | E8: Actifs (15-64 ans) | F8: =SUM('ACT RES 2023'!$P$3:$P$40) | H8: Niveau de vie médian | I8: 16080 | K8: Logements | L8: =SUM('LOG 2023'!$D$3:$D$40)
B9: RP 2023 · onglet POP 2023 | E9: RP 2023 · onglet ACT RES 2023 | H9: Filosofi 2021 · valeur figée · Roubaix | K9: RP 2023 · onglet LOG 2023
B10: Habitants au km² | C10: =IFERROR((SUM('POP 2023'!$D$3:$D$40))/(SUM('POP 2023'!$BL$3:$BL$40)),"") | E10: Taux d'emploi (15-64 ans) | F10: =IFERROR((SUM('ACT RES 2023'!$AB$3:$AB$40))/(SUM('ACT RES 2023'!$D$3:$D$40)),"") | H10: Taux de pauvreté (seuil de 60 % du niveau de vie médian) | I10: 47.4 | K10: Résidences principales | L10: =SUM('LOG 2023'!$E$3:$E$40)
B11: RP 2023 · onglet POP 2023 | E11: RP 2023 · onglet ACT RES 2023 | H11: Filosofi 2021 · valeur figée · Roubaix | K11: RP 2023 · onglet LOG 2023
B12: Moins de 20 ans | C12: =IFERROR((SUM('POP 2023'!$P$3:$P$40))/(SUM('POP 2023'!$D$3:$D$40)),"") | E12: Taux de chômage (15-64 ans) | F12: =IFERROR((SUM('ACT RES 2023'!$AN$3:$AN$40))/(SUM('ACT RES 2023'!$P$3:$P$40)),"") | H12: Allocataires CAF | I12: =SUM('CAF 2024'!$D$3:$D$40) | K12: Logements vacants | L12: =IFERROR((SUM('LOG 2023'!$G$3:$G$40))/(SUM('LOG 2023'!$D$3:$D$40)),"")
B13: RP 2023 · onglet POP 2023 | E13: RP 2023 · onglet ACT RES 2023 | H13: CAF 2024 · onglet CAF 2024 | K13: RP 2023 · onglet LOG 2023
B14: 65 ans ou plus | C14: =IFERROR((SUM('POP 2023'!$R$3:$R$40))/(SUM('POP 2023'!$D$3:$D$40)),"") | E14: Taux de chômage des 15-24 ans | F14: =IFERROR((SUM('ACT RES 2023'!$AO$3:$AO$40))/(SUM('ACT RES 2023'!$Q$3:$Q$40)),"") | H14: Population couverte par la CAF | I14: =IFERROR((SUM('CAF 2024'!$E$3:$E$40))/(SUM('CAF 2024'!$Z$3:$Z$40)),"") | K14: Maisons | L14: =IFERROR((SUM('LOG 2023'!$H$3:$H$40))/(SUM('LOG 2023'!$D$3:$D$40)),"")
B15: RP 2023 · onglet POP 2023 | E15: RP 2023 · onglet ACT RES 2023 | H15: CAF 2024 · onglet CAF 2024 | K15: RP 2023 · onglet LOG 2023
B16: Femmes | C16: =IFERROR((SUM('POP 2023'!$X$3:$X$40))/(SUM('POP 2023'!$D$3:$D$40)),"") | E16: Salariés en CDI ou fonction publique | F16: =IFERROR((SUM('ACT RES 2023'!$BV$3:$BV$40))/(SUM('ACT RES 2023'!$BH$3:$BH$40)),"") | H16: Allocataires CAF au RSA socle | I16: =IFERROR((SUM('CAF 2024'!$X$3:$X$40))/(SUM('CAF 2024'!$D$3:$D$40)),"") | K16: Propriétaires occupants | L16: =IFERROR((SUM('LOG 2023'!$AH$3:$AH$40))/(SUM('LOG 2023'!$E$3:$E$40)),"")
B17: RP 2023 · onglet POP 2023 | E17: RP 2023 · onglet ACT RES 2023 | H17: CAF 2024 · onglet CAF 2024 | K17: RP 2023 · onglet LOG 2023
B18: Étrangers | C18: =IFERROR((SUM('POP 2023'!$BE$3:$BE$40))/(SUM('POP 2023'!$D$3:$D$40)),"") | E18: Sans diplôme ou CEP (15 ans ou plus non scolarisés) | F18: =IFERROR((SUM('DIP FORMATION 2023'!$S$3:$S$40))/(SUM('DIP FORMATION 2023'!$R$3:$R$40)),"") | H18: Allocataires CAF mono-parents | I18: =IFERROR((SUM('CAF 2024'!$G$3:$G$40))/(SUM('CAF 2024'!$D$3:$D$40)),"") | K18: Locataires HLM | L18: =IFERROR((SUM('LOG 2023'!$AJ$3:$AJ$40))/(SUM('LOG 2023'!$E$3:$E$40)),"")
B19: RP 2023 · onglet POP 2023 | E19: RP 2023 · onglet DIP FORMATION 2023 | H19: CAF 2024 · onglet CAF 2024 | K19: RP 2023 · onglet LOG 2023
B20: Immigrés | C20: =IFERROR((SUM('POP 2023'!$BF$3:$BF$40))/(SUM('POP 2023'!$D$3:$D$40)),"") | E20: Diplômés du supérieur (15 ans ou plus non scolarisés) | F20: =IFERROR((SUM('DIP FORMATION 2023'!$W$3:$W$40)+SUM('DIP FORMATION 2023'!$X$3:$X$40)+SUM('DIP FORMATION 2023'!$Y$3:$Y$40))/(SUM('DIP FORMATION 2023'!$R$3:$R$40)),"") | H20: Allocataires de l'AAH | I20: =SUM('CAF 2024'!$V$3:$V$40) | K20: Résidences en suroccupation | L20: =IFERROR((SUM('LOG 2023'!$AY$3:$AY$40)+SUM('LOG 2023'!$AZ$3:$AZ$40))/(SUM('LOG 2023'!$E$3:$E$40)),"")
B21: RP 2023 · onglet POP 2023 | E21: RP 2023 · onglet DIP FORMATION 2023 | H21: CAF 2024 · onglet CAF 2024 | K21: RP 2023 · onglet LOG 2023
B22: Enfants de 0 à 17 ans | C22: =SUM('PETITE ENFANCE 2022'!$V$3:$V$40) | E22: Demandeurs d'emploi (cat. ABC) | F22: =SUM('DEFM 2024'!$G$3:$G$40) | H22: Bénéficiaires de la C2S non participative | I22: =IFERROR((SUM('CNAM 2025'!$M$3:$M$40))/(SUM('CNAM 2025'!$D$3:$D$40)),"") | K22: Ménages avec au moins une voiture | L22: =IFERROR((SUM('LOG 2023'!$AR$3:$AR$40))/(SUM('LOG 2023'!$AB$3:$AB$40)),"")
B23: RP (fichier détail) 2022 · onglet PETITE ENFANCE 2022 | E23: France Travail 2024 · onglet DEFM 2024 | H23: CNAM 2025 · onglet CNAM 2025 | K23: RP 2023 · onglet LOG 2023
B24: Ménages | C24: =SUM('COU FAM 2023'!$D$3:$D$40) | E24: Demandeurs ABC de moins de 26 ans | F24: =IFERROR((SUM('DEFM 2024'!$L$3:$L$40))/(SUM('DEFM 2024'!$G$3:$G$40)),"") | H24: Bénéficiaires de la C2S participative | I24: =IFERROR((SUM('CNAM 2025'!$U$3:$U$40))/(SUM('CNAM 2025'!$D$3:$D$40)),"") | K24: Logements sociaux (RPLS) | L24: =SUM('RPLS 2025'!$D$3:$D$40)
B25: RP 2023 · onglet COU FAM 2023 | E25: France Travail 2024 · onglet DEFM 2024 | H25: CNAM 2025 · onglet CNAM 2025 | K25: RPLS 2025 · onglet RPLS 2025
B26: Taille moyenne des ménages | C26: =IFERROR((SUM('COU FAM 2023'!$M$3:$M$40))/(SUM('COU FAM 2023'!$D$3:$D$40)),"") | E26: Demandeurs ABC depuis 2 ans ou plus | F26: =IFERROR((SUM('DEFM 2024'!$AR$3:$AR$40))/(SUM('DEFM 2024'!$G$3:$G$40)),"")
B27: RP 2023 · onglet COU FAM 2023 | E27: France Travail 2024 · onglet DEFM 2024
B28: Familles monoparentales | C28: =IFERROR((SUM('COU FAM 2023'!$AT$3:$AT$40))/(SUM('COU FAM 2023'!$AR$3:$AR$40)),"")
B29: RP 2023 · onglet COU FAM 2023
B30: Familles nombreuses (3 enfants ou plus) | C30: =IFERROR((SUM('COU FAM 2023'!$AY$3:$AY$40)+SUM('COU FAM 2023'!$AZ$3:$AZ$40))/(SUM('COU FAM 2023'!$AR$3:$AR$40)),"")
B31: RP 2023 · onglet COU FAM 2023
B33: À savoir
B34: • Les parts et taux sont recalculés sur Roubaix entière (somme des IRIS), pas en moyenne des IRIS.
B35: • Les valeurs sont des formules : elles suivent les onglets du classeur. Cliquer sur une source ouvre l'onglet.
B36: • Revenus Filosofi 2021 (Roubaix) : valeurs figées pour comparaison, les onglets Filosofi étant retirés (données trop anciennes).

Sheet Detail calcul
A1: Base MAS - INSEE mise à jour 2023
A2: Details sur les calculs de la population | B2: Details sur les calculs du logement | C2: Details sur les calculs des activités des résidents | D2: Details sur les calculs des couples-familles-ménages | E2: Details sur les calculs des diplômes et formations | F2: Details sur les calculs des demandeurs d'emploi | G2: Details sur les calculs des bénéficiaires de la CAF | H2: Details sur les calculs des bénéficiaires de la CNAM
A3: Superficie en hectares (POP) -> Superficie en km² * 100 | B3: Superficie en hectares (LOG) -> Superficie en km² * 100 | C3: Population (ACT RES) -> Population (feuille POP) | D3: Part des ménages avec famille(s) (%) -> Ménages avec famille(s) * 100 / Ménages | E3: Part pop 15 ans et plus non scol sans dip ou CEP max (%) -> Pop 15 ans ou plus non scol. Sans diplôme ou CEP * 100 / Pop 15 ans ou plus non scolarisée | F3: Population (DEFM) -> Population (feuille POP) | G3: Population (CAF) -> Population (feuille POP) | H3: Part de la population couverte bénéficiaire de la C2S non participative (%) -> Population couverte bénéficiaire de la C2S non participative (ex-CMUC) * 100 / Population couverte bénéficiaire du régime général (non calculé : variable absente de ce millésime)
A4: Densité de population en hab/km² -> Population / Superficie en km² | B4: Densité de logements au km² -> Logements / Superficie en km² | C4: Part de la population en âge de travailler (%) -> Pop 15-64 ans * 100 / Population (ACT RES) | D4: Part des ménages famille couple avec enfant(s) (%) -> Mén fam princ Couple avec enfant(s) * 100 / Ménages | E4: Pop 15 ans ou plus non scol dipl Ens Sup -> Pop 15 ans ou plus non scol. Enseignement sup de niveau bac + 2 + Pop 15 ans ou plus non scol. Enseignement sup de niveau bac + 3 ou 4 + Pop 15 ans ou plus non scol. Enseignement sup de niveau bac + 5 ou plus | F4: Part des DEFM dans la population totale (%) -> DEFM * 100 / Population (DEFM) | G4: Part de la population couverte par une allocation CAF (%) -> Personnes couvertes * 100 / Population (CAF) | H4: Part des bénéficiaires de la C2S non participative de moins de 18 ans (%) -> Bénéficiaires de la C2S non participative (ex-CMUC) de moins de 18 ans * 100 / Population couverte bénéficiaire de la C2S non participative (ex-CMUC) (non calculé : variable absente de ce millésime)
A5: Part de la population de l’IRIS dans la population totale (%) -> Population * 100 / Population (total Roubaix) | B5: Densité de logements par hectare -> Logements / Superficie en hectares (LOG) | C5: Part de la population active dans la population en âge de travailler (%) -> Actifs 15-64 ans * 100 / Pop 15-64 ans | D5: Part des familles couple avec enfant(s) (%) -> Fam Couple avec enfant(s) * 100 / Familles | E5: Part pop 15 ans et plus non scol dipl Ens Sup (%) -> Pop 15 ans ou plus non scol dipl Ens Sup * 100 / Pop 15 ans ou plus non scolarisée | F5: Part des DEFM hommes (%) -> DEFM hommes * 100 / Population (DEFM) | G5: Part des allocataires mono-parent (%) -> Allocataires mono-parent * 100 / Nombre total d'allocataires | H5: Part des moins de 18 ans bénéficiaires de la C2S non participative(%) -> Bénéficiaires de la C2S non participative (ex-CMUC) de moins de 18 ans * 100 / Bénéficiaires du régime général de moins de 18 ans (non calculé : variable absente de ce millésime)
A6: Densité d’habitants à l’hectare -> Population / Superficie en hectares (POP) | B6: Part des logements vacants (%) -> Logements vacants * 100 / Logements | C6: Part des actifs 15-24 ans (%) -> Actifs 15-24 ans * 100 / Pop 15-24 ans | D6: Part de familles monoparentales (%) -> Fam Monoparentales * 100 / Familles | F6: Part des DEFM femmes (%) -> DEFM femmes * 100 / Population (DEFM) | G6: Part des allocataires percevant l’APL (%) -> Allocataires percevant l’Aide Personnalisée au Logement (Métropole) * 100 / Nombre total d'allocataires | H6: Part de la population couverte bénéficiaire de la C2S participative (%) -> Population couverte bénéficiaire de la C2S participative (ex-ACS) * 100 / Population couverte bénéficiaire du régime général (non calculé : variable absente de ce millésime)
A7: Population de plus de 60 ans -> Pop 60-74 ans + Pop 75 ans ou plus (non calculé : variable absente de ce millésime) | B7: Part des logements individuels (%) -> Maisons * 100 / Logements | C7: Taux d’emploi des 15-64 ans (%) -> Actifs occupés 15-64 ans * 100 / Pop 15-64 ans | D7: Nombre de familles nombreuses -> Fam 3 enfants moins 25 ans + Fam 4 enfants ou plus moins 25 ans | F7: Part des DEFM catégorie ABC (tenus de faire une recherche d'emploi active) -> DEFM catégories ABC * 100 / DEFM | G7: Part des allocataires percevant l’AAH (%) -> Allocataires percevant l’Allocation Adulte Handicapé * 100 / Nombre total d'allocataires | H7: Part des bénéficiaires de la C2S participative de moins de 18 ans (%) -> Bénéficiaires de la C2S participative (ex-ACS) de moins de 18 ans * 100 / Population couverte bénéficiaire de la C2S participative (ex-ACS) (non calculé : variable absente de ce millésime)
A8: Part de la population de plus de 60 ans (%) parmi la population iris -> Population de plus de 60 ans * 100 / Population (non calculé : variable absente de ce millésime) | B8: Nombre de RP de petite typologie -> Rés princ 1 pièce + Rés princ 2 pièces | C8: Taux d’emploi des 15-24 ans (%) -> Actifs occupés 15-24 ans * 100 / Pop 15-24 ans | D8: Part de familles nombreuses (%) -> Nombre de familles nombreuses * 100 / Familles | F8: Part des DEFM ABC de moins de 26 ans (%) -> DEFM catégories ABC moins de 26 ans * 100 / DEFM catégories ABC | G8: Part des allocataires bénéficiant du RSA socle (%) -> Allocataires percevant le RSA socle * 100 / Nombre total d'allocataires | H8: Part des moins de 18 ans bénéficiaires de la C2S participative (%) -> Bénéficiaires de la C2S participative (ex-ACS) de moins de 18 ans * 100 / Bénéficiaires du régime général de moins de 18 ans (non calculé : variable absente de ce millésime)
A9: Part de la population de moins de 20 ans (%) parmi la population iris -> Pop 0-19 ans * 100 / Population | B9: Part des RP de petite typologie (%) -> Nombre de RP de petite typologie * 100 / Résidences principales | C9: Taux de chômage dans la pop active (%) -> Chômeurs 15-64 ans * 100 / Actifs 15-64 ans | F9: Part des DEFM ABC de niveau ≤ au BAC dans les DEFM ABC (%) -> (DEFM catégories ABC de niveau de formation inférieur au CAP-BEP + DEFM catégories ABC de niveau de formation CAP-BEP + DEFM catégories ABC de niveau de formation BAC) * 100 / DEFM catégories ABC
A10: Indice de jeunesse -> Pop 0-19 ans / (Pop 60-74 ans + Pop 75 ans ou plus) (non calculé : variable absente de ce millésime) | B10: Nombre de RP de grande typologie -> Rés princ 3 pièces + Rés princ 4 pièces + Rés princ 5 pièces ou plus | C10: Taux de chômage chez les 15-24 ans dans la pop active (%) -> Chômeurs 15-24 ans * 100 / Actifs 15-24 ans | F10: Part des DEFM ABC au chômage depuis plus de 2 ans parmi les DEFM ABC (%) -> DEFM catégories ABC d'ancienneté au chômage d'au moins 2 ans * 100 / DEFM catégories ABC
A11: Indice de vieillissement -> Pop 65 ans ou plus / Pop 0-19 ans | B11: Part des RP de grande typologie (%) -> Nombre de RP de grande typologie * 100 / Résidences principales | C11: Part salariés chez les actifs occupés (%) -> Salariés 15 ans ou plus * 100 / Actifs occupés 15 ans ou plus | F11: Part des DEFM ABC au chômage depuis plus de 2 ans dans l'ensemble des chômeurs inscrits à PE (%) -> DEFM catégories ABC d'ancienneté au chômage d'au moins 2 ans * 100 / DEFM
A12: Part de la population étrangère parmi la population iris (%) -> Pop Etrangers * 100 / Population | B12: Part des ménages emménagés depuis moins de 2 ans (%) -> Ménages emménagés moins 2 ans * 100 / Ménages | C12: Part des femmes chez les salariés de 15 ans et plus (%) -> Salariés 15 ans ou plus Femmes * 100 / Salariés 15 ans ou plus | F12: Part des DEFM ABC bénéficiaires du RSA parmi les DEFM ABC (%) -> DEFM catégories ABC bénéficiaires du RSA * 100 / DEFM catégories ABC
A13: Part de la population immigrée parmi la population iris (%) -> Pop Immigrés * 100 / Population | B13: Ménages emménagés moins 10 ans -> Ménages - Ménages emménagés depuis 10 ans ou plus | C13: Part des actifs occupés salariés en CDI ou fonction publique (%) -> Salariés 15 ans ou plus Fonct publ, CDI * 100 / Salariés 15 ans ou plus | F13: Part des DEFM ABC bénéficiaires du RSA parmi l'ensemble des inscrits à PE (%) -> DEFM catégories ABC bénéficiaires du RSA * 100 / DEFM
B14: Part des ménages emménagés depuis moins de 10 ans (%) -> Ménages emménagés moins 10 ans * 100 / Ménages | C14: Part des actifs occupés travaillant dans la commune de résidence (%) -> Actif occ 15 ans ou plus travaille commune résidence * 100 / Actifs occupés 15 ans ou plus
B15: Taille moyenne des ménages -> Pop Ménages / Ménages
B16: Nombre de RP parc privé -> Résidences principales - Rés princ HLM louée vide
B17: Part propriétaire dans les RP parc privé (%) -> Rés princ occupées Propriétaires * 100 / Nombre de RP parc privé
B18: Part propriétaire dans le parc de RP total (%) -> Rés princ occupées Propriétaires * 100 / Résidences principales
B19: Part HLM dans RP totale (%) -> Rés princ HLM louée vide * 100 / Résidences principales
B20: Part HLM dans les RP locataires (%) -> Rés princ HLM louée vide * 100 / Rés princ occupées Locataires
B21: Part des ménages avec parking (%) -> Ménages au moins un parking * 100 / Ménages
B22: Part des ménages avec au moins une voiture (%) -> Ménages au moins une voiture * 100 / Ménages

Sheet POP 2023
A1: Données infra-communales - Population | D1: =SUBTOTAL(9,D3:D40) | E1: =SUBTOTAL(9,E3:E40) | F1: =SUBTOTAL(9,F3:F40) | G1: =SUBTOTAL(9,G3:G40) | H1: =SUBTOTAL(9,H3:H40) | I1: =SUBTOTAL(9,I3:I40) | J1: =SUBTOTAL(9,J3:J40) | K1: =SUBTOTAL(9,K3:K40) | ... BM1: =SUBTOTAL(9,BM3:BM40)
A2: Mairies de quartiers | B2: Grands quartiers | C2: Libellé de l'Iris | D2: Population | E2: Pop 0-2 ans | F2: Pop 3-5 ans | G2: Pop 6-10 ans | H2: Pop 11-17 ans | I2: Pop 18-24 ans | J2: Pop 25-39 ans | K2: Pop 40-54 ans | L2: Pop 55-64 ans | M2: Pop 65-79 ans | N2: Pop 80 ans ou plus | O2: Pop 0-14 ans | P2: Pop 0-19 ans | Q2: Pop 20-64 ans | R2: Pop 65 ans ou plus | S2: Pop Hommes | T2: Pop Hommes 0-14 ans | U2: Pop Hommes 0-19 ans | V2: Pop Hommes 20-64 ans | W2: Pop Hommes 65 ans ou plus | X2: Pop Femmes | Y2: Pop Femmes 0-14 ans | Z2: Pop Femmes 0-19 ans | AA2: Pop Femmes 20-64 ans | AB2: Pop Femmes 65 ans ou plus | AC2: Pop 15 ans ou plus | AD2: Pop 15 ans ou plus Agriculteurs exploitants | AE2: Pop 15 ans ou plus Artisans, Comm., Chefs entr. | AF2: Pop 15 ans ou plus Cadres, Prof. intel. sup. | AG2: Pop 15 ans ou plus Prof. intermédiaires | AH2: Pop 15 ans ou plus Employés | AI2: Pop 15 ans ou plus Ouvriers | AJ2: Pop 15 ans ou plus Retraités | AK2: Pop 15 ans ou plus Autres | AL2: Pop 15 ans ou plus Hommes | AM2: Pop 15 ans ou plus Hommes Agriculteurs exploitants | AN2: Pop 15 ans ou plus Hommes Artisans, Comm., Chefs entr. | AO2: Pop 15 ans ou plus Hommes Cadres, Prof. intel. sup. | AP2: Pop 15 ans ou plus Hommes Prof. intermédiaires | AQ2: Pop 15 ans ou plus Hommes Employés | AR2: Pop 15 ans ou plus Hommes Ouvriers | AS2: Pop 15 ans ou plus Hommes Retraités | AT2: Pop 15 ans ou plus Hommes Autres | AU2: Pop 15 ans ou plus Femmes | AV2: Pop 15 ans ou plus Femmes Agriculteurs exploitants | AW2: Pop 15 ans ou plus Femmes Artisans, Comm., Chefs entr. | AX2: Pop 15 ans ou plus Femmes Cadres, Prof. intel. sup. | AY2: Pop 15 ans ou plus Femmes Prof. intermédiaires | AZ2: Pop 15 ans ou plus Femmes Employés | BA2: Pop 15 ans ou plus Femmes Ouvriers | BB2: Pop 15 ans ou plus Femmes Retraités | BC2: Pop 15 ans ou plus Femmes Autres | BD2: Pop Français | BE2: Pop Etrangers | BF2: Pop Immigrés | BG2: Pop ménages | BH2: Pop hors ménages | BI2: Pop 15-24 ans | BJ2: Pop 15-24 ans Hommes | BK2: Pop 15-24 ans Femmes | BL2: Superficie en km² | BM2: Superficie en hectares (POP) | BN2: Densité de population en hab/km² | BO2: Part de la population de l’IRIS dans la population totale (%) | BP2: Densité d’habitants à l’hectare | BQ2: Part de la population de moins de 20 ans (%) parmi la population iris | BR2: Indice de vieillissement | BS2: Part de la population étrangère parmi la population iris (%) | BT2: Part de la population immigrée parmi la population iris (%)
A3: OUEST | B3: FRESNOY MACKELLERIE | C3: Mackellerie | D3: 2501 | E3: 99 | F3: 204 | G3: 235 | H3: 304 | I3: 256 | J3: 540 | K3: 413 | L3: 221 | M3: 173 | N3: 55 | O3: 725 | P3: 914 | Q3: 1358 | R3: 229 | S3: 1280 | T3: 415 | U3: 519 | V3: 647 | W3: 115 | X3: 1221 | Y3: 310 | Z3: 395 | AA3: 711 | AB3: 114 | AC3: 1849 | AD3: 0 | AE3: 36 | AF3: 87 | AG3: 175 | AH3: 370 | AI3: 334 | AJ3: 283 | AK3: 564 | AL3: 869 | AM3: 0 | AN3: 18 | AO3: 50 | AP3: 91 | AQ3: 121 | AR3: 257 | AS3: 137 | AT3: 193 | AU3: 981 | AV3: 0 | AW3: 18 | AX3: 38 | AY3: 84 | AZ3: 249 | BA3: 76 | BB3: 146 | BC3: 371 | BD3: 2113 | BE3: 388 | BF3: 502 | BG3: 2460 | BH3: 41 | BI3: 373 | BJ3: 166 | BK3: 207 | BL3: 0.32 | BM3: 31.63 | BN3: 7906.73 | BO3: 2.5 | BP3: 79.07 | BQ3: 36.6 | BR3: 0.25 | BS3: 15.5 | BT3: 20.1
A4: OUEST | B4: ARMENTIERES | C4: Fresnoy | D4: 4280 | E4: 112 | F4: 174 | G4: 338 | H4: 447 | I4: 784 | J4: 834 | K4: 781 | L4: 403 | M4: 330 | N4: 77 | O4: 877 | P4: 1313 | Q4: 2560 | R4: 407 | S4: 2144 | T4: 496 | U4: 691 | V4: 1267 | W4: 185 | X4: 2135 | Y4: 381 | Z4: 622 | AA4: 1293 | AB4: 221 | AC4: 3619 | AD4: 0 | AE4: 71 | AF4: 308 | AG4: 441 | AH4: 614 | AI4: 458 | AJ4: 467 | AK4: 1260 | AL4: 1745 | AM4: 0 | AN4: 46 | AO4: 205 | AP4: 225 | AQ4: 244 | AR4: 346 | AS4: 200 | AT4: 479 | AU4: 1875 | AV4: 0 | AW4: 25 | AX4: 104 | AY4: 216 | AZ4: 370 | BA4: 111 | BB4: 268 | BC4: 781 | BD4: 3567 | BE4: 713 | BF4: 892 | BG4: 4279 | BH4: 0 | BI4: 978 | BJ4: 423 | BK4: 555 | BL4: 0.53 | BM4: 52.75 | BN4: 8113.17 | BO4: 4.4 | BP4: 81.13 | BQ4: 30.7 | BR4: 0.31 | BS4: 16.7 | BT4: 20.8
A5: NORD | B5: FOSSE AUX CHENES | C5: Fosse aux Chênes | D5: 2843 | E5: 98 | F5: 189 | G5: 181 | H5: 312 | I5: 332 | J5: 499 | K5: 585 | L5: 276 | M5: 273 | N5: 98 | O5: 653 | P5: 869 | Q5: 1604 | R5: 370 | S5: 1413 | T5: 356 | U5: 456 | V5: 786 | W5: 172 | X5: 1430 | Y5: 296 | Z5: 413 | AA5: 818 | AB5: 199 | AC5: 1948 | AD5: 0 | AE5: 56 | AF5: 52 | AG5: 93 | AH5: 259 | AI5: 307 | AJ5: 403 | AK5: 777 | AL5: 922 | AM5: 0 | AN5: 46 | AO5: 19 | AP5: 38 | AQ5: 54 | AR5: 234 | AS5: 185 | AT5: 346 | AU5: 1026 | AV5: 0 | AW5: 11 | AX5: 33 | AY5: 55 | AZ5: 205 | BA5: 74 | BB5: 218 | BC5: 431 | BD5: 2135 | BE5: 708 | BF5: 834 | BG5: 2703 | BH5: 140 | BI5: 460 | BJ5: 214 | BK5: 246 | BL5: 0.41 | BM5: 40.66 | BN5: 6992.38 | BO5: 2.9 | BP5: 69.93 | BQ5: 30.5 | BR5: 0.43 | BS5: 24.9 | BT5: 29.3
A6: NORD | B6: ALMA GARE | C6: Alma Sud | D6: 1529 | E6: 64 | F6: 124 | G6: 173 | H6: 172 | I6: 217 | J6: 273 | K6: 248 | L6: 161 | M6: 92 | N6: 4 | O6: 452 | P6: 602 | Q6: 830 | R6: 96 | S6: 777 | T6: 245 | U6: 318 | V6: 413 | W6: 47 | X6: 751 | Y6: 207 | Z6: 284 | AA6: 417 | AB6: 49 | AC6: 1051 | AD6: 0 | AE6: 21 | AF6: 15 | AG6: 26 | AH6: 127 | AI6: 237 | AJ6: 111 | AK6: 514 | AL6: 518 | AM6: 0 | AN6: 21 | AO6: 5 | AP6: 15 | AQ6: 32 | AR6: 180 | AS6: 52 | AT6: 212 | AU6: 534 | AV6: 0 | AW6: 0 | AX6: 11 | AY6: 11 | AZ6: 94 | BA6: 58 | BB6: 59 | BC6: 301 | BD6: 974 | BE6: 554 | BF6: 559 | BG6: 1529 | BH6: 0 | BI6: 299 | BJ6: 153 | BK6: 146 | BL6: 0.09 | BM6: 9.35 | BN6: 16355.06 | BO6: 1.6 | BP6: 163.49 | BQ6: 39.4 | BR6: 0.16 | BS6: 36.3 | BT6: 36.6
A7: NORD | B7: ALMA GARE | C7: Alma Nord | D7: 1613 | E7: 45 | F7: 110 | G7: 161 | H7: 248 | I7: 171 | J7: 280 | K7: 300 | L7: 129 | M7: 145 | N7: 25 | O7: 441 | P7: 611 | Q7: 832 | R7: 169 | S7: 799 | T7: 250 | U7: 310 | V7: 399 | W7: 90 | X7: 813 | Y7: 191 | Z7: 301 | AA7: 432 | AB7: 79 | AC7: 1010 | AD7: 0 | AE7: 18 | AF7: 25 | AG7: 60 | AH7: 100 | AI7: 180 | AJ7: 171 | AK7: 456 | AL7: 470 | AM7: 0 | AN7: 18 | AO7: 8 | AP7: 22 | AQ7: 20 | AR7: 137 | AS7: 96 | AT7: 168 | AU7: 540 | AV7: 0 | AW7: 0 | AX7: 17 | AY7: 38 | AZ7: 80 | BA7: 43 | BB7: 75 | BC7: 288 | BD7: 1190 | BE7: 423 | BF7: 503 | BG7: 1613 | BH7: 0 | BI7: 294 | BJ7: 112 | BK7: 182 | BL7: 0.42 | BM7: 41.78 | BN7: 3860.19 | BO7: 1.6 | BP7: 38.6 | BQ7: 37.9 | BR7: 0.28 | BS7: 26.2 | BT7: 31.2
A8: NORD | B8: ENTREPONT | C8: Entrepont-Cartigny | D8: 2372 | E8: 60 | F8: 145 | G8: 231 | H8: 305 | I8: 233 | J8: 427 | K8: 461 | L8: 200 | M8: 260 | N8: 49 | O8: 617 | P8: 834 | Q8: 1229 | R8: 309 | S8: 1190 | T8: 323 | U8: 449 | V8: 593 | W8: 148 | X8: 1182 | Y8: 294 | Z8: 385 | AA8: 636 | AB8: 161 | AC8: 1813 | AD8: 0 | AE8: 40 | AF8: 37 | AG8: 138 | AH8: 299 | AI8: 331 | AJ8: 319 | AK8: 651 | AL8: 899 | AM8: 0 | AN8: 31 | AO8: 12 | AP8: 63 | AQ8: 68 | AR8: 267 | AS8: 162 | AT8: 296 | AU8: 913 | AV8: 0 | AW8: 8 | AX8: 24 | AY8: 75 | AZ8: 231 | BA8: 64 | BB8: 156 | BC8: 355 | BD8: 1783 | BE8: 589 | BF8: 597 | BG8: 2364 | BH8: 8 | BI8: 357 | BJ8: 182 | BK8: 175 | BL8: 0.85 | BM8: 84.99 | BN8: 2790.47 | BO8: 2.4 | BP8: 27.9 | BQ8: 35.2 | BR8: 0.37 | BS8: 24.8 | BT8: 25.2
A9: NORD | B9: HUTIN - ORAN - CARTIGNY | C9: Hutin-Oran | D9: 2166 | E9: 76 | F9: 144 | G9: 166 | H9: 310 | I9: 196 | J9: 351 | K9: 441 | L9: 141 | M9: 269 | N9: 72 | O9: 584 | P9: 768 | Q9: 1057 | R9: 342 | S9: 1041 | T9: 301 | U9: 386 | V9: 510 | W9: 145 | X9: 1126 | Y9: 283 | Z9: 382 | AA9: 547 | AB9: 197 | AC9: 1543 | AD9: 0 | AE9: 11 | AF9: 42 | AG9: 158 | AH9: 190 | AI9: 286 | AJ9: 363 | AK9: 493 | AL9: 725 | AM9: 0 | AN9: 10 | AO9: 7 | AP9: 83 | AQ9: 61 | AR9: 214 | AS9: 161 | AT9: 188 | AU9: 818 | AV9: 0 | AW9: 1 | AX9: 35 | AY9: 75 | AZ9: 129 | BA9: 72 | BB9: 201 | BC9: 305 | BD9: 1734 | BE9: 432 | BF9: 526 | BG9: 2166 | BH9: 0 | BI9: 308 | BJ9: 139 | BK9: 169 | BL9: 0.42 | BM9: 41.76 | BN9: 5187.63 | BO9: 2.2 | BP9: 51.88 | BQ9: 35.4 | BR9: 0.45 | BS9: 19.9 | BT9: 24.3
A10: NORD | B10: CUL DE FOUR | C10: Cul de Four | D10: 3471 | E10: 108 | F10: 274 | G10: 298 | H10: 525 | I10: 429 | J10: 575 | K10: 638 | L10: 294 | M10: 252 | N10: 78 | O10: 991 | P10: 1355 | Q10: 1785 | R10: 331 | S10: 1791 | T10: 536 | U10: 729 | V10: 897 | W10: 165 | X10: 1680 | Y10: 455 | Z10: 626 | AA10: 888 | AB10: 166 | AC10: 2428 | AD10: 0 | AE10: 36 | AF10: 38 | AG10: 134 | AH10: 314 | AI10: 517 | AJ10: 329 | AK10: 1059 | AL10: 1233 | AM10: 0 | AN10: 36 | AO10: 32 | AP10: 53 | AQ10: 122 | AR10: 418 | AS10: 132 | AT10: 440 | AU10: 1195 | AV10: 0 | AW10: 0 | AX10: 6 | AY10: 81 | AZ10: 192 | BA10: 99 | BB10: 198 | BC10: 619 | BD10: 2556 | BE10: 915 | BF10: 945 | BG10: 3471 | BH10: 0 | BI10: 643 | BJ10: 356 | BK10: 287 | BL10: 0.56 | BM10: 56.3 | BN10: 6165.13 | BO10: 3.5 | BP10: 61.65 | BQ10: 39 | BR10: 0.24 | BS10: 26.4 | BT10: 27.2
A11: NORD | B11: HOMMELET | C11: Hommelet Nord | D11: 2308 | E11: 68 | F11: 180 | G11: 219 | H11: 297 | I11: 260 | J11: 453 | K11: 410 | L11: 180 | M11: 228 | N11: 14 | O11: 635 | P11: 851 | Q11: 1215 | R11: 242 | S11: 1130 | T11: 281 | U11: 374 | V11: 636 | W11: 121 | X11: 1177 | Y11: 354 | Z11: 477 | AA11: 579 | AB11: 121 | AC11: 1761 | AD11: 0 | AE11: 42 | AF11: 105 | AG11: 137 | AH11: 196 | AI11: 337 | AJ11: 280 | AK11: 665 | AL11: 885 | AM11: 0 | AN11: 38 | AO11: 54 | AP11: 97 | AQ11: 51 | AR11: 264 | AS11: 138 | AT11: 244 | AU11: 876 | AV11: 0 | AW11: 4 | AX11: 50 | AY11: 40 | AZ11: 145 | BA11: 73 | BB11: 143 | BC11: 420 | BD11: 1735 | BE11: 573 | BF11: 608 | BG11: 2308 | BH11: 0 | BI11: 388 | BJ11: 165 | BK11: 223 | BL11: 0.18 | BM11: 18.34 | BN11: 12585.26 | BO11: 2.3 | BP11: 125.84 | BQ11: 36.9 | BR11: 0.28 | BS11: 24.8 | BT11: 26.3
A12: NORD | B12: HOMMELET | C12: Hommelet Centre | D12: 2774 | E12: 69 | F12: 204 | G12: 247 | H12: 436 | I12: 267 | J12: 363 | K12: 550 | L12: 270 | M12: 262 | N12: 106 | O12: 746 | P12: 1045 | Q12: 1361 | R12: 369 | S12: 1300 | T12: 367 | U12: 540 | V12: 614 | W12: 145 | X12: 1474 | Y12: 378 | Z12: 505 | AA12: 747 | AB12: 223 | AC12: 2141 | AD12: 0 | AE12: 53 | AF12: 45 | AG12: 121 | AH12: 313 | AI12: 374 | AJ12: 405 | AK12: 830 | AL12: 1000 | AM12: 0 | AN12: 36 | AO12: 26 | AP12: 68 | AQ12: 118 | AR12: 267 | AS12: 172 | AT12: 313 | AU12: 1141 | AV12: 0 | AW12: 17 | AX12: 20 | AY12: 53 | AZ12: 195 | BA12: 107 | BB12: 233 | BC12: 517 | BD12: 2086 | BE12: 688 | BF12: 784 | BG12: 2701 | BH12: 73 | BI12: 477 | BJ12: 249 | BK12: 228 | BL12: 0.28 | BM12: 28.27 | BN12: 9811.37 | BO12: 2.8 | BP12: 98.12 | BQ12: 37.7 | BR12: 0.35 | BS12: 24.8 | BT12: 28.3
A13: NORD | B13: HOMMELET | C13: Hommelet Sud | D13: 2353 | E13: 56 | F13: 132 | G13: 197 | H13: 302 | I13: 302 | J13: 428 | K13: 474 | L13: 217 | M13: 182 | N13: 63 | O13: 533 | P13: 777 | Q13: 1332 | R13: 245 | S13: 1229 | T13: 272 | U13: 385 | V13: 728 | W13: 116 | X13: 1124 | Y13: 261 | Z13: 391 | AA13: 604 | AB13: 129 | AC13: 1909 | AD13: 0 | AE13: 38 | AF13: 132 | AG13: 126 | AH13: 273 | AI13: 389 | AJ13: 266 | AK13: 685 | AL13: 986 | AM13: 0 | AN13: 25 | AO13: 85 | AP13: 64 | AQ13: 90 | AR13: 313 | AS13: 125 | AT13: 283 | AU13: 923 | AV13: 0 | AW13: 13 | AX13: 47 | AY13: 61 | AZ13: 182 | BA13: 76 | BB13: 141 | BC13: 402 | BD13: 1736 | BE13: 618 | BF13: 681 | BG13: 2250 | BH13: 103 | BI13: 457 | BJ13: 247 | BK13: 210 | BL13: 0.21 | BM13: 21.15 | BN13: 11129.05 | BO13: 2.4 | BP13: 111.27 | BQ13: 33 | BR13: 0.31 | BS13: 26.2 | BT13: 28.9
A14: OUEST | B14: EPEULE | C14: Épeule Nord | D14: 1947 | E14: 46 | F14: 124 | G14: 198 | H14: 210 | I14: 204 | J14: 313 | K14: 369 | L14: 249 | M14: 194 | N14: 40 | O14: 475 | P14: 660 | Q14: 1054 | R14: 233 | S14: 964 | T14: 230 | U14: 325 | V14: 510 | W14: 129 | X14: 983 | Y14: 245 | Z14: 335 | AA14: 544 | AB14: 104 | AC14: 1347 | AD14: 0 | AE14: 31 | AF14: 15 | AG14: 87 | AH14: 198 | AI14: 256 | AJ14: 214 | AK14: 546 | AL14: 692 | AM14: 0 | AN14: 28 | AO14: 8 | AP14: 35 | AQ14: 80 | AR14: 206 | AS14: 123 | AT14: 212 | AU14: 656 | AV14: 0 | AW14: 3 | AX14: 7 | AY14: 52 | AZ14: 119 | BA14: 50 | BB14: 91 | BC14: 333 | BD14: 1254 | BE14: 694 | BF14: 685 | BG14: 1947 | BH14: 0 | BI14: 308 | BJ14: 158 | BK14: 150 | BL14: 0.15 | BM14: 15.31 | BN14: 12719.86 | BO14: 2 | BP14: 127.18 | BQ14: 33.9 | BR14: 0.35 | BS14: 35.6 | BT14: 35.2
... A40: SUD | B40: HAUTS CHAMPS/PETITES HAIES | C40: Hauts Champs | D40: 2227 | E40: 70 | F40: 156 | G40: 185 | H40: 204 | I40: 289 | J40: 424 | K40: 407 | L40: 227 | M40: 209 | N40: 57 | O40: 535 | P40: 705 | Q40: 1257 | R40: 266 | S40: 1045 | T40: 283 | U40: 361 | V40: 595 | W40: 89 | X40: 1183 | Y40: 252 | Z40: 344 | AA40: 662 | AB40: 177 | AC40: 1649 | AD40: 0 | AE40: 49 | AF40: 21 | AG40: 108 | AH40: 346 | AI40: 347 | AJ40: 312 | AK40: 466 | AL40: 760 | AM40: 0 | AN40: 40 | AO40: 8 | AP40: 35 | AQ40: 124 | AR40: 291 | AS40: 106 | AT40: 157 | AU40: 889 | AV40: 0 | AW40: 10 | AX40: 13 | AY40: 74 | AZ40: 222 | BA40: 56 | BB40: 206 | BC40: 309 | BD40: 1804 | BE40: 423 | BF40: 490 | BG40: 2171 | BH40: 56 | BI40: 368 | BJ40: 195 | BK40: 173 | BL40: 0.31 | BM40: 31.34 | BN40: 7107.07 | BO40: 2.3 | BP40: 71.07 | BQ40: 31.6 | BR40: 0.38 | BS40: 19 | BT40: 22

Sheet ACT RES 2023
A1: Données infra-communales - Activité des résidents | D1: =SUBTOTAL(9,D3:D40) | E1: =SUBTOTAL(9,E3:E40) | F1: =SUBTOTAL(9,F3:F40) | G1: =SUBTOTAL(9,G3:G40) | H1: =SUBTOTAL(9,H3:H40) | I1: =SUBTOTAL(9,I3:I40) | J1: =SUBTOTAL(9,J3:J40) | K1: =SUBTOTAL(9,K3:K40) | ... CJ1: =SUBTOTAL(9,CJ3:CJ40)
A2: Mairies de quartiers | B2: Grands quartiers | C2: Libellé de l'Iris | D2: Pop 15-64 ans | E2: Pop 15-24 ans | F2: Pop 25-54 ans | G2: Pop 55-64 ans | H2: Pop 15-64 ans Hommes | I2: Pop 15-24 ans Hommes | J2: Pop 25-54 ans Hommes | K2: Pop 55-64 ans Hommes | L2: Pop 15-64 ans Femmes | M2: Pop 15-24 ans Femmes | N2: Pop 25-54 ans Femmes | O2: Pop 55-64 ans Femmes | P2: Actifs 15-64 ans | Q2: Actifs 15-24 ans | R2: Actifs 25-54 ans | S2: Actifs 55-64 ans | T2: Actifs 15-64 ans Hommes | U2: Actifs 15-24 ans Hommes | V2: Actifs 25-54 ans Hommes | W2: Actifs 55-64 ans Hommes | X2: Actifs 15-64 ans Femmes | Y2: Actifs 15-24 ans Femmes | Z2: Actifs 25-54 ans Femmes | AA2: Actifs 55-64 ans Femmes | AB2: Actifs occupés 15-64 ans | AC2: Actifs occupés 15-24 ans | AD2: Actifs occupés 25-54 ans | AE2: Actifs occupés 55-64 ans | AF2: Actifs occupés 15-64 ans Hommes | AG2: Actifs occupés 15-24 ans Hommes | AH2: Actifs occupés 25-54 ans Hommes | AI2: Actifs occupés 55-64 ans Hommes | AJ2: Actifs occupés 15-64 ans Femmes | AK2: Actifs occupés 15-24 ans Femmes | AL2: Actifs occupés 25-54 ans Femmes | AM2: Actifs occupés 55-64 ans Femmes | AN2: Chômeurs 15-64 ans | AO2: Chômeurs 15-24 ans | AP2: Chômeurs 25-54 ans | AQ2: Chômeurs 55-64 ans | AR2: Inactifs 15-64 ans | AS2: Elèv. Etud. Stag. non rémunérés 15-64 ans | AT2: Retraités Préretraités 15-64 ans | AU2: Autres inactifs 15-64 ans | AV2: Actifs 15-64 ans Agriculteurs exploitants | AW2: Actifs 15-64 ans Artisans, Comm., Chefs entr. | AX2: Actifs 15-64 ans Cadres, Prof. intel. sup. | AY2: Actifs 15-64 ans Prof. intermédiaires | AZ2: Actifs 15-64 ans Employés | BA2: Actifs 15-64 ans Ouvriers | BB2: Actifs occ 15-64 ans Agriculteurs exploitants | BC2: Actifs occ 15-64 ans Artisans, Comm., Chefs entr. | BD2: Actifs occ 15-64 ans Cadres Prof. intel. sup. | BE2: Actifs occ 15-64 ans Prof. intermédiaires | BF2: Actifs occupés 15-64 ans Employés | BG2: Actifs occupés 15-64 ans Ouvriers | BH2: Actifs occupés 15 ans ou plus | BI2: Actifs occupés 15 ans ou plus Hommes | BJ2: Actifs occupés 15 ans ou plus Femmes | BK2: Salariés 15 ans ou plus | BL2: Salariés 15 ans ou plus Hommes | BM2: Salariés 15 ans ou plus Femmes | BN2: Non-salariés 15 ans ou plus | BO2: Non-salariés 15 ans ou plus Hommes | BP2: Non-salariés 15 ans ou plus Femmes | BQ2: Actifs occ 15 ans ou plus TP | BR2: Salariés 15 ans ou plus TP | BS2: Salariés 15 ans ou plus TP Hommes | BT2: Salariés 15 ans ou plus TP Femmes | BU2: Non-salariés 15 ans ou plus TP | BV2: Salariés 15 ans ou plus Fonct publ, CDI | BW2: Actif occ 15 ans ou plus travaille commune résidence | BX2: Actif occ 15 ans ou plus travaille autre commune que commune résidence | BY2: Actif occ 15 ans ou plus travaille autre commune même dépt résidence | BZ2: Actif occ 15 ans ou plus travaille autre dépt même région résidence | CA2: Actif occ 15 ans ou plus travaille autre région en métropole | CB2: Actif occ 15 ans ou plus travaille autre région hors métropole | CC2: Actifs occ 15 ans ou plus pas de transport pour travail | CD2: Actifs occ 15 ans ou plus marche à pied pour travail | CE2: Actifs occ 15 ans ou plus vélo | CF2: Actifs occ 15 ans ou plus deux-roues motorisé | CG2: Actifs occ 15 ans ou plus voiture | CH2: Actifs occ 15 ans ou plus transport en commun | CI2: Superficie en km² | CJ2: Population (ACT RES) | CK2: Part de la population en âge de travailler (%) | CL2: Part de la population active dans la population en âge de travailler (%) | CM2: Part des actifs 15-24 ans (%) | CN2: Taux d’emploi des 15-64 ans (%) | CO2: Taux d’emploi des 15-24 ans (%) | CP2: Taux de chômage dans la pop active (%) | CQ2: Taux de chômage chez les 15-24 ans dans la pop active (%) | CR2: Part salariés chez les actifs occupés (%) | CS2: Part des femmes chez les salariés de 15 ans et plus (%) | CT2: Part des actifs occupés salariés en CDI ou fonction publique (%) | CU2: Part des actifs occupés travaillant dans la commune de résidence (%)
A3: OUEST | B3: FRESNOY MACKELLERIE | C3: Mackellerie | D3: 1547 | E3: 373 | F3: 953 | G3: 221 | H3: 750 | I3: 166 | J3: 476 | K3: 108 | L3: 796 | M3: 207 | N3: 476 | O3: 113 | P3: 973 | Q3: 156 | R3: 718 | S3: 99 | T3: 507 | U3: 67 | V3: 393 | W3: 47 | X3: 465 | Y3: 89 | Z3: 325 | AA3: 51 | AB3: 686 | AC3: 70 | AD3: 533 | AE3: 83 | AF3: 368 | AG3: 25 | AH3: 308 | AI3: 35 | AJ3: 318 | AK3: 45 | AL3: 225 | AM3: 48 | AN3: 286 | AO3: 86 | AP3: 185 | AQ3: 15 | AR3: 574 | AS3: 215 | AT3: 55 | AU3: 304 | AV3: 0 | AW3: 32 | AX3: 87 | AY3: 171 | AZ3: 366 | BA3: 332 | BB3: 0 | BC3: 24 | BD3: 87 | BE3: 166 | BF3: 259 | BG3: 220 | BH3: 696 | BI3: 375 | BJ3: 322 | BK3: 640 | BL3: 343 | BM3: 297 | BN3: 57 | BO3: 32 | BP3: 25 | BQ3: 133 | BR3: 120 | BS3: 47 | BT3: 73 | BU3: 12 | BV3: 495 | BW3: 217 | BX3: 480 | BY3: 453 | BZ3: 10 | CA3: 7 | CB3: 10 | CC3: 15 | CD3: 62 | CE3: 20 | CF3: 16 | CG3: 383 | CH3: 200 | CI3: 0.32 | CJ3: 2501 | CK3: 61.8 | CL3: 62.9 | CM3: 41.8 | CN3: 44.4 | CO3: 18.6 | CP3: 29.5 | CQ3: 55.4 | CR3: 91.9 | CS3: 46.4 | CT3: 77.5 | CU3: 31.1
A4: OUEST | B4: ARMENTIERES | C4: Fresnoy | D4: 2996 | E4: 978 | F4: 1615 | G4: 403 | H4: 1463 | I4: 423 | J4: 805 | K4: 235 | L4: 1533 | M4: 555 | N4: 811 | O4: 168 | P4: 1866 | Q4: 355 | R4: 1271 | S4: 240 | T4: 1021 | U4: 168 | V4: 689 | W4: 164 | X4: 845 | Y4: 187 | Z4: 582 | AA4: 76 | AB4: 1410 | AC4: 225 | AD4: 996 | AE4: 190 | AF4: 816 | AG4: 122 | AH4: 555 | AI4: 138 | AJ4: 595 | AK4: 102 | AL4: 441 | AM4: 51 | AN4: 456 | AO4: 131 | AP4: 275 | AQ4: 50 | AR4: 1130 | AS4: 573 | AT4: 73 | AU4: 484 | AV4: 0 | AW4: 71 | AX4: 308 | AY4: 432 | AZ4: 595 | BA4: 441 | BB4: 0 | BC4: 64 | BD4: 296 | BE4: 391 | BF4: 454 | BG4: 318 | BH4: 1439 | BI4: 833 | BJ4: 606 | BK4: 1286 | BL4: 733 | BM4: 553 | BN4: 154 | BO4: 100 | BP4: 53 | BQ4: 301 | BR4: 263 | BS4: 95 | BT4: 167 | BU4: 39 | BV4: 951 | BW4: 453 | BX4: 986 | BY4: 861 | BZ4: 26 | CA4: 35 | CB4: 65 | CC4: 27 | CD4: 85 | CE4: 12 | CF4: 15 | CG4: 887 | CH4: 414 | CI4: 0.53 | CJ4: 4280 | CK4: 70 | CL4: 62.3 | CM4: 36.3 | CN4: 47.1 | CO4: 23 | CP4: 24.4 | CQ4: 36.8 | CR4: 89.3 | CS4: 43 | CT4: 74 | CU4: 31.5
A5: NORD | B5: FOSSE AUX CHENES | C5: Fosse aux Chênes | D5: 1820 | E5: 460 | F5: 1084 | G5: 276 | H5: 885 | I5: 214 | J5: 549 | K5: 123 | L5: 935 | M5: 246 | N5: 535 | O5: 153 | P5: 937 | Q5: 143 | R5: 695 | S5: 99 | T5: 507 | U5: 68 | V5: 399 | W5: 40 | X5: 430 | Y5: 75 | Z5: 295 | AA5: 59 | AB5: 662 | AC5: 96 | AD5: 492 | AE5: 73 | AF5: 341 | AG5: 39 | AH5: 273 | AI5: 29 | AJ5: 321 | AK5: 57 | AL5: 219 | AM5: 44 | AN5: 275 | AO5: 47 | AP5: 203 | AQ5: 26 | AR5: 883 | AS5: 286 | AT5: 63 | AU5: 533 | AV5: 0 | AW5: 48 | AX5: 52 | AY5: 93 | AZ5: 255 | BA5: 303 | BB5: 0 | BC5: 48 | BD5: 48 | BE5: 83 | BF5: 205 | BG5: 209 | BH5: 678 | BI5: 352 | BJ5: 325 | BK5: 584 | BL5: 298 | BM5: 286 | BN5: 94 | BO5: 54 | BP5: 39 | BQ5: 192 | BR5: 161 | BS5: 56 | BT5: 105 | BU5: 31 | BV5: 369 | BW5: 318 | BX5: 359 | BY5: 308 | BZ5: 6 | CA5: 21 | CB5: 24 | CC5: 35 | CD5: 135 | CE5: 9 | CF5: 0 | CG5: 284 | CH5: 215 | CI5: 0.41 | CJ5: 2843 | CK5: 64 | CL5: 51.5 | CM5: 31.2 | CN5: 36.4 | CO5: 21 | CP5: 29.4 | CQ5: 32.7 | CR5: 86.2 | CS5: 48.9 | CT5: 63.2 | CU5: 47
A6: NORD | B6: ALMA GARE | C6: Alma Sud | D6: 981 | E6: 299 | F6: 522 | G6: 161 | H6: 486 | I6: 153 | J6: 239 | K6: 94 | L6: 495 | M6: 146 | N6: 282 | O6: 67 | P6: 487 | Q6: 77 | R6: 331 | S6: 78 | T6: 268 | U6: 39 | V6: 180 | W6: 50 | X6: 219 | Y6: 39 | Z6: 151 | AA6: 29 | AB6: 267 | AC6: 26 | AD6: 187 | AE6: 54 | AF6: 155 | AG6: 18 | AH6: 113 | AI6: 25 | AJ6: 112 | AK6: 9 | AL6: 74 | AM6: 29 | AN6: 220 | AO6: 51 | AP6: 144 | AQ6: 25 | AR6: 494 | AS6: 179 | AT6: 17 | AU6: 298 | AV6: 0 | AW6: 21 | AX6: 15 | AY6: 26 | AZ6: 127 | BA6: 237 | BB6: 0 | BC6: 16 | BD6: 0 | BE6: 21 | BF6: 99 | BG6: 143 | BH6: 267 | BI6: 155 | BJ6: 112 | BK6: 250 | BL6: 139 | BM6: 112 | BN6: 17 | BO6: 17 | BP6: 0 | BQ6: 66 | BR6: 62 | BS6: 24 | BT6: 38 | BU6: 4 | BV6: 175 | BW6: 101 | BX6: 166 | BY6: 137 | BZ6: 4 | CA6: 0 | CB6: 25 | CC6: 8 | CD6: 29 | CE6: 5 | CF6: 0 | CG6: 142 | CH6: 82 | CI6: 0.09 | CJ6: 1529 | CK6: 64.2 | CL6: 49.7 | CM6: 25.9 | CN6: 27.2 | CO6: 8.8 | CP6: 45.2 | CQ6: 66.2 | CR6: 93.7 | CS6: 44.7 | CT6: 69.8 | CU6: 37.8
A7: NORD | B7: ALMA GARE | C7: Alma Nord | D7: 1003 | E7: 294 | F7: 580 | G7: 129 | H7: 459 | I7: 112 | J7: 276 | K7: 71 | L7: 543 | M7: 182 | N7: 304 | O7: 58 | P7: 493 | Q7: 80 | R7: 351 | S7: 63 | T7: 298 | U7: 40 | V7: 218 | W7: 40 | X7: 196 | Y7: 40 | Z7: 132 | AA7: 23 | AB7: 357 | AC7: 57 | AD7: 254 | AE7: 46 | AF7: 201 | AG7: 23 | AH7: 152 | AI7: 26 | AJ7: 155 | AK7: 34 | AL7: 102 | AM7: 20 | AN7: 136 | AO7: 23 | AP7: 96 | AQ7: 17 | AR7: 509 | AS7: 166 | AT7: 21 | AU7: 323 | AV7: 0 | AW7: 18 | AX7: 25 | AY7: 52 | AZ7: 83 | BA7: 176 | BB7: 0 | BC7: 16 | BD7: 20 | BE7: 48 | BF7: 75 | BG7: 118 | BH7: 377 | BI7: 208 | BJ7: 169 | BK7: 345 | BL7: 190 | BM7: 155 | BN7: 32 | BO7: 18 | BP7: 14 | BQ7: 86 | BR7: 76 | BS7: 31 | BT7: 44 | BU7: 10 | BV7: 277 | BW7: 157 | BX7: 220 | BY7: 182 | BZ7: 0 | CA7: 6 | CB7: 31 | CC7: 4 | CD7: 41 | CE7: 3 | CF7: 10 | CG7: 218 | CH7: 101 | CI7: 0.42 | CJ7: 1613 | CK7: 62.2 | CL7: 49.2 | CM7: 27.1 | CN7: 35.6 | CO7: 19.3 | CP7: 27.6 | CQ7: 28.8 | CR7: 91.6 | CS7: 44.9 | CT7: 80.2 | CU7: 41.7
A8: NORD | B8: ENTREPONT | C8: Entrepont-Cartigny | D8: 1445 | E8: 357 | F8: 888 | G8: 200 | H8: 719 | I8: 182 | J8: 425 | K8: 112 | L8: 727 | M8: 175 | N8: 463 | O8: 88 | P8: 869 | Q8: 107 | R8: 678 | S8: 84 | T8: 463 | U8: 56 | V8: 362 | W8: 45 | X8: 406 | Y8: 51 | Z8: 316 | AA8: 39 | AB8: 585 | AC8: 61 | AD8: 472 | AE8: 52 | AF8: 320 | AG8: 24 | AH8: 276 | AI8: 20 | AJ8: 266 | AK8: 38 | AL8: 197 | AM8: 31 | AN8: 283 | AO8: 46 | AP8: 205 | AQ8: 32 | AR8: 576 | AS8: 213 | AT8: 33 | AU8: 331 | AV8: 0 | AW8: 36 | AX8: 37 | AY8: 138 | AZ8: 295 | BA8: 327 | BB8: 0 | BC8: 36 | BD8: 31 | BE8: 128 | BF8: 159 | BG8: 220 | BH8: 592 | BI8: 323 | BJ8: 269 | BK8: 527 | BL8: 281 | BM8: 246 | BN8: 65 | BO8: 42 | BP8: 23 | BQ8: 121 | BR8: 100 | BS8: 37 | BT8: 63 | BU8: 21 | BV8: 398 | BW8: 224 | BX8: 367 | BY8: 298 | BZ8: 3 | CA8: 21 | CB8: 44 | CC8: 14 | CD8: 57 | CE8: 6 | CF8: 9 | CG8: 425 | CH8: 80 | CI8: 0.85 | CJ8: 2372 | CK8: 60.9 | CL8: 60.1 | CM8: 30 | CN8: 40.5 | CO8: 17.1 | CP8: 32.6 | CQ8: 42.8 | CR8: 89.1 | CS8: 46.7 | CT8: 75.6 | CU8: 37.9
A9: NORD | B9: HUTIN - ORAN - CARTIGNY | C9: Hutin-Oran | D9: 1240 | E9: 308 | F9: 792 | G9: 141 | H9: 594 | I9: 139 | J9: 374 | K9: 81 | L9: 646 | M9: 169 | N9: 417 | O9: 60 | P9: 769 | Q9: 93 | R9: 585 | S9: 91 | T9: 422 | U9: 44 | V9: 326 | W9: 53 | X9: 346 | Y9: 49 | Z9: 259 | AA9: 38 | AB9: 531 | AC9: 53 | AD9: 421 | AE9: 58 | AF9: 304 | AG9: 27 | AH9: 240 | AI9: 36 | AJ9: 228 | AK9: 26 | AL9: 180 | AM9: 22 | AN9: 237 | AO9: 40 | AP9: 165 | AQ9: 33 | AR9: 471 | AS9: 158 | AT9: 22 | AU9: 291 | AV9: 0 | AW9: 11 | AX9: 42 | AY9: 157 | AZ9: 186 | BA9: 282 | BB9: 0 | BC9: 6 | BD9: 42 | BE9: 141 | BF9: 120 | BG9: 177 | BH9: 548 | BI9: 308 | BJ9: 240 | BK9: 501 | BL9: 279 | BM9: 221 | BN9: 47 | BO9: 29 | BP9: 19 | BQ9: 104 | BR9: 98 | BS9: 46 | BT9: 52 | BU9: 7 | BV9: 372 | BW9: 204 | BX9: 344 | BY9: 291 | BZ9: 4 | CA9: 4 | CB9: 45 | CC9: 16 | CD9: 27 | CE9: 15 | CF9: 3 | CG9: 423 | CH9: 63 | CI9: 0.42 | CJ9: 2166 | CK9: 57.2 | CL9: 62 | CM9: 30 | CN9: 42.8 | CO9: 17.1 | CP9: 30.9 | CQ9: 43.2 | CR9: 91.4 | CS9: 44.2 | CT9: 74.3 | CU9: 37.2
A10: NORD | B10: CUL DE FOUR | C10: Cul de Four | D10: 2149 | E10: 643 | F10: 1213 | G10: 294 | H10: 1090 | I10: 356 | J10: 601 | K10: 133 | L10: 1059 | M10: 287 | N10: 611 | O10: 161 | P10: 1122 | Q10: 195 | R10: 803 | S10: 125 | T10: 701 | U10: 131 | V10: 492 | W10: 78 | X10: 421 | Y10: 63 | Z10: 311 | AA10: 47 | AB10: 687 | AC10: 122 | AD10: 477 | AE10: 89 | AF10: 440 | AG10: 85 | AH10: 301 | AI10: 54 | AJ10: 247 | AK10: 36 | AL10: 176 | AM10: 34 | AN10: 435 | AO10: 73 | AP10: 326 | AQ10: 36 | AR10: 1027 | AS10: 376 | AT10: 48 | AU10: 603 | AV10: 0 | AW10: 32 | AX10: 38 | AY10: 134 | AZ10: 309 | BA10: 508 | BB10: 0 | BC10: 22 | BD10: 38 | BE10: 101 | BF10: 188 | BG10: 325 | BH10: 702 | BI10: 452 | BJ10: 250 | BK10: 678 | BL10: 429 | BM10: 249 | BN10: 24 | BO10: 23 | BP10: 1 | BQ10: 204 | BR10: 200 | BS10: 106 | BT10: 94 | BU10: 4 | BV10: 451 | BW10: 245 | BX10: 457 | BY10: 394 | BZ10: 4 | CA10: 20 | CB10: 39 | CC10: 4 | CD10: 24 | CE10: 55 | CF10: 11 | CG10: 461 | CH10: 146 | CI10: 0.56 | CJ10: 3471 | CK10: 61.9 | CL10: 52.2 | CM10: 30.3 | CN10: 32 | CO10: 18.9 | CP10: 38.8 | CQ10: 37.5 | CR10: 96.6 | CS10: 36.7 | CT10: 66.5 | CU10: 34.9
A11: NORD | B11: HOMMELET | C11: Hommelet Nord | D11: 1431 | E11: 388 | F11: 863 | G11: 180 | H11: 729 | I11: 165 | J11: 459 | K11: 105 | L11: 702 | M11: 223 | N11: 404 | O11: 75 | P11: 829 | Q11: 112 | R11: 624 | S11: 93 | T11: 497 | U11: 45 | V11: 383 | W11: 70 | X11: 332 | Y11: 67 | Z11: 241 | AA11: 24 | AB11: 614 | AC11: 61 | AD11: 480 | AE11: 73 | AF11: 381 | AG11: 25 | AH11: 300 | AI11: 56 | AJ11: 233 | AK11: 37 | AL11: 180 | AM11: 17 | AN11: 216 | AO11: 51 | AP11: 144 | AQ11: 21 | AR11: 602 | AS11: 217 | AT11: 48 | AU11: 336 | AV11: 0 | AW11: 42 | AX11: 105 | AY11: 132 | AZ11: 196 | BA11: 337 | BB11: 0 | BC11: 37 | BD11: 105 | BE11: 98 | BF11: 147 | BG11: 246 | BH11: 617 | BI11: 384 | BJ11: 233 | BK11: 539 | BL11: 326 | BM11: 213 | BN11: 78 | BO11: 58 | BP11: 20 | BQ11: 154 | BR11: 141 | BS11: 45 | BT11: 96 | BU11: 13 | BV11: 423 | BW11: 190 | BX11: 427 | BY11: 373 | BZ11: 10 | CA11: 15 | CB11: 29 | CC11: 32 | CD11: 38 | CE11: 17 | CF11: 0 | CG11: 389 | CH11: 142 | CI11: 0.18 | CJ11: 2308 | CK11: 62 | CL11: 58 | CM11: 28.8 | CN11: 42.9 | CO11: 15.7 | CP11: 26 | CQ11: 45.5 | CR11: 87.3 | CS11: 39.5 | CT11: 78.5 | CU11: 30.8
A12: NORD | B12: HOMMELET | C12: Hommelet Centre | D12: 1660 | E12: 477 | F12: 913 | G12: 270 | H12: 787 | I12: 249 | J12: 394 | K12: 145 | L12: 873 | M12: 228 | N12: 520 | O12: 126 | P12: 916 | Q12: 125 | R12: 656 | S12: 135 | T12: 505 | U12: 77 | V12: 339 | W12: 89 | X12: 412 | Y12: 49 | Z12: 317 | AA12: 47 | AB12: 630 | AC12: 59 | AD12: 468 | AE12: 103 | AF12: 362 | AG12: 32 | AH12: 262 | AI12: 68 | AJ12: 268 | AK12: 27 | AL12: 206 | AM12: 35 | AN12: 287 | AO12: 66 | AP12: 188 | AQ12: 32 | AR12: 743 | AS12: 298 | AT12: 45 | AU12: 401 | AV12: 0 | AW12: 53 | AX12: 39 | AY12: 121 | AZ12: 306 | BA12: 368 | BB12: 0 | BC12: 47 | BD12: 32 | BE12: 100 | BF12: 226 | BG12: 266 | BH12: 641 | BI12: 371 | BJ12: 270 | BK12: 587 | BL12: 336 | BM12: 251 | BN12: 54 | BO12: 34 | BP12: 20 | BQ12: 161 | BR12: 144 | BS12: 63 | BT12: 82 | BU12: 17 | BV12: 425 | BW12: 223 | BX12: 418 | BY12: 371 | BZ12: 3 | CA12: 8 | CB12: 37 | CC12: 10 | CD12: 67 | CE12: 6 | CF12: 3 | CG12: 379 | CH12: 177 | CI12: 0.28 | CJ12: 2774 | CK12: 59.8 | CL12: 55.2 | CM12: 26.3 | CN12: 38 | CO12: 12.4 | CP12: 31.3 | CQ12: 53 | CR12: 91.6 | CS12: 42.7 | CT12: 72.4 | CU12: 34.8
A13: NORD | B13: HOMMELET | C13: Hommelet Sud | D13: 1576 | E13: 457 | F13: 902 | G13: 217 | H13: 842 | I13: 247 | J13: 487 | K13: 108 | L13: 734 | M13: 210 | N13: 416 | O13: 109 | P13: 949 | Q13: 125 | R13: 680 | S13: 144 | T13: 562 | U13: 75 | V13: 402 | W13: 85 | X13: 387 | Y13: 50 | Z13: 278 | AA13: 59 | AB13: 670 | AC13: 75 | AD13: 490 | AE13: 105 | AF13: 415 | AG13: 48 | AH13: 295 | AI13: 72 | AJ13: 255 | AK13: 27 | AL13: 195 | AM13: 33 | AN13: 279 | AO13: 50 | AP13: 190 | AQ13: 39 | AR13: 627 | AS13: 284 | AT13: 30 | AU13: 313 | AV13: 0 | AW13: 38 | AX13: 132 | AY13: 126 | AZ13: 270 | BA13: 384 | BB13: 0 | BC13: 34 | BD13: 123 | BE13: 117 | BF13: 193 | BG13: 258 | BH13: 674 | BI13: 419 | BJ13: 255 | BK13: 600 | BL13: 364 | BM13: 236 | BN13: 74 | BO13: 55 | BP13: 19 | BQ13: 146 | BR13: 137 | BS13: 61 | BT13: 76 | BU13: 9 | BV13: 440 | BW13: 238 | BX13: 436 | BY13: 393 | BZ13: 11 | CA13: 14 | CB13: 18 | CC13: 25 | CD13: 69 | CE13: 12 | CF13: 16 | CG13: 356 | CH13: 195 | CI13: 0.21 | CJ13: 2353 | CK13: 67 | CL13: 60.2 | CM13: 27.4 | CN13: 42.5 | CO13: 16.5 | CP13: 29.4 | CQ13: 39.8 | CR13: 89 | CS13: 39.4 | CT13: 73.3 | CU13: 35.3
A14: OUEST | B14: EPEULE | C14: Épeule Nord | D14: 1239 | E14: 308 | F14: 681 | G14: 249 | H14: 605 | I14: 158 | J14: 340 | K14: 106 | L14: 634 | M14: 150 | N14: 341 | O14: 143 | P14: 681 | Q14: 90 | R14: 452 | S14: 139 | T14: 383 | U14: 47 | V14: 271 | W14: 66 | X14: 298 | Y14: 43 | Z14: 182 | AA14: 73 | AB14: 448 | AC14: 51 | AD14: 294 | AE14: 103 | AF14: 262 | AG14: 21 | AH14: 191 | AI14: 50 | AJ14: 187 | AK14: 30 | AL14: 103 | AM14: 54 | AN14: 232 | AO14: 39 | AP14: 158 | AQ14: 36 | AR14: 558 | AS14: 154 | AT14: 38 | AU14: 366 | AV14: 0 | AW14: 31 | AX14: 15 | AY14: 83 | AZ14: 184 | BA14: 253 | BB14: 0 | BC14: 24 | BD14: 15 | BE14: 62 | BF14: 146 | BG14: 184 | BH14: 466 | BI14: 271 | BJ14: 195 | BK14: 406 | BL14: 233 | BM14: 173 | BN14: 60 | BO14: 38 | BP14: 22 | BQ14: 157 | BR14: 140 | BS14: 64 | BT14: 76 | BU14: 17 | BV14: 276 | BW14: 230 | BX14: 237 | BY14: 202 | BZ14: 8 | CA14: 11 | CB14: 15 | CC14: 27 | CD14: 54 | CE14: 4 | CF14: 3 | CG14: 192 | CH14: 187 | CI14: 0.15 | CJ14: 1947 | CK14: 63.6 | CL14: 55 | CM14: 29.1 | CN14: 36.2 | CO14: 16.6 | CP14: 34.1 | CQ14: 43 | CR14: 87.1 | CS14: 42.7 | CT14: 67.9 | CU14: 49.3
... A40: SUD | B40: HAUTS CHAMPS/PETITES HAIES | C40: Hauts Champs | D40: 1426 | E40: 368 | F40: 831 | G40: 227 | H40: 673 | I40: 195 | J40: 384 | K40: 94 | L40: 753 | M40: 173 | N40: 448 | O40: 133 | P40: 855 | Q40: 165 | R40: 595 | S40: 96 | T40: 493 | U40: 110 | V40: 338 | W40: 45 | X40: 362 | Y40: 55 | Z40: 257 | AA40: 50 | AB40: 557 | AC40: 118 | AD40: 372 | AE40: 67 | AF40: 308 | AG40: 71 | AH40: 211 | AI40: 26 | AJ40: 249 | AK40: 47 | AL40: 161 | AM40: 41 | AN40: 299 | AO40: 47 | AP40: 223 | AQ40: 29 | AR40: 571 | AS40: 149 | AT40: 46 | AU40: 376 | AV40: 0 | AW40: 49 | AX40: 21 | AY40: 108 | AZ40: 343 | BA40: 347 | BB40: 0 | BC40: 42 | BD40: 19 | BE40: 93 | BF40: 251 | BG40: 186 | BH40: 563 | BI40: 312 | BJ40: 252 | BK40: 502 | BL40: 270 | BM40: 232 | BN40: 61 | BO40: 42 | BP40: 20 | BQ40: 108 | BR40: 79 | BS40: 21 | BT40: 58 | BU40: 29 | BV40: 386 | BW40: 244 | BX40: 319 | BY40: 288 | BZ40: 8 | CA40: 12 | CB40: 11 | CC40: 6 | CD40: 38 | CE40: 11 | CF40: 2 | CG40: 370 | CH40: 136 | CI40: 0.31 | CJ40: 2227 | CK40: 64 | CL40: 60 | CM40: 44.7 | CN40: 39 | CO40: 32.1 | CP40: 34.9 | CQ40: 28.3 | CR40: 89.1 | CS40: 46.2 | CT40: 76.9 | CU40: 43.3

Sheet COU FAM 2023
A1: Données infra-communales - Couples - Familles - Ménages | D1: =SUBTOTAL(9,D3:D40) | E1: =SUBTOTAL(9,E3:E40) | F1: =SUBTOTAL(9,F3:F40) | G1: =SUBTOTAL(9,G3:G40) | H1: =SUBTOTAL(9,H3:H40) | I1: =SUBTOTAL(9,I3:I40) | J1: =SUBTOTAL(9,J3:J40) | K1: =SUBTOTAL(9,K3:K40) | ... BC1: =SUBTOTAL(9,BC3:BC40) | BH1: =SUBTOTAL(9,BH3:BH40)
A2: Mairies de quartiers | B2: Grands quartiers | C2: Libellé de l'Iris | D2: Ménages | E2: Ménages 1 personne | F2: Ménages Hommes seuls | G2: Ménages Femmes seules | H2: Ménages Autres sans famille | I2: Ménages avec famille(s) | J2: Mén fam princ Couple sans enfant | K2: Mén fam princ Couple avec enfant(s) | L2: Mén fam princ Famille mono | M2: Pop Ménages | N2: Pop mén Personnes seules | O2: Pop mén Hommes seuls | P2: Pop mén Femmes seules | Q2: Pop mén Autres sans famille | R2: Pop mén avec famille(s) | S2: Pop mén fam princ Couple sans enfant | T2: Pop mén fam princ Couple avec enfant(s) | U2: Pop mén fam princ Famille mono | V2: Pop 15 ans ou plus mariée | W2: Pop 15 ans ou plus pacsée | X2: Pop 15 ans ou plus en concubinage ou union libre | Y2: Pop 15 ans ou plus veuves ou veufs | Z2: Pop 15 ans ou plus divorcée | AA2: Pop 15 ans ou plus célibataire | AB2: Ménages Pers Réf Agri. expl. | AC2: Ménages Pers Réf Art. Comm. Chef entr. | AD2: Ménages Pers Réf Cadre Prof int sup | AE2: Ménages Pers Réf Prof intermédiaire | AF2: Ménages Pers Réf Employé | AG2: Ménages Pers Réf Ouvrier | AH2: Ménages Pers Réf Retraité | AI2: Ménages Pers Réf Autre | AJ2: Pop mén Pers Réf Agri. expl. | AK2: Pop mén Pers Réf Art Com Chef entr. | AL2: Pop mén Pers Réf Cadre Prof int sup | AM2: Pop mén Pers Réf Prof intermédiaire | AN2: Pop mén Pers Réf Employé | AO2: Pop mén Pers Réf Ouvrier | AP2: Pop mén Pers Réf Retraité | AQ2: Pop mén Pers Réf Autre | AR2: Familles | AS2: Fam Couple avec enfant(s) | AT2: Fam Monoparentales | AU2: Fam Couple sans enfant | AV2: Fam 0 enfant moins 25 ans | AW2: Fam 1 enfant moins 25 ans | AX2: Fam 2 enfants moins 25 ans | AY2: Fam 3 enfants moins 25 ans | AZ2: Fam 4 enfants ou plus moins 25 ans | BA2: Fam Couple avec uniq enfant(s) Couple | BB2: Fam Couple avec mini 1 enfant 1 des 2 Couple | BC2: Superficie en km² | BD2: Part des ménages avec famille(s) (%) | BE2: Part des ménages famille couple avec enfant(s) (%) | BF2: Part des familles couple avec enfant(s) (%) | BG2: Part de familles monoparentales (%) | BH2: Nombre de familles nombreuses | BI2: Part de familles nombreuses (%)
A3: OUEST | B3: FRESNOY MACKELLERIE | C3: Mackellerie | D3: 924 | E3: 310 | F3: 191 | G3: 152 | H3: 22 | I3: 617 | J3: 127 | K3: 263 | L3: 227 | M3: 2550 | N3: 342 | O3: 191 | P3: 152 | Q3: 55 | R3: 2153 | S3: 255 | T3: 1189 | U3: 709 | V3: 587 | W3: 31 | X3: 180 | Y3: 90 | Z3: 178 | AA3: 709 | AB3: 0 | AC3: 25 | AD3: 58 | AE3: 124 | AF3: 212 | AG3: 254 | AH3: 154 | AI3: 154 | AJ3: 0 | AK3: 61 | AL3: 187 | AM3: 322 | AN3: 593 | AO3: 772 | AP3: 226 | AQ3: 390 | AR3: 633 | AS3: 263 | AT3: 243 | AU3: 127 | AV3: 193 | AW3: 168 | AX3: 129 | AY3: 70 | AZ3: 73 | BA3: 234 | BB3: 30 | BC3: 0.32 | BD3: 66.8 | BE3: 28.5 | BF3: 41.6 | BG3: 38.3 | BH3: 143 | BI3: 22.6
A4: OUEST | B4: ARMENTIERES | C4: Fresnoy | D4: 1906 | E4: 915 | F4: 516 | G4: 516 | H4: 57 | I4: 978 | J4: 258 | K4: 424 | L4: 296 | M4: 4498 | N4: 1032 | O4: 516 | P4: 516 | Q4: 151 | R4: 3315 | S4: 573 | T4: 1809 | U4: 933 | V4: 1016 | W4: 46 | X4: 384 | Y4: 142 | Z4: 195 | AA4: 1619 | AB4: 0 | AC4: 62 | AD4: 206 | AE4: 267 | AF4: 407 | AG4: 300 | AH4: 293 | AI4: 532 | AJ4: 0 | AK4: 223 | AL4: 491 | AM4: 577 | AN4: 1031 | AO4: 835 | AP4: 487 | AQ4: 853 | AR4: 1000 | AS4: 424 | AT4: 310 | AU4: 267 | AV4: 373 | AW4: 228 | AX4: 198 | AY4: 117 | AZ4: 86 | BA4: 359 | BB4: 65 | BC4: 0.53 | BD4: 51.3 | BE4: 22.2 | BF4: 42.4 | BG4: 30.9 | BH4: 202 | BI4: 20.2
A5: NORD | B5: FOSSE AUX CHENES | C5: Fosse aux Chênes | D5: 1129 | E5: 487 | F5: 245 | G5: 173 | H5: 8 | I5: 561 | J5: 124 | K5: 238 | L5: 199 | M5: 2378 | N5: 418 | O5: 245 | P5: 173 | Q5: 28 | R5: 1931 | S5: 274 | T5: 1092 | U5: 566 | V5: 788 | W5: 14 | X5: 91 | Y5: 125 | Z5: 200 | AA5: 973 | AB5: 0 | AC5: 42 | AD5: 44 | AE5: 53 | AF5: 159 | AG5: 236 | AH5: 198 | AI5: 256 | AJ5: 0 | AK5: 154 | AL5: 103 | AM5: 164 | AN5: 426 | AO5: 694 | AP5: 345 | AQ5: 493 | AR5: 566 | AS5: 238 | AT5: 204 | AU5: 124 | AV5: 197 | AW5: 122 | AX5: 111 | AY5: 88 | AZ5: 49 | BA5: 196 | BB5: 42 | BC5: 0.41 | BD5: 49.7 | BE5: 21.1 | BF5: 42 | BG5: 36 | BH5: 136 | BI5: 24.1
A6: NORD | B6: ALMA GARE | C6: Alma Sud | D6: 493 | E6: 175 | F6: 116 | G6: 69 | H6: 5 | I6: 303 | J6: 27 | K6: 198 | L6: 78 | M6: 1477 | N6: 185 | O6: 116 | P6: 69 | Q6: 11 | R6: 1282 | S6: 53 | T6: 978 | U6: 250 | V6: 432 | W6: 0 | X6: 43 | Y6: 50 | Z6: 83 | AA6: 469 | AB6: 0 | AC6: 21 | AD6: 5 | AE6: 16 | AF6: 63 | AG6: 185 | AH6: 90 | AI6: 113 | AJ6: 0 | AK6: 43 | AL6: 15 | AM6: 31 | AN6: 269 | AO6: 625 | AP6: 190 | AQ6: 305 | AR6: 303 | AS6: 198 | AT6: 78 | AU6: 27 | AV6: 47 | AW6: 69 | AX6: 68 | AY6: 54 | AZ6: 65 | BA6: 172 | BB6: 26 | BC6: 0.09 | BD6: 61.5 | BE6: 40.3 | BF6: 65.4 | BG6: 25.8 | BH6: 119 | BI6: 39.2
A7: NORD | B7: ALMA GARE | C7: Alma Nord | D7: 558 | E7: 178 | F7: 123 | G7: 59 | H7: 9 | I7: 293 | J7: 57 | K7: 151 | L7: 85 | M7: 1321 | N7: 182 | O7: 123 | P7: 59 | Q7: 19 | R7: 1120 | S7: 123 | T7: 737 | U7: 261 | V7: 449 | W7: 7 | X7: 75 | Y7: 64 | Z7: 73 | AA7: 504 | AB7: 0 | AC7: 13 | AD7: 17 | AE7: 39 | AF7: 67 | AG7: 158 | AH7: 96 | AI7: 95 | AJ7: 0 | AK7: 63 | AL7: 58 | AM7: 104 | AN7: 142 | AO7: 510 | AP7: 154 | AQ7: 289 | AR7: 302 | AS7: 150 | AT7: 94 | AU7: 57 | AV7: 91 | AW7: 50 | AX7: 55 | AY7: 53 | AZ7: 53 | BA7: 136 | BB7: 14 | BC7: 0.42 | BD7: 52.5 | BE7: 26.9 | BF7: 49.9 | BG7: 31.2 | BH7: 106 | BI7: 35.1
A8: NORD | B8: ENTREPONT | C8: Entrepont-Cartigny | D8: 892 | E8: 316 | F8: 245 | G8: 107 | H8: 10 | I8: 571 | J8: 105 | K8: 263 | L8: 204 | M8: 2425 | N8: 352 | O8: 245 | P8: 107 | Q8: 20 | R8: 2053 | S8: 214 | T8: 1220 | U8: 619 | V8: 702 | W8: 10 | X8: 119 | Y8: 75 | Z8: 93 | AA8: 755 | AB8: 0 | AC8: 22 | AD8: 20 | AE8: 84 | AF8: 184 | AG8: 250 | AH8: 162 | AI8: 211 | AJ8: 0 | AK8: 82 | AL8: 57 | AM8: 188 | AN8: 576 | AO8: 820 | AP8: 308 | AQ8: 393 | AR8: 581 | AS8: 263 | AT8: 213 | AU8: 105 | AV8: 184 | AW8: 136 | AX8: 116 | AY8: 78 | AZ8: 66 | BA8: 228 | BB8: 35 | BC8: 0.85 | BD8: 64.1 | BE8: 29.5 | BF8: 45.3 | BG8: 36.7 | BH8: 145 | BI8: 24.9
A9: NORD | B9: HUTIN - ORAN - CARTIGNY | C9: Hutin-Oran | D9: 807 | E9: 270 | F9: 138 | G9: 142 | H9: 4 | I9: 507 | J9: 152 | K9: 200 | L9: 155 | M9: 2071 | N9: 280 | O9: 138 | P9: 142 | Q9: 8 | R9: 1783 | S9: 315 | T9: 972 | U9: 496 | V9: 727 | W9: 0 | X9: 67 | Y9: 87 | Z9: 118 | AA9: 584 | AB9: 0 | AC9: 11 | AD9: 31 | AE9: 99 | AF9: 132 | AG9: 209 | AH9: 233 | AI9: 77 | AJ9: 0 | AK9: 58 | AL9: 65 | AM9: 337 | AN9: 375 | AO9: 646 | AP9: 370 | AQ9: 221 | AR9: 514 | AS9: 200 | AT9: 162 | AU9: 152 | AV9: 206 | AW9: 70 | AX9: 112 | AY9: 68 | AZ9: 59 | BA9: 168 | BB9: 32 | BC9: 0.42 | BD9: 62.8 | BE9: 24.8 | BF9: 38.9 | BG9: 31.5 | BH9: 127 | BI9: 24.7
A10: NORD | B10: CUL DE FOUR | C10: Cul de Four | D10: 1059 | E10: 274 | F10: 136 | G10: 137 | H10: 29 | I10: 734 | J10: 155 | K10: 363 | L10: 216 | M10: 3339 | N10: 273 | O10: 136 | P10: 137 | Q10: 63 | R10: 3003 | S10: 344 | T10: 1883 | U10: 777 | V10: 919 | W10: 0 | X10: 201 | Y10: 132 | Z10: 123 | AA10: 1105 | AB10: 0 | AC10: 27 | AD10: 28 | AE10: 66 | AF10: 172 | AG10: 327 | AH10: 213 | AI10: 204 | AJ10: 0 | AK10: 96 | AL10: 80 | AM10: 221 | AN10: 673 | AO10: 1254 | AP10: 415 | AQ10: 600 | AR10: 758 | AS10: 363 | AT10: 230 | AU10: 164 | AV10: 273 | AW10: 113 | AX10: 100 | AY10: 123 | AZ10: 150 | BA10: 307 | BB10: 56 | BC10: 0.56 | BD10: 69.3 | BE10: 34.3 | BF10: 47.9 | BG10: 30.4 | BH10: 272 | BI10: 35.9
A11: NORD | B11: HOMMELET | C11: Hommelet Nord | D11: 796 | E11: 232 | F11: 165 | G11: 96 | H11: 10 | I11: 586 | J11: 156 | K11: 287 | L11: 142 | M11: 2431 | N11: 262 | O11: 165 | P11: 96 | Q11: 25 | R11: 2145 | S11: 331 | T11: 1354 | U11: 460 | V11: 718 | W11: 9 | X11: 148 | Y11: 33 | Z11: 51 | AA11: 715 | AB11: 0 | AC11: 27 | AD11: 66 | AE11: 86 | AF11: 99 | AG11: 265 | AH11: 182 | AI11: 133 | AJ11: 0 | AK11: 115 | AL11: 190 | AM11: 284 | AN11: 269 | AO11: 879 | AP11: 313 | AQ11: 381 | AR11: 596 | AS11: 287 | AT11: 151 | AU11: 157 | AV11: 210 | AW11: 104 | AX11: 92 | AY11: 114 | AZ11: 76 | BA11: 250 | BB11: 37 | BC11: 0.18 | BD11: 73.6 | BE11: 36.1 | BF11: 48.2 | BG11: 25.3 | BH11: 189 | BI11: 31.8
A12: NORD | B12: HOMMELET | C12: Hommelet Centre | D12: 986 | E12: 331 | F12: 178 | G12: 188 | H12: 17 | I12: 659 | J12: 141 | K12: 290 | L12: 229 | M12: 2832 | N12: 366 | O12: 178 | P12: 188 | Q12: 51 | R12: 2415 | S12: 282 | T12: 1354 | U12: 779 | V12: 724 | W12: 18 | X12: 111 | Y12: 130 | Z12: 157 | AA12: 888 | AB12: 0 | AC12: 47 | AD12: 32 | AE12: 97 | AF12: 223 | AG12: 266 | AH12: 222 | AI12: 154 | AJ12: 0 | AK12: 195 | AL12: 109 | AM12: 292 | AN12: 587 | AO12: 831 | AP12: 395 | AQ12: 422 | AR12: 667 | AS12: 289 | AT12: 235 | AU12: 142 | AV12: 194 | AW12: 130 | AX12: 118 | AY12: 136 | AZ12: 89 | BA12: 256 | BB12: 33 | BC12: 0.28 | BD12: 66.9 | BE12: 29.4 | BF12: 43.4 | BG12: 35.3 | BH12: 225 | BI12: 33.7
A13: NORD | B13: HOMMELET | C13: Hommelet Sud | D13: 931 | E13: 379 | F13: 223 | G13: 190 | H13: 27 | I13: 567 | J13: 118 | K13: 231 | L13: 218 | M13: 2389 | N13: 414 | O13: 223 | P13: 190 | Q13: 71 | R13: 1904 | S13: 240 | T13: 1009 | U13: 656 | V13: 544 | W13: 70 | X13: 90 | Y13: 98 | Z13: 168 | AA13: 852 | AB13: 0 | AC13: 34 | AD13: 87 | AE13: 74 | AF13: 188 | AG13: 280 | AH13: 182 | AI13: 163 | AJ13: 0 | AK13: 89 | AL13: 216 | AM13: 190 | AN13: 483 | AO13: 811 | AP13: 255 | AQ13: 343 | AR13: 567 | AS13: 231 | AT13: 218 | AU13: 118 | AV13: 159 | AW13: 141 | AX13: 113 | AY13: 103 | AZ13: 51 | BA13: 193 | BB13: 38 | BC13: 0.21 | BD13: 60.9 | BE13: 24.8 | BF13: 40.7 | BG13: 38.5 | BH13: 154 | BI13: 27.2
A14: OUEST | B14: EPEULE | C14: Épeule Nord | D14: 708 | E14: 234 | F14: 124 | G14: 89 | H14: 18 | I14: 389 | J14: 87 | K14: 203 | L14: 98 | M14: 1748 | N14: 213 | O14: 124 | P14: 89 | Q14: 54 | R14: 1481 | S14: 177 | T14: 992 | U14: 311 | V14: 590 | W14: 3 | X14: 62 | Y14: 68 | Z14: 131 | AA14: 618 | AB14: 0 | AC14: 28 | AD14: 5 | AE14: 45 | AF14: 126 | AG14: 169 | AH14: 138 | AI14: 110 | AJ14: 0 | AK14: 80 | AL14: 8 | AM14: 132 | AN14: 410 | AO14: 610 | AP14: 237 | AQ14: 270 | AR14: 388 | AS14: 203 | AT14: 98 | AU14: 87 | AV14: 150 | AW14: 51 | AX14: 66 | AY14: 50 | AZ14: 71 | BA14: 176 | BB14: 28 | BC14: 0.15 | BD14: 54.9 | BE14: 28.7 | BF14: 52.4 | BG14: 25.2 | BH14: 121 | BI14: 31
... A40: SUD | B40: HAUTS CHAMPS/PETITES HAIES | C40: Hauts Champs | D40: 915 | E40: 403 | F40: 168 | G40: 267 | H40: 11 | I40: 458 | J40: 87 | K40: 211 | L40: 160 | M40: 2090 | N40: 435 | O40: 168 | P40: 267 | Q40: 23 | R40: 1633 | S40: 174 | T40: 999 | U40: 460 | V40: 598 | W40: 12 | X40: 95 | Y40: 97 | Z40: 189 | AA40: 701 | AB40: 0 | AC40: 35 | AD40: 14 | AE40: 67 | AF40: 197 | AG40: 262 | AH40: 242 | AI40: 87 | AJ40: 0 | AK40: 136 | AL40: 31 | AM40: 154 | AN40: 477 | AO40: 776 | AP40: 351 | AQ40: 165 | AR40: 465 | AS40: 211 | AT40: 162 | AU40: 92 | AV40: 119 | AW40: 97 | AX40: 118 | AY40: 88 | AZ40: 43 | BA40: 174 | BB40: 37 | BC40: 0.31 | BD40: 50.1 | BE40: 23.1 | BF40: 45.4 | BG40: 34.8 | BH40: 130 | BI40: 28.1

Sheet DIP FORMATION 2023
A1: Données infra-communales - Diplômes - Formation | D1: =SUBTOTAL(9,D3:D40) | E1: =SUBTOTAL(9,E3:E40) | F1: =SUBTOTAL(9,F3:F40) | G1: =SUBTOTAL(9,G3:G40) | H1: =SUBTOTAL(9,H3:H40) | I1: =SUBTOTAL(9,I3:I40) | J1: =SUBTOTAL(9,J3:J40) | K1: =SUBTOTAL(9,K3:K40) | ... AH1: =SUBTOTAL(9,AH3:AH40) | AJ1: =SUBTOTAL(9,AJ3:AJ40)
A2: Mairies de quartiers | B2: Grands quartiers | C2: Libellé de l'Iris | D2: Pop 2-5 ans | E2: Pop 6-10 ans | F2: Pop 11-14 ans | G2: Pop 15-17 ans | H2: Pop 18-24 ans | I2: Pop 25-29 ans | J2: Pop 30 ans ou plus | K2: Pop scolarisée 2-5 ans | L2: Pop scolarisée 6-10 ans | M2: Pop scolarisée 11-14 ans | N2: Pop scolarisée 15-17 ans | O2: Pop scolarisée 18-24 ans | P2: Pop scolarisée 25-29 ans | Q2: Pop scolarisée 30 ans ou plus | R2: Pop 15 ans ou plus non scolarisée | S2: Pop 15 ans ou plus non scol. Sans diplôme ou CEP | T2: Pop 15 ans ou plus non scol. BEPC, brevet des collèges, DNB | U2: Pop 15 ans ou plus non scol. CAP-BEP ou équiv. | V2: Pop 15 ans ou plus non scol. Bac, brevet pro. ou équiv. | W2: Pop 15 ans ou plus non scol. Enseignement sup de niveau bac + 2 | X2: Pop 15 ans ou plus non scol. Enseignement sup de niveau bac + 3 ou 4 | Y2: Pop 15 ans ou plus non scol. Enseignement sup de niveau bac + 5 ou plus | Z2: Hommes 15 ans ou plus non scolarisée | AA2: Hommes 15 ans ou plus non scol. Sans diplôme ou CEP | AB2: Hommes 15 ans ou plus non scol. CAP-BEP ou équiv. | AC2: Hommes 15 ans ou plus non scol. Bac, brevet pro. ou équiv. | AD2: Femmes 15 ans ou plus non scolarisée | AE2: Femmes 15 ans ou plus non scol. Sans diplôme ou CEP | AF2: Femmes 15 ans ou plus non scol. CAP-BEP ou équiv. | AG2: Femmes 15 ans ou plus non scol. Bac, brevet pro. ou équiv. | AH2: Superficie en km² | AI2: Part pop 15 ans et plus non scol sans dip ou CEP max (%) | AJ2: Pop 15 ans ou plus non scol dipl Ens Sup | AK2: Part pop 15 ans et plus non scol dipl Ens Sup (%)
A3: OUEST | B3: FRESNOY MACKELLERIE | C3: Mackellerie | D3: 204 | E3: 235 | F3: 188 | G3: 117 | H3: 256 | I3: 187 | J3: 1216 | K3: 157 | L3: 235 | M3: 188 | N3: 101 | O3: 110 | P3: 18 | Q3: 54 | R3: 1492 | S3: 487 | T3: 84 | U3: 363 | V3: 286 | W3: 103 | X3: 93 | Y3: 75 | Z3: 729 | AA3: 228 | AB3: 208 | AC3: 123 | AD3: 763 | AE3: 259 | AF3: 155 | AG3: 163 | AH3: 0.32 | AI3: 32.6 | AJ3: 271 | AK3: 18.2
A4: OUEST | B4: ARMENTIERES | C4: Fresnoy | D4: 174 | E4: 338 | F4: 253 | G4: 195 | H4: 784 | I4: 346 | J4: 2079 | K4: 148 | L4: 310 | M4: 239 | N4: 177 | O4: 511 | P4: 78 | Q4: 31 | R4: 2606 | S4: 631 | T4: 174 | U4: 580 | V4: 412 | W4: 294 | X4: 236 | Y4: 281 | Z4: 1306 | AA4: 297 | AB4: 313 | AC4: 188 | AD4: 1300 | AE4: 334 | AF4: 267 | AG4: 223 | AH4: 0.53 | AI4: 24.2 | AJ4: 810 | AK4: 31.1
A5: NORD | B5: FOSSE AUX CHENES | C5: Fosse aux Chênes | D5: 189 | E5: 181 | F5: 185 | G5: 127 | H5: 332 | I5: 193 | J5: 1538 | K5: 133 | L5: 153 | M5: 167 | N5: 119 | O5: 186 | P5: 19 | Q5: 17 | R5: 1850 | S5: 848 | T5: 104 | U5: 390 | V5: 290 | W5: 86 | X5: 88 | Y5: 43 | Z5: 893 | AA5: 415 | AB5: 215 | AC5: 137 | AD5: 956 | AE5: 433 | AF5: 175 | AG5: 153 | AH5: 0.41 | AI5: 45.8 | AJ5: 217 | AK5: 11.8
A6: NORD | B6: ALMA GARE | C6: Alma Sud | D6: 124 | E6: 173 | F6: 90 | G6: 81 | H6: 217 | I6: 99 | J6: 679 | K6: 111 | L6: 173 | M6: 86 | N6: 73 | O6: 106 | P6: 4 | Q6: 9 | R6: 884 | S6: 456 | T6: 54 | U6: 157 | V6: 138 | W6: 50 | X6: 17 | Y6: 13 | Z6: 427 | AA6: 221 | AB6: 84 | AC6: 67 | AD6: 458 | AE6: 235 | AF6: 73 | AG6: 71 | AH6: 0.09 | AI6: 51.5 | AJ6: 80 | AK6: 9
A7: NORD | B7: ALMA GARE | C7: Alma Nord | D7: 110 | E7: 161 | F7: 125 | G7: 123 | H7: 171 | I7: 92 | J7: 786 | K7: 97 | L7: 158 | M7: 121 | N7: 116 | O7: 67 | P7: 7 | Q7: 7 | R7: 975 | S7: 474 | T7: 32 | U7: 219 | V7: 118 | W7: 46 | X7: 51 | Y7: 35 | Z7: 490 | AA7: 225 | AB7: 127 | AC7: 54 | AD7: 485 | AE7: 249 | AF7: 92 | AG7: 64 | AH7: 0.42 | AI7: 48.6 | AJ7: 132 | AK7: 13.5
A8: NORD | B8: ENTREPONT | C8: Entrepont-Cartigny | D8: 145 | E8: 231 | F8: 181 | G8: 124 | H8: 233 | I8: 151 | J8: 1247 | K8: 121 | L8: 220 | M8: 175 | N8: 114 | O8: 122 | P8: 17 | Q8: 20 | R8: 1481 | S8: 726 | T8: 39 | U8: 332 | V8: 181 | W8: 109 | X8: 56 | Y8: 38 | Z8: 728 | AA8: 363 | AB8: 175 | AC8: 65 | AD8: 753 | AE8: 363 | AF8: 157 | AG8: 116 | AH8: 0.85 | AI8: 49.1 | AJ8: 203 | AK8: 13.7
A9: NORD | B9: HUTIN - ORAN - CARTIGNY | C9: Hutin-Oran | D9: 144 | E9: 166 | F9: 198 | G9: 112 | H9: 196 | I9: 99 | J9: 1175 | K9: 117 | L9: 166 | M9: 198 | N9: 103 | O9: 78 | P9: 0 | Q9: 1 | R9: 1401 | S9: 707 | T9: 38 | U9: 293 | V9: 228 | W9: 82 | X9: 27 | Y9: 25 | Z9: 650 | AA9: 329 | AB9: 176 | AC9: 85 | AD9: 750 | AE9: 378 | AF9: 117 | AG9: 143 | AH9: 0.42 | AI9: 50.5 | AJ9: 134 | AK9: 9.6
A10: NORD | B10: CUL DE FOUR | C10: Cul de Four | D10: 274 | E10: 298 | F10: 311 | G10: 214 | H10: 429 | I10: 209 | J10: 1628 | K10: 231 | L10: 287 | M10: 296 | N10: 191 | O10: 189 | P10: 16 | Q10: 35 | R10: 2049 | S10: 1068 | T10: 113 | U10: 286 | V10: 346 | W10: 133 | X10: 61 | Y10: 42 | Z10: 1037 | AA10: 484 | AB10: 167 | AC10: 196 | AD10: 1011 | AE10: 585 | AF10: 120 | AG10: 150 | AH10: 0.56 | AI10: 52.1 | AJ10: 235 | AK10: 11.5
A11: NORD | B11: HOMMELET | C11: Hommelet Nord | D11: 180 | E11: 219 | F11: 169 | G11: 129 | H11: 260 | I11: 146 | J11: 1138 | K11: 151 | L11: 212 | M11: 138 | N11: 110 | O11: 109 | P11: 19 | Q11: 29 | R11: 1406 | S11: 680 | T11: 63 | U11: 257 | V11: 203 | W11: 66 | X11: 35 | Y11: 101 | Z11: 742 | AA11: 366 | AB11: 125 | AC11: 107 | AD11: 664 | AE11: 314 | AF11: 132 | AG11: 97 | AH11: 0.18 | AI11: 48.4 | AJ11: 202 | AK11: 14.4
A12: NORD | B12: HOMMELET | C12: Hommelet Centre | D12: 204 | E12: 247 | F12: 226 | G12: 210 | H12: 267 | I12: 113 | J12: 1439 | K12: 175 | L12: 237 | M12: 224 | N12: 199 | O12: 122 | P12: 8 | Q12: 9 | R12: 1691 | S12: 882 | T12: 83 | U12: 285 | V12: 227 | W12: 82 | X12: 78 | Y12: 55 | Z12: 759 | AA12: 359 | AB12: 135 | AC12: 110 | AD12: 932 | AE12: 523 | AF12: 150 | AG12: 116 | AH12: 0.28 | AI12: 52.2 | AJ12: 214 | AK12: 12.7
A13: NORD | B13: HOMMELET | C13: Hommelet Sud | D13: 132 | E13: 197 | F13: 147 | G13: 155 | H13: 302 | I13: 139 | J13: 1225 | K13: 108 | L13: 197 | M13: 140 | N13: 136 | O13: 159 | P13: 24 | Q13: 17 | R13: 1485 | S13: 675 | T13: 64 | U13: 251 | V13: 208 | W13: 93 | X13: 86 | Y13: 108 | Z13: 780 | AA13: 327 | AB13: 145 | AC13: 120 | AD13: 706 | AE13: 348 | AF13: 106 | AG13: 88 | AH13: 0.21 | AI13: 45.5 | AJ13: 287 | AK13: 19.3
A14: OUEST | B14: EPEULE | C14: Épeule Nord | D14: 124 | E14: 198 | F14: 107 | G14: 104 | H14: 204 | I14: 124 | J14: 1040 | K14: 84 | L14: 189 | M14: 103 | N14: 87 | O14: 85 | P14: 13 | Q14: 22 | R14: 1266 | S14: 591 | T14: 95 | U14: 267 | V14: 182 | W14: 70 | X14: 40 | Y14: 21 | Z14: 641 | AA14: 305 | AB14: 159 | AC14: 90 | AD14: 625 | AE14: 285 | AF14: 108 | AG14: 92 | AH14: 0.15 | AI14: 46.7 | AJ14: 130 | AK14: 10.3
... A40: SUD | B40: HAUTS CHAMPS/PETITES HAIES | C40: Hauts Champs | D40: 156 | E40: 185 | F40: 125 | G40: 80 | H40: 289 | I40: 144 | J40: 1180 | K40: 116 | L40: 182 | M40: 125 | N40: 80 | O40: 102 | P40: 3 | Q40: 11 | R40: 1496 | S40: 547 | T40: 112 | U40: 385 | V40: 235 | W40: 111 | X40: 54 | Y40: 52 | Z40: 682 | AA40: 240 | AB40: 185 | AC40: 118 | AD40: 814 | AE40: 307 | AF40: 200 | AG40: 118 | AH40: 0.31 | AI40: 36.6 | AJ40: 217 | AK40: 14.5

Sheet LOG 2023
A1: Données infra-communales - Logement | D1: =SUBTOTAL(9,D3:D40) | E1: =SUBTOTAL(9,E3:E40) | F1: =SUBTOTAL(9,F3:F40) | G1: =SUBTOTAL(9,G3:G40) | H1: =SUBTOTAL(9,H3:H40) | I1: =SUBTOTAL(9,I3:I40) | J1: =SUBTOTAL(9,J3:J40) | K1: =SUBTOTAL(9,K3:K40) | ... BB1: =SUBTOTAL(9,BB3:BB40) | BG1: =SUBTOTAL(9,BG3:BG40) | BI1: =SUBTOTAL(9,BI3:BI40) | BL1: =SUBTOTAL(9,BL3:BL40) | BO1: =SUBTOTAL(9,BO3:BO40)
A2: Mairies de quartiers | B2: Grands quartiers | C2: Libellé de l'Iris | D2: Logements | E2: Résidences principales | F2: Rés secondaires et logts occasionnels | G2: Logements vacants | H2: Maisons | I2: Appartements | J2: Rés princ 1 pièce | K2: Rés princ 2 pièces | L2: Rés princ 3 pièces | M2: Rés princ 4 pièces | N2: Rés princ 5 pièces ou plus | O2: Rés princ de moins de 30 m2 | P2: Rés princ de 30 à moins de 40 m2 | Q2: Rés princ de 40 à moins de 60 m2 | R2: Rés princ de 60 à moins de 80 m2 | S2: Rés princ de 80 à moins de 100 m2 | T2: Rés princ de 100 à moins de 120 m2 | U2: Rés princ de 120 m2 ou plus | V2: Rés princ avt 1919 | W2: Rés princ 1919 à 1945 | X2: Rés princ 1946 à 1970 | Y2: Rés princ 1971 à 1990 | Z2: Rés princ 1991 à 2005 | AA2: Rés princ 2006 à 2019 | AB2: Ménages | AC2: Ménages emménagés moins 2 ans | AD2: Ménages emménagés entre 2-4 ans | AE2: Ménages emménagés entre 5-9 ans | AF2: Ménages emménagés depuis 10 ans ou plus | AG2: Pop Ménages | AH2: Rés princ occupées Propriétaires | AI2: Rés princ occupées Locataires | AJ2: Rés princ HLM louée vide | AK2: Rés princ logé gratuit | AL2: nombre de résidences principales avec combustible principal de chauffage gaz de ville - réseau de chaleur | AM2: nombre de résidences principales avec combustible principal de chauffage fioul | AN2: nombre de résidences principales avec combustible principal de chauffage électricité | AO2: nombre de résidences principales avec combustible principal de chauffage gaz en bouteilles ou citerne | AP2: nombre de résidences principales avec combustible principal de chauffage autres | AQ2: Ménages au moins un parking | AR2: Ménages au moins une voiture | AS2: Ménages une voiture | AT2: Ménages deux voitures ou plus | AU2: résidences principales en occupation dans la norm | AV2: résidences principales en sous-occupation modérée | AW2: résidences principales en sous-occupation accentuée | AX2: résidences principales en sous-occupation très accentuée | AY2: résidences principales en suroccupation modérée | AZ2: résidences principales en suroccupation accentuée | BA2: Superficie en km² | BB2: Superficie en hectares (LOG) | BC2: Densité de logements au km² | BD2: Densité de logements par hectare | BE2: Part des logements vacants (%) | BF2: Part des logements individuels (%) | BG2: Nombre de RP de petite typologie | BH2: Part des RP de petite typologie (%) | BI2: Nombre de RP de grande typologie | BJ2: Part des RP de grande typologie (%) | BK2: Part des ménages emménagés depuis moins de 2 ans (%) | BL2: Ménages emménagés moins 10 ans | BM2: Part des ménages emménagés depuis moins de 10 ans (%) | BN2: Taille moyenne des ménages | BO2: Nombre de RP parc privé | BP2: Part propriétaire dans les RP parc privé (%) | BQ2: Part propriétaire dans le parc de RP total (%) | BR2: Part HLM dans RP totale (%) | BS2: Part HLM dans les RP locataires (%) | BT2: Part des ménages avec parking (%) | BU2: Part des ménages avec au moins une voiture (%)
A3: OUEST | B3: FRESNOY MACKELLERIE | C3: Mackellerie | D3: 1021 | E3: 924 | F3: 4 | G3: 92 | H3: 579 | I3: 438 | J3: 37 | K3: 151 | L3: 229 | M3: 209 | N3: 299 | O3: 22 | P3: 111 | Q3: 198 | R3: 225 | S3: 212 | T3: 91 | U3: 65 | V3: 70 | W3: 453 | X3: 273 | Y3: 93 | Z3: 15 | AA3: 18 | AB3: 924 | AC3: 108 | AD3: 258 | AE3: 150 | AF3: 407 | AG3: 2460 | AH3: 324 | AI3: 592 | AJ3: 272 | AK3: 9 | AL3: 599 | AM3: 16 | AN3: 285 | AO3: 0 | AP3: 23 | AQ3: 120 | AR3: 561 | AS3: 453 | AT3: 109 | AU3: 321 | AV3: 269 | AW3: 136 | AX3: 120 | AY3: 124 | AZ3: 12 | BA3: 0.32 | BB3: 31.63 | BC3: 3226.33 | BD3: 32.26 | BE3: 9 | BF3: 56.8 | BG3: 188 | BH3: 20.3 | BI3: 737 | BJ3: 79.7 | BK3: 11.7 | BL3: 517 | BM3: 55.9 | BN3: 2.66 | BO3: 652 | BP3: 49.6 | BQ3: 35 | BR3: 29.4 | BS3: 45.9 | BT3: 13 | BU3: 60.8
A4: OUEST | B4: ARMENTIERES | C4: Fresnoy | D4: 2097 | E4: 1906 | F4: 48 | G4: 143 | H4: 775 | I4: 1269 | J4: 350 | K4: 412 | L4: 308 | M4: 284 | N4: 552 | O4: 417 | P4: 197 | Q4: 297 | R4: 339 | S4: 343 | T4: 143 | U4: 170 | V4: 171 | W4: 580 | X4: 151 | Y4: 135 | Z4: 306 | AA4: 516 | AB4: 1906 | AC4: 366 | AD4: 594 | AE4: 293 | AF4: 653 | AG4: 4279 | AH4: 551 | AI4: 1329 | AJ4: 380 | AK4: 26 | AL4: 984 | AM4: 24 | AN4: 867 | AO4: 3 | AP4: 29 | AQ4: 551 | AR4: 1132 | AS4: 806 | AT4: 327 | AU4: 666 | AV4: 335 | AW4: 208 | AX4: 300 | AY4: 521 | AZ4: 38 | BA4: 0.53 | BB4: 52.75 | BC4: 3975.55 | BD4: 39.75 | BE4: 6.8 | BF4: 37 | BG4: 762 | BH4: 40 | BI4: 1144 | BJ4: 60 | BK4: 19.2 | BL4: 1253 | BM4: 65.7 | BN4: 2.25 | BO4: 1526 | BP4: 36.1 | BQ4: 28.9 | BR4: 19.9 | BS4: 28.6 | BT4: 28.9 | BU4: 59.4
A5: NORD | B5: FOSSE AUX CHENES | C5: Fosse aux Chênes | D5: 1272 | E5: 1129 | F5: 3 | G5: 140 | H5: 259 | I5: 1007 | J5: 161 | K5: 292 | L5: 312 | M5: 131 | N5: 232 | O5: 47 | P5: 261 | Q5: 344 | R5: 225 | S5: 154 | T5: 68 | U5: 29 | V5: 30 | W5: 295 | X5: 194 | Y5: 338 | Z5: 241 | AA5: 26 | AB5: 1129 | AC5: 138 | AD5: 270 | AE5: 266 | AF5: 454 | AG5: 2703 | AH5: 166 | AI5: 953 | AJ5: 631 | AK5: 10 | AL5: 632 | AM5: 21 | AN5: 451 | AO5: 3 | AP5: 21 | AQ5: 250 | AR5: 560 | AS5: 465 | AT5: 95 | AU5: 353 | AV5: 236 | AW5: 77 | AX5: 79 | AY5: 196 | AZ5: 45 | BA5: 0.41 | BB5: 40.66 | BC5: 3128.12 | BD5: 31.28 | BE5: 11 | BF5: 20.4 | BG5: 453 | BH5: 40.2 | BI5: 675 | BJ5: 59.8 | BK5: 12.2 | BL5: 675 | BM5: 59.8 | BN5: 2.4 | BO5: 498 | BP5: 33.4 | BQ5: 14.7 | BR5: 55.9 | BS5: 66.2 | BT5: 22.2 | BU5: 49.6
A6: NORD | B6: ALMA GARE | C6: Alma Sud | D6: 592 | E6: 493 | F6: 3 | G6: 96 | H6: 97 | I6: 490 | J6: 4 | K6: 118 | L6: 143 | M6: 114 | N6: 113 | O6: 4 | P6: 37 | Q6: 228 | R6: 105 | S6: 74 | T6: 32 | U6: 13 | V6: 0 | W6: 25 | X6: 242 | Y6: 218 | Z6: 8 | AA6: 0 | AB6: 493 | AC6: 31 | AD6: 88 | AE6: 108 | AF6: 265 | AG6: 1529 | AH6: 17 | AI6: 471 | AJ6: 441 | AK6: 5 | AL6: 447 | AM6: 0 | AN6: 34 | AO6: 0 | AP6: 12 | AQ6: 131 | AR6: 279 | AS6: 228 | AT6: 51 | AU6: 198 | AV6: 138 | AW6: 31 | AX6: 15 | AY6: 81 | AZ6: 31 | BA6: 0.09 | BB6: 9.35 | BC6: 6328.38 | BD6: 63.26 | BE6: 16.2 | BF6: 16.4 | BG6: 123 | BH6: 24.9 | BI6: 370 | BJ6: 75.1 | BK6: 6.3 | BL6: 228 | BM6: 46.2 | BN6: 3.1 | BO6: 51 | BP6: 32.6 | BQ6: 3.4 | BR6: 89.6 | BS6: 93.6 | BT6: 26.7 | BU6: 56.7
A7: NORD | B7: ALMA GARE | C7: Alma Nord | D7: 639 | E7: 558 | F7: 0 | G7: 81 | H7: 327 | I7: 307 | J7: 47 | K7: 64 | L7: 153 | M7: 136 | N7: 159 | O7: 20 | P7: 55 | Q7: 149 | R7: 149 | S7: 109 | T7: 50 | U7: 26 | V7: 53 | W7: 260 | X7: 162 | Y7: 34 | Z7: 18 | AA7: 31 | AB7: 558 | AC7: 65 | AD7: 94 | AE7: 141 | AF7: 258 | AG7: 1613 | AH7: 137 | AI7: 418 | AJ7: 209 | AK7: 3 | AL7: 377 | AM7: 10 | AN7: 167 | AO7: 0 | AP7: 4 | AQ7: 126 | AR7: 361 | AS7: 297 | AT7: 64 | AU7: 120 | AV7: 94 | AW7: 67 | AX7: 87 | AY7: 100 | AZ7: 16 | BA7: 0.42 | BB7: 41.78 | BC7: 1529.51 | BD7: 15.29 | BE7: 12.6 | BF7: 51.2 | BG7: 111 | BH7: 19.9 | BI7: 447 | BJ7: 80.1 | BK7: 11.7 | BL7: 300 | BM7: 53.8 | BN7: 2.89 | BO7: 350 | BP7: 39.1 | BQ7: 24.5 | BR7: 37.4 | BS7: 49.9 | BT7: 22.6 | BU7: 64.6
A8: NORD | B8: ENTREPONT | C8: Entrepont-Cartigny | D8: 1048 | E8: 892 | F8: 8 | G8: 148 | H8: 685 | I8: 226 | J8: 153 | K8: 135 | L8: 98 | M8: 175 | N8: 330 | O8: 126 | P8: 151 | Q8: 146 | R8: 169 | S8: 171 | T8: 78 | U8: 52 | V8: 40 | W8: 501 | X8: 79 | Y8: 24 | Z8: 19 | AA8: 225 | AB8: 892 | AC8: 109 | AD8: 163 | AE8: 207 | AF8: 412 | AG8: 2364 | AH8: 374 | AI8: 508 | AJ8: 149 | AK8: 10 | AL8: 635 | AM8: 14 | AN8: 187 | AO8: 1 | AP8: 55 | AQ8: 178 | AR8: 515 | AS8: 403 | AT8: 112 | AU8: 221 | AV8: 139 | AW8: 147 | AX8: 105 | AY8: 290 | AZ8: 31 | BA8: 0.85 | BB8: 84.99 | BC8: 1233.07 | BD8: 12.33 | BE8: 14.1 | BF8: 65.4 | BG8: 288 | BH8: 32.3 | BI8: 603 | BJ8: 67.7 | BK8: 12.3 | BL8: 480 | BM8: 53.8 | BN8: 2.65 | BO8: 743 | BP8: 50.4 | BQ8: 42 | BR8: 16.7 | BS8: 29.3 | BT8: 20 | BU8: 57.8
A9: NORD | B9: HUTIN - ORAN - CARTIGNY | C9: Hutin-Oran | D9: 1020 | E9: 807 | F9: 4 | G9: 209 | H9: 503 | I9: 517 | J9: 33 | K9: 132 | L9: 208 | M9: 125 | N9: 309 | O9: 29 | P9: 202 | Q9: 173 | R9: 133 | S9: 158 | T9: 99 | U9: 12 | V9: 24 | W9: 359 | X9: 208 | Y9: 148 | Z9: 27 | AA9: 39 | AB9: 807 | AC9: 58 | AD9: 122 | AE9: 191 | AF9: 436 | AG9: 2166 | AH9: 347 | AI9: 457 | AJ9: 339 | AK9: 3 | AL9: 630 | AM9: 3 | AN9: 152 | AO9: 3 | AP9: 18 | AQ9: 190 | AR9: 580 | AS9: 458 | AT9: 122 | AU9: 208 | AV9: 175 | AW9: 113 | AX9: 150 | AY9: 120 | AZ9: 25 | BA9: 0.42 | BB9: 41.76 | BC9: 2441.26 | BD9: 24.41 | BE9: 20.5 | BF9: 49.3 | BG9: 165 | BH9: 20.4 | BI9: 642 | BJ9: 79.6 | BK9: 7.2 | BL9: 371 | BM9: 46 | BN9: 2.69 | BO9: 468 | BP9: 74.1 | BQ9: 43 | BR9: 42 | BS9: 74.2 | BT9: 23.5 | BU9: 71.9
A10: NORD | B10: CUL DE FOUR | C10: Cul de Four | D10: 1177 | E10: 1059 | F10: 4 | G10: 115 | H10: 704 | I10: 473 | J10: 69 | K10: 111 | L10: 230 | M10: 203 | N10: 446 | O10: 62 | P10: 127 | Q10: 252 | R10: 236 | S10: 277 | T10: 67 | U10: 38 | V10: 31 | W10: 648 | X10: 214 | Y10: 117 | Z10: 21 | AA10: 24 | AB10: 1059 | AC10: 96 | AD10: 198 | AE10: 228 | AF10: 537 | AG10: 3471 | AH10: 350 | AI10: 702 | AJ10: 335 | AK10: 7 | AL10: 849 | AM10: 8 | AN10: 170 | AO10: 4 | AP10: 28 | AQ10: 138 | AR10: 658 | AS10: 510 | AT10: 148 | AU10: 245 | AV10: 254 | AW10: 168 | AX10: 138 | AY10: 166 | AZ10: 66 | BA10: 0.56 | BB10: 56.3 | BC10: 2091.51 | BD10: 20.91 | BE10: 9.7 | BF10: 59.8 | BG10: 180 | BH10: 17 | BI10: 879 | BJ10: 83 | BK10: 9.1 | BL10: 522 | BM10: 49.3 | BN10: 3.28 | BO10: 724 | BP10: 48.4 | BQ10: 33 | BR10: 31.7 | BS10: 47.8 | BT10: 13 | BU10: 62.1
A11: NORD | B11: HOMMELET | C11: Hommelet Nord | D11: 894 | E11: 796 | F11: 3 | G11: 94 | H11: 501 | I11: 379 | J11: 87 | K11: 121 | L11: 138 | M11: 177 | N11: 272 | O11: 67 | P11: 128 | Q11: 145 | R11: 171 | S11: 171 | T11: 73 | U11: 41 | V11: 84 | W11: 430 | X11: 176 | Y11: 13 | Z11: 27 | AA11: 64 | AB11: 796 | AC11: 73 | AD11: 174 | AE11: 187 | AF11: 362 | AG11: 2308 | AH11: 265 | AI11: 530 | AJ11: 136 | AK11: 0 | AL11: 446 | AM11: 16 | AN11: 286 | AO11: 0 | AP11: 49 | AQ11: 145 | AR11: 501 | AS11: 340 | AT11: 161 | AU11: 198 | AV11: 205 | AW11: 141 | AX11: 118 | AY11: 166 | AZ11: 29 | BA11: 0.18 | BB11: 18.34 | BC11: 4872.51 | BD11: 48.72 | BE11: 10.6 | BF11: 56 | BG11: 208 | BH11: 26.2 | BI11: 587 | BJ11: 73.8 | BK11: 9.2 | BL11: 434 | BM11: 54.6 | BN11: 2.9 | BO11: 660 | BP11: 40.2 | BQ11: 33.3 | BR11: 17.1 | BS11: 25.6 | BT11: 18.2 | BU11: 63
A12: NORD | B12: HOMMELET | C12: Hommelet Centre | D12: 1089 | E12: 986 | F12: 5 | G12: 98 | H12: 428 | I12: 656 | J12: 38 | K12: 168 | L12: 272 | M12: 257 | N12: 249 | O12: 36 | P12: 87 | Q12: 268 | R12: 273 | S12: 166 | T12: 97 | U12: 60 | V12: 41 | W12: 305 | X12: 156 | Y12: 380 | Z12: 29 | AA12: 74 | AB12: 986 | AC12: 111 | AD12: 167 | AE12: 211 | AF12: 497 | AG12: 2701 | AH12: 224 | AI12: 735 | AJ12: 512 | AK12: 26 | AL12: 820 | AM12: 25 | AN12: 112 | AO12: 3 | AP12: 26 | AQ12: 252 | AR12: 589 | AS12: 441 | AT12: 148 | AU12: 374 | AV12: 246 | AW12: 130 | AX12: 117 | AY12: 148 | AZ12: 27 | BA12: 0.28 | BB12: 28.27 | BC12: 3853.49 | BD12: 38.54 | BE12: 9 | BF12: 39.3 | BG12: 207 | BH12: 21 | BI12: 779 | BJ12: 79 | BK12: 11.2 | BL12: 488 | BM12: 49.5 | BN12: 2.74 | BO12: 474 | BP12: 47.3 | BQ12: 22.7 | BR12: 52 | BS12: 69.6 | BT12: 25.5 | BU12: 59.8
A13: NORD | B13: HOMMELET | C13: Hommelet Sud | D13: 1012 | E13: 931 | F13: 4 | G13: 77 | H13: 422 | I13: 584 | J13: 76 | K13: 153 | L13: 185 | M13: 178 | N13: 339 | O13: 53 | P13: 92 | Q13: 248 | R13: 217 | S13: 120 | T13: 104 | U13: 98 | V13: 51 | W13: 505 | X13: 99 | Y13: 203 | Z13: 60 | AA13: 12 | AB13: 931 | AC13: 152 | AD13: 218 | AE13: 167 | AF13: 395 | AG13: 2250 | AH13: 299 | AI13: 611 | AJ13: 312 | AK13: 21 | AL13: 694 | AM13: 10 | AN13: 192 | AO13: 14 | AP13: 21 | AQ13: 224 | AR13: 460 | AS13: 359 | AT13: 101 | AU13: 239 | AV13: 243 | AW13: 157 | AX13: 193 | AY13: 150 | AZ13: 25 | BA13: 0.21 | BB13: 21.15 | BC13: 4787.94 | BD13: 47.87 | BE13: 7.6 | BF13: 41.7 | BG13: 229 | BH13: 24.6 | BI13: 703 | BJ13: 75.4 | BK13: 16.3 | BL13: 536 | BM13: 57.6 | BN13: 2.42 | BO13: 619 | BP13: 48.3 | BQ13: 32.1 | BR13: 33.5 | BS13: 51.1 | BT13: 24 | BU13: 49.4
A14: OUEST | B14: EPEULE | C14: Épeule Nord | D14: 794 | E14: 708 | F14: 5 | G14: 80 | H14: 205 | I14: 588 | J14: 19 | K14: 139 | L14: 229 | M14: 167 | N14: 154 | O14: 15 | P14: 81 | Q14: 221 | R14: 236 | S14: 94 | T14: 47 | U14: 14 | V14: 85 | W14: 114 | X14: 55 | Y14: 439 | Z14: 15 | AA14: 0 | AB14: 708 | AC14: 56 | AD14: 71 | AE14: 186 | AF14: 395 | AG14: 1947 | AH14: 130 | AI14: 575 | AJ14: 477 | AK14: 3 | AL14: 569 | AM14: 13 | AN14: 105 | AO14: 6 | AP14: 15 | AQ14: 84 | AR14: 340 | AS14: 288 | AT14: 52 | AU14: 223 | AV14: 149 | AW14: 67 | AX14: 63 | AY14: 86 | AZ14: 31 | BA14: 0.15 | BB14: 15.31 | BC14: 5183.67 | BD14: 51.83 | BE14: 10.1 | BF14: 25.8 | BG14: 157 | BH14: 22.2 | BI14: 551 | BJ14: 77.8 | BK14: 8 | BL14: 313 | BM14: 44.2 | BN14: 2.75 | BO14: 232 | BP14: 56 | BQ14: 18.3 | BR14: 67.3 | BS14: 82.8 | BT14: 11.8 | BU14: 48
... A40: SUD | B40: HAUTS CHAMPS/PETITES HAIES | C40: Hauts Champs | D40: 990 | E40: 915 | F40: 4 | G40: 72 | H40: 305 | I40: 679 | J40: 27 | K40: 177 | L40: 280 | M40: 256 | N40: 175 | O40: 8 | P40: 95 | Q40: 438 | R40: 185 | S40: 161 | T40: 20 | U40: 7 | V40: 1 | W40: 100 | X40: 589 | Y40: 124 | Z40: 49 | AA40: 52 | AB40: 915 | AC40: 72 | AD40: 156 | AE40: 181 | AF40: 505 | AG40: 2171 | AH40: 147 | AI40: 760 | AJ40: 665 | AK40: 8 | AL40: 822 | AM40: 17 | AN40: 47 | AO40: 0 | AP40: 29 | AQ40: 183 | AR40: 544 | AS40: 404 | AT40: 140 | AU40: 315 | AV40: 211 | AW40: 145 | AX40: 94 | AY40: 114 | AZ40: 26 | BA40: 0.31 | BB40: 31.34 | BC40: 3159.11 | BD40: 31.59 | BE40: 7.2 | BF40: 30.8 | BG40: 204 | BH40: 22.3 | BI40: 711 | BJ40: 77.7 | BK40: 7.9 | BL40: 410 | BM40: 44.8 | BN40: 2.37 | BO40: 250 | BP40: 58.9 | BQ40: 16.1 | BR40: 72.7 | BS40: 87.5 | BT40: 20 | BU40: 59.5

Sheet PETITE ENFANCE 2022
A1: Répartition pondérée des enfants par âge révolu et par IRIS | D1: =SUBTOTAL(9,D3:D40) | E1: =SUBTOTAL(9,E3:E40) | F1: =SUBTOTAL(9,F3:F40) | G1: =SUBTOTAL(9,G3:G40) | H1: =SUBTOTAL(9,H3:H40) | I1: =SUBTOTAL(9,I3:I40) | J1: =SUBTOTAL(9,J3:J40) | K1: =SUBTOTAL(9,K3:K40) | ... V1: =SUBTOTAL(9,V3:V40)
A2: Mairies de qartiers | B2: Quartiers SIG (Grands quartiers) | C2: Libellé de l'Iris | D2: Age : 0 | E2: Age : 1 | F2: Age : 2 | G2: Age : 3 | H2: Age : 4 | I2: Age : 5 | J2: Age : 6 | K2: Age : 7 | L2: Age : 8 | M2: Age : 9 | N2: Age : 10 | O2: Age : 11 | P2: Age : 12 | Q2: Age : 13 | R2: Age : 14 | S2: Age : 15 | T2: Age : 16 | U2: Age : 17 | V2: TOTAL 0-17
A3: OUEST | B3: FRESNOY MACKELLERIE | C3: Mackellerie | D3: 57 | E3: 42 | F3: 33 | G3: 64 | H3: 41 | I3: 47 | J3: 58 | K3: 34 | L3: 45 | M3: 52 | N3: 49 | O3: 51 | P3: 50 | Q3: 51 | R3: 39 | S3: 45 | T3: 21 | U3: 56 | V3: 835
A4: OUEST | B4: ARMENTIERES | C4: Fresnoy | D4: 54 | E4: 38 | F4: 35 | G4: 71 | H4: 36 | I4: 40 | J4: 57 | K4: 76 | L4: 58 | M4: 100 | N4: 59 | O4: 77 | P4: 31 | Q4: 80 | R4: 94 | S4: 64 | T4: 61 | U4: 55 | V4: 1086
A5: NORD | B5: FOSSE AUX CHENES | C5: Fosse aux Chênes | D5: 41 | E5: 67 | F5: 68 | G5: 44 | H5: 56 | I5: 48 | J5: 37 | K5: 46 | L5: 38 | M5: 33 | N5: 37 | O5: 25 | P5: 42 | Q5: 30 | R5: 41 | S5: 44 | T5: 43 | U5: 28 | V5: 768
A6: NORD | B6: ALMA GARE | C6: Alma Sud | D6: 36 | E6: 57 | F6: 17 | G6: 56 | H6: 37 | I6: 32 | J6: 21 | K6: 60 | L6: 43 | M6: 31 | N6: 75 | O6: 33 | P6: 32 | Q6: 37 | R6: 37 | S6: 32 | T6: 38 | U6: 48 | V6: 722
A7: NORD | B7: ALMA GARE | C7: Alma Nord | D7: 10 | E7: 17 | F7: 9 | G7: 15 | H7: 39 | I7: 24 | J7: 24 | K7: 27 | L7: 32 | M7: 31 | N7: 23 | O7: 11 | P7: 34 | Q7: 34 | R7: 24 | S7: 41 | T7: 34 | U7: 32 | V7: 461
A8: NORD | B8: ENTREPONT | C8: Entrepont-Cartigny | D8: 29 | E8: 34 | F8: 30 | G8: 42 | H8: 46 | I8: 67 | J8: 63 | K8: 70 | L8: 44 | M8: 47 | N8: 76 | O8: 18 | P8: 77 | Q8: 36 | R8: 47 | S8: 52 | T8: 60 | U8: 45 | V8: 883
A9: NORD | B9: HUTIN - ORAN - CARTIGNY | C9: Hutin-Oran | D9: 28 | E9: 24 | F9: 31 | G9: 26 | H9: 51 | I9: 38 | J9: 25 | K9: 42 | L9: 41 | M9: 37 | N9: 53 | O9: 43 | P9: 56 | Q9: 40 | R9: 60 | S9: 36 | T9: 38 | U9: 32 | V9: 701
A10: NORD | B10: CUL DE FOUR | C10: Cul de Four | D10: 56 | E10: 34 | F10: 49 | G10: 62 | H10: 33 | I10: 86 | J10: 48 | K10: 63 | L10: 89 | M10: 44 | N10: 84 | O10: 74 | P10: 77 | Q10: 104 | R10: 64 | S10: 71 | T10: 56 | U10: 101 | V10: 1195
A11: NORD | B11: HOMMELET | C11: Hommelet Nord | D11: 37 | E11: 59 | F11: 63 | G11: 59 | H11: 51 | I11: 56 | J11: 79 | K11: 34 | L11: 62 | M11: 38 | N11: 70 | O11: 70 | P11: 40 | Q11: 48 | R11: 66 | S11: 41 | T11: 36 | U11: 46 | V11: 955
A12: NORD | B12: HOMMELET | C12: Hommelet Centre | D12: 26 | E12: 26 | F12: 47 | G12: 50 | H12: 57 | I12: 39 | J12: 44 | K12: 38 | L12: 67 | M12: 66 | N12: 65 | O12: 50 | P12: 60 | Q12: 69 | R12: 47 | S12: 62 | T12: 64 | U12: 72 | V12: 949
A13: NORD | B13: HOMMELET | C13: Hommelet Sud | D13: 28 | E13: 27 | F13: 43 | G13: 46 | H13: 50 | I13: 21 | J13: 25 | K13: 75 | L13: 47 | M13: 37 | N13: 47 | O13: 17 | P13: 35 | Q13: 51 | R13: 64 | S13: 44 | T13: 54 | U13: 42 | V13: 753
A14: OUEST | B14: EPEULE | C14: Épeule Nord | D14: 9 | E14: 23 | F14: 38 | G14: 47 | H14: 8 | I14: 22 | J14: 33 | K14: 30 | L14: 32 | M14: 13 | N14: 35 | O14: 31 | P14: 28 | Q14: 7 | R14: 54 | S14: 23 | T14: 35 | U14: 39 | V14: 507
... A40: SUD | B40: HAUTS CHAMPS/PETITES HAIES | C40: Hauts Champs | D40: 30 | E40: 21 | F40: 41 | G40: 28 | H40: 47 | I40: 51 | J40: 30 | K40: 47 | L40: 24 | M40: 20 | N40: 40 | O40: 33 | P40: 59 | Q40: 56 | R40: 21 | S40: 32 | T40: 40 | U40: 16 | V40: 636

Sheet CAF 2024
A1: Bénéficiaires des prestations légales versées par les CAF | D1: =SUBTOTAL(9,D3:D40) | E1: =SUBTOTAL(9,E3:E40) | F1: =SUBTOTAL(9,F3:F40) | G1: =SUBTOTAL(9,G3:G40) | H1: =SUBTOTAL(9,H3:H40) | I1: =SUBTOTAL(9,I3:I40) | J1: =SUBTOTAL(9,J3:J40) | K1: =SUBTOTAL(9,K3:K40) | ... Z1: =SUBTOTAL(9,Z3:Z40)
A2: Mairies de quartiers | B2: Grands quartiers | C2: Libellé de l'Iris | D2: Nombre total d'allocataires | E2: Personnes couvertes | F2: Allocataires isolés sans enfant | G2: Allocataires mono-parent | H2: Allocataires couples sans enfant | I2: Allocataires couples avec enfant(s) | J2: Allocataires couples avec au moins 3 enfants à charge | K2: Enfants couverts par au moins une prestation Caf | L2: Enfants de moins de 3 ans | M2: Enfants de 3 à moins de 6 ans | N2: Enfants de 6 à moins de 11 ans | O2: Enfants de 11 à moins de 15 ans | P2: Enfants de 15 à moins de 18 ans | Q2: Enfants de 18 à moins de 25 ans | R2: Allocataires étudiants | S2: Allocataires de moins de 25 ans non étudiants | T2: Allocataires percevant une aide au logement | U2: Allocataires percevant l’Aide Personnalisée au Logement (Métropole) | V2: Allocataires percevant l’Allocation Adulte Handicapé | W2: Allocataires percevant la prime d'activité | X2: Allocataires percevant le RSA socle | Y2: Superficie en km² | Z2: Population (CAF) | AA2: Part de la population couverte par une allocation CAF (%) | AB2: Part des allocataires mono-parent (%) | AC2: Part des allocataires percevant l’APL (%) | AD2: Part des allocataires percevant l’AAH (%) | AE2: Part des allocataires bénéficiant du RSA socle (%)
A3: OUEST | B3: FRESNOY MACKELLERIE | C3: Mackellerie | D3: 865 | E3: 1931 | F3: 482 | G3: 149 | H3: 49 | I3: 196 | J3: 87 | K3: 834 | L3: 118 | M3: 112 | N3: 203 | O3: 179 | P3: 118 | Q3: 108 | R3: 136 | S3: 70 | T3: 532 | U3: 135 | V3: 84 | W3: 296 | X3: 249 | Y3: 0.32 | Z3: 2501 | AA3: 77.2 | AB3: 17.2 | AC3: 15.6 | AD3: 9.7 | AE3: 28.8
A4: OUEST | B4: ARMENTIERES | C4: Fresnoy | D4: 1810 | E4: 3130 | F4: 1317 | G4: 179 | H4: 59 | I4: 251 | J4: 101 | K4: 1009 | L4: 126 | M4: 122 | N4: 243 | O4: 214 | P4: 169 | Q4: 139 | R4: 662 | S4: 198 | T4: 1330 | U4: 450 | V4: 127 | W4: 441 | X4: 278 | Y4: 0.53 | Z4: 4280 | AA4: 73.1 | AB4: 9.9 | AC4: 24.9 | AD4: 7 | AE4: 15.4
A5: NORD | B5: FOSSE AUX CHENES | C5: Fosse aux Chênes | D5: 1135 | E5: 2393 | F5: 658 | G5: 173 | H5: 81 | I5: 218 | J5: 119 | K5: 983 | L5: 120 | M5: 143 | N5: 242 | O5: 211 | P5: 141 | Q5: 122 | R5: 36 | S5: 75 | T5: 756 | U5: 488 | V5: 168 | W5: 396 | X5: 320 | Y5: 0.41 | Z5: 2843 | AA5: 84.2 | AB5: 15.2 | AC5: 43 | AD5: 14.8 | AE5: 28.2
A6: NORD | B6: ALMA GARE | C6: Alma Sud | D6: 333 | E6: 747 | F6: 178 | G6: 55 | H6: 35 | I6: 69 | J6: 42 | K6: 321 | L6: 25 | M6: 44 | N6: 74 | O6: 71 | P6: 55 | Q6: 51 | R6: 0 | S6: 8 | T6: 221 | U6: 211 | V6: 49 | W6: 105 | X6: 121 | Y6: 0.09 | Z6: 1529 | AA6: 48.9 | AB6: 16.5 | AC6: 63.4 | AD6: 14.7 | AE6: 36.3
A7: NORD | B7: ALMA GARE | C7: Alma Nord | D7: 541 | E7: 1172 | F7: 324 | G7: 79 | H7: 28 | I7: 114 | J7: 71 | K7: 503 | L7: 63 | M7: 61 | N7: 125 | O7: 110 | P7: 71 | Q7: 74 | R7: 99 | S7: 55 | T7: 382 | U7: 219 | V7: 53 | W7: 144 | X7: 150 | Y7: 0.42 | Z7: 1613 | AA7: 72.7 | AB7: 14.6 | AC7: 40.5 | AD7: 9.8 | AE7: 27.7
A8: NORD | B8: ENTREPONT | C8: Entrepont-Cartigny | D8: 731 | E8: 1889 | F8: 339 | G8: 137 | H8: 39 | I8: 219 | J8: 118 | K8: 895 | L8: 96 | M8: 86 | N8: 226 | O8: 201 | P8: 147 | Q8: 137 | R8: 14 | S8: 73 | T8: 388 | U8: 197 | V8: 106 | W8: 269 | X8: 229 | Y8: 0.85 | Z8: 2372 | AA8: 79.6 | AB8: 18.7 | AC8: 26.9 | AD8: 14.5 | AE8: 31.3
A9: NORD | B9: HUTIN - ORAN - CARTIGNY | C9: Hutin-Oran | D9: 682 | E9: 1787 | F9: 298 | G9: 120 | H9: 37 | I9: 232 | J9: 103 | K9: 835 | L9: 99 | M9: 100 | N9: 187 | O9: 204 | P9: 141 | Q9: 110 | R9: 5 | S9: 33 | T9: 375 | U9: 224 | V9: 81 | W9: 258 | X9: 194 | Y9: 0.42 | Z9: 2166 | AA9: 82.5 | AB9: 17.6 | AC9: 32.8 | AD9: 11.9 | AE9: 28.4
A10: NORD | B10: CUL DE FOUR | C10: Cul de Four | D10: 914 | E10: 2426 | F10: 411 | G10: 188 | H10: 71 | I10: 251 | J10: 133 | K10: 1184 | L10: 115 | M10: 146 | N10: 283 | O10: 253 | P10: 189 | Q10: 184 | R10: 11 | S10: 62 | T10: 531 | U10: 282 | V10: 119 | W10: 357 | X10: 318 | Y10: 0.56 | Z10: 3471 | AA10: 69.9 | AB10: 20.6 | AC10: 30.9 | AD10: 13 | AE10: 34.8
A11: NORD | B11: HOMMELET | C11: Hommelet Nord | D11: 735 | E11: 1960 | F11: 305 | G11: 156 | H11: 47 | I11: 223 | J11: 120 | K11: 960 | L11: 130 | M11: 140 | N11: 240 | O11: 175 | P11: 151 | Q11: 132 | R11: 10 | S11: 57 | T11: 440 | U11: 195 | V11: 97 | W11: 262 | X11: 263 | Y11: 0.18 | Z11: 2308 | AA11: 84.9 | AB11: 21.2 | AC11: 26.5 | AD11: 13.2 | AE11: 35.8
A12: NORD | B12: HOMMELET | C12: Hommelet Centre | D12: 934 | E12: 2185 | F12: 482 | G12: 175 | H12: 67 | I12: 214 | J12: 110 | K12: 961 | L12: 96 | M12: 147 | N12: 232 | O12: 205 | P12: 138 | Q12: 132 | R12: 19 | S12: 64 | T12: 588 | U12: 379 | V12: 134 | W12: 312 | X12: 278 | Y12: 0.28 | Z12: 2774 | AA12: 78.8 | AB12: 18.7 | AC12: 40.6 | AD12: 14.3 | AE12: 29.8
A13: NORD | B13: HOMMELET | C13: Hommelet Sud | D13: 751 | E13: 1665 | F13: 419 | G13: 122 | H13: 53 | I13: 156 | J13: 75 | K13: 713 | L13: 88 | M13: 94 | N13: 162 | O13: 136 | P13: 112 | Q13: 114 | R13: 42 | S13: 56 | T13: 467 | U13: 217 | V13: 87 | W13: 289 | X13: 211 | Y13: 0.21 | Z13: 2353 | AA13: 70.7 | AB13: 16.2 | AC13: 28.9 | AD13: 11.6 | AE13: 28.1
A14: OUEST | B14: EPEULE | C14: Épeule Nord | D14: 471 | E14: 1107 | F14: 242 | G14: 83 | H14: 39 | I14: 103 | J14: 62 | K14: 487 | L14: 45 | M14: 64 | N14: 116 | O14: 113 | P14: 79 | Q14: 68 | R14: 13 | S14: 17 | T14: 308 | U14: 198 | V14: 75 | W14: 153 | X14: 150 | Y14: 0.15 | Z14: 1947 | AA14: 56.9 | AB14: 17.6 | AC14: 42 | AD14: 15.9 | AE14: 31.8
... A40: SUD | B40: HAUTS CHAMPS/PETITES HAIES | C40: Hauts Champs | D40: 807 | E40: 1785 | F40: 404 | G40: 170 | H40: 54 | I40: 175 | J40: 72 | K40: 739 | L40: 98 | M40: 110 | N40: 201 | O40: 130 | P40: 104 | Q40: 98 | R40: 6 | S40: 39 | T40: 560 | U40: 539 | V40: 110 | W40: 322 | X40: 218 | Y40: 0.31 | Z40: 2227 | AA40: 80.1 | AB40: 21.1 | AC40: 66.8 | AD40: 13.6 | AE40: 27

Sheet CNAM 2025
A1: Bénéficiaires du régime général de l’assurance maladie, dont bénéficiaires de la complémentaire santé solidaire | D1: =SUBTOTAL(9,D3:D40) | E1: =SUBTOTAL(9,E3:E40) | F1: =SUBTOTAL(9,F3:F40) | G1: =SUBTOTAL(9,G3:G40) | H1: =SUBTOTAL(9,H3:H40) | I1: =SUBTOTAL(9,I3:I40) | J1: =SUBTOTAL(9,J3:J40) | K1: =SUBTOTAL(9,K3:K40) | ... AC1: =SUBTOTAL(9,AC3:AC40)
A2: Mairies de quartiers | B2: Grands quartiers | C2: Libellé de l'Iris | D2: Population couverte | E2: Hommes | F2: Femmes | G2: Moins de 18 ans | H2: de 18 ans à moins de 25 ans | I2: de 25 ans à moins de 50 ans | J2: de 50 ans à moins de 60 ans | K2: de 60 ans à moins de 75 ans | L2: 75 ans ou plus | M2: Population couverte bénéficiaire de la C2S non participative | N2: Hommes bénéficiaires de la C2S non participative | O2: Femmes bénéficiaires de la C2S non participative | P2: Bénéficiaires de la C2S non participative de moins de 18 ans | Q2: Bénéficiaires de la C2S non participative de 18 ans à moins de 25 ans | R2: Bénéficiaires de la C2S non participative de 25 ans à moins de 50 ans | S2: Bénéficiaires de la C2S non participative de 50 ans à moins de 60 ans | T2: Bénéficiaires de la C2S non participative de 60 ans ou plus | U2: Population couverte bénéficiaire de la C2S participative | V2: Hommes bénéficiaires de la C2S participative | W2: Femmes bénéficiaires de la C2S participative | X2: Bénéficiaires de la C2S participative de moins de 18 ans | Y2: Bénéficiaires de la C2S participative de 18 ans à moins de 25 ans | Z2: Bénéficiaires de la C2S participative de 25 ans à moins de 50 ans | AA2: Bénéficiaires de la C2S participative de 50 ans à moins de 60 ans | AB2: Bénéficiaires de la C2S participative de 60 ans ou plus | AC2: Superficie en km²
A3: OUEST | B3: FRESNOY MACKELLERIE | C3: Mackellerie | D3: 2485 | E3: 1276 | F3: 1221 | G3: 698 | H3: 340 | I3: 862 | J3: 269 | K3: 230 | L3: 77 | M3: 874 | N3: 440 | O3: 424 | P3: 314 | Q3: 137 | R3: 282 | S3: 74 | T3: 50 | U3: 190 | V3: 82 | W3: 100 | X3: 73 | Y3: 27 | Z3: 55 | AA3: 27 | AB3: 28 | AC3: 0.32
A4: OUEST | B4: ARMENTIERES | C4: Fresnoy | D4: 3814 | E4: 1912 | F4: 1911 | G4: 794 | H4: 661 | I4: 1405 | J4: 425 | K4: 384 | L4: 135 | M4: 1006 | N4: 501 | O4: 517 | P4: 319 | Q4: 165 | R4: 382 | S4: 111 | T4: 54 | U4: 173 | V4: 69 | W4: 96 | X4: 43 | Y4: 16 | Z4: 41 | AA4: 24 | AB4: 48 | AC4: 0.53
A5: NORD | B5: FOSSE AUX CHENES | C5: Fosse aux Chênes | D5: 2964 | E5: 1467 | F5: 1487 | G5: 812 | H5: 352 | I5: 973 | J5: 347 | K5: 307 | L5: 165 | M5: 1221 | N5: 595 | O5: 636 | P5: 472 | Q5: 133 | R5: 416 | S5: 119 | T5: 84 | U5: 242 | V5: 117 | W5: 133 | X5: 55 | Y5: 23 | Z5: 39 | AA5: 36 | AB5: 86 | AC5: 0.41
A6: NORD | B6: ALMA GARE | C6: Alma Sud | D6: 1005 | E6: 509 | F6: 482 | G6: 264 | H6: 130 | I6: 298 | J6: 135 | K6: 140 | L6: 50 | M6: 456 | N6: 262 | O6: 206 | P6: 167 | Q6: 62 | R6: 126 | S6: 56 | T6: 42 | U6: 111 | V6: 55 | W6: 68 | X6: 34 | Y6: 33 | Z6: 14 | AA6: 13 | AB6: 43 | AC6: 0.09
A7: NORD | B7: ALMA GARE | C7: Alma Nord | D7: 1519 | E7: 779 | F7: 732 | G7: 396 | H7: 229 | I7: 491 | J7: 162 | K7: 141 | L7: 74 | M7: 626 | N7: 324 | O7: 291 | P7: 236 | Q7: 86 | R7: 201 | S7: 58 | T7: 44 | U7: 105 | V7: 48 | W7: 65 | X7: 40 | Y7: 13 | Z7: 16 | AA7: 0 | AB7: 35 | AC7: 0.42
A8: NORD | B8: ENTREPONT | C8: Entrepont-Cartigny | D8: 2646 | E8: 1381 | F8: 1255 | G8: 745 | H8: 371 | I8: 854 | J8: 288 | K8: 260 | L8: 137 | M8: 947 | N8: 498 | O8: 458 | P8: 344 | Q8: 141 | R8: 315 | S8: 98 | T8: 49 | U8: 146 | V8: 61 | W8: 76 | X8: 49 | Y8: 21 | Z8: 29 | AA8: 27 | AB8: 36 | AC8: 0.85
A9: NORD | B9: HUTIN - ORAN - CARTIGNY | C9: Hutin-Oran | D9: 2473 | E9: 1251 | F9: 1213 | G9: 694 | H9: 273 | I9: 825 | J9: 300 | K9: 246 | L9: 124 | M9: 735 | N9: 367 | O9: 360 | P9: 279 | Q9: 96 | R9: 252 | S9: 80 | T9: 29 | U9: 164 | V9: 82 | W9: 93 | X9: 51 | Y9: 22 | Z9: 35 | AA9: 19 | AB9: 40 | AC9: 0.42
A10: NORD | B10: CUL DE FOUR | C10: Cul de Four | D10: 3151 | E10: 1624 | F10: 1520 | G10: 969 | H10: 393 | I10: 965 | J10: 341 | K10: 333 | L10: 180 | M10: 1379 | N10: 689 | O10: 682 | P10: 567 | Q10: 181 | R10: 417 | S10: 113 | T10: 85 | U10: 238 | V10: 107 | W10: 140 | X10: 76 | Y10: 25 | Z10: 43 | AA10: 27 | AB10: 68 | AC10: 0.56
A11: NORD | B11: HOMMELET | C11: Hommelet Nord | D11: 2425 | E11: 1231 | F11: 1186 | G11: 734 | H11: 308 | I11: 801 | J11: 240 | K11: 226 | L11: 91 | M11: 938 | N11: 458 | O11: 472 | P11: 388 | Q11: 117 | R11: 307 | S11: 78 | T11: 50 | U11: 188 | V11: 71 | W11: 106 | X11: 59 | Y11: 18 | Z11: 45 | AA11: 14 | AB11: 49 | AC11: 0.18
A12: NORD | B12: HOMMELET | C12: Hommelet Centre | D12: 2855 | E12: 1456 | F12: 1407 | G12: 770 | H12: 347 | I12: 850 | J12: 344 | K12: 347 | L12: 182 | M12: 1057 | N12: 539 | O12: 505 | P12: 418 | Q12: 103 | R12: 330 | S12: 111 | T12: 74 | U12: 241 | V12: 110 | W12: 139 | X12: 62 | Y12: 23 | Z12: 38 | AA12: 25 | AB12: 74 | AC12: 0.28
A13: NORD | B13: HOMMELET | C13: Hommelet Sud | D13: 2261 | E13: 1168 | F13: 1082 | G13: 597 | H13: 274 | I13: 756 | J13: 259 | K13: 252 | L13: 111 | M13: 860 | N13: 426 | O13: 426 | P13: 313 | Q13: 111 | R13: 286 | S13: 93 | T13: 57 | U13: 187 | V13: 77 | W13: 101 | X13: 40 | Y13: 40 | Z13: 44 | AA13: 25 | AB13: 60 | AC13: 0.21
A14: OUEST | B14: EPEULE | C14: Épeule Nord | D14: 1542 | E14: 782 | F14: 769 | G14: 380 | H14: 176 | I14: 488 | J14: 179 | K14: 219 | L14: 111 | M14: 602 | N14: 302 | O14: 292 | P14: 226 | Q14: 62 | R14: 200 | S14: 38 | T14: 57 | U14: 165 | V14: 65 | W14: 112 | X14: 24 | Y14: 13 | Z14: 30 | AA14: 13 | AB14: 64 | AC14: 0.15
... A40: SUD | B40: HAUTS CHAMPS/PETITES HAIES | C40: Hauts Champs | D40: 2259 | E40: 1152 | F40: 1116 | G40: 609 | H40: 228 | I40: 771 | J40: 276 | K40: 232 | L40: 124 | M40: 838 | N40: 407 | O40: 439 | P40: 338 | Q40: 83 | R40: 311 | S40: 79 | T40: 23 | U40: 228 | V40: 109 | W40: 126 | X40: 77 | Y40: 25 | Z40: 63 | AA40: 22 | AB40: 58 | AC40: 0.31

Sheet DEFM 2024
A1: Demandeurs d'emploi au 31 décembre (données annuelles) | D1: =SUBTOTAL(9,D3:D40) | E1: =SUBTOTAL(9,E3:E40) | F1: =SUBTOTAL(9,F3:F40) | G1: =SUBTOTAL(9,G3:G40) | H1: =SUBTOTAL(9,H3:H40) | I1: =SUBTOTAL(9,I3:I40) | J1: =SUBTOTAL(9,J3:J40) | K1: =SUBTOTAL(9,K3:K40) | ... BE1: =SUBTOTAL(9,BE3:BE40)
A2: Mairies de quartiers | B2: Grands quartiers | C2: Libellé de l'Iris | D2: DEFM | E2: DEFM hommes | F2: DEFM femmes | G2: DEFM catégories ABC | H2: DEFM hommes catégories ABC | I2: DEFM femmes catégories ABC | J2: DEFM hommes catégorie A | K2: DEFM femmes catégorie A | L2: DEFM catégories ABC moins de 26 ans | M2: DEFM hommes catégories ABC moins de 26 ans | N2: DEFM femmes catégories ABC moins de 26 ans | O2: DEFM catégories ABC de 26 ans à moins de 50 ans | P2: DEFM hommes catégories ABC de 26 ans à moins de 50 ans | Q2: DEFM femmes catégories ABC de 26 ans à moins de 50 ans | R2: DEFM catégories ABC de 50 ans et plus | S2: DEFM hommes catégories ABC de 50 ans et plus | T2: DEFM femmes catégories ABC de 50 ans et plus | U2: DEFM catégories ABC nationalité française | V2: DEFM catégories ABC nationalité étrangère | W2: DEFM catégories ABC de niveau de formation inférieur au CAP-BEP | X2: DEFM hommes catégories ABC de niveau de formation inférieur au CAP-BEP | Y2: DEFM femmes catégories ABC de niveau de formation inférieur au CAP-BEP | Z2: DEFM catégories ABC de niveau de formation CAP-BEP | AA2: DEFM hommes catégories ABC de niveau de formation CAP-BEP | AB2: DEFM femmes catégories ABC de niveau de formation CAP-BEP | AC2: DEFM catégories ABC de niveau de formation BAC | AD2: DEFM hommes catégories ABC de niveau de formation BAC | AE2: DEFM femmes catégories ABC de niveau de formation BAC | AF2: DEFM catégories ABC de niveau de formation supérieur au BAC | AG2: DEFM hommes catégories ABC de niveau de formation supérieur au BAC | AH2: DEFM femmes catégories ABC de niveau de formation supérieur au BAC | AI2: DEFM catégories ABC d'ancienneté au chômage de moins de 6 mois | AJ2: DEFM hommes catégories ABC d'ancienneté au chômage de moins de 6 mois | AK2: DEFM femmes catégories ABC d'ancienneté au chômage de moins de 6 mois | AL2: DEFM catégories ABC d'ancienneté au chômage de 6 mois à moins d'1 an | AM2: DEFM hommes catégories ABC d'ancienneté au chômage de 6 mois à moins d'1 an | AN2: DEFM femmes catégories ABC d'ancienneté au chômage de 6 mois à moins d'1 an | AO2: DEFM catégories ABC d'ancienneté au chômage de 1 an à moins de 2 ans | AP2: DEFM hommes catégories ABC d'ancienneté au chômage de 1 an à moins de 2 ans | AQ2: DEFM femmes catégories ABC d'ancienneté au chômage de 1 an à moins de 2 ans | AR2: DEFM catégories ABC d'ancienneté au chômage d'au moins 2 ans | AS2: DEFM hommes catégories ABC d'ancienneté au chômage d'au moins 2 ans | AT2: DEFM femmes catégories ABC d'ancienneté au chômage d'au moins 2 ans | AU2: DEFM catégories ABC dont le motif d'inscription est une 1ère entrée sur le marché du travail | AV2: DEFM catégories ABC dont le motif d'inscription est un licenciement | AW2: DEFM catégories ABC dont le motif d'inscription est une fin de CDD | AX2: DEFM catégories ABC dont le motif d'inscription est une fin de mission d'intérim | AY2: DEFM catégories ABC dont le motif d'inscription est autre | AZ2: DEFM catégories ABC bénéficiaires du RSA | BA2: DEFM hommes catégories ABC bénéficiaires du RSA | BB2: DEFM femmes catégories ABC bénéficiaires du RSA | BC2: Nombre total d'allocataires | BD2: Superficie en km² | BE2: Population (DEFM) | BF2: Part des DEFM dans la population totale (%) | BG2: Part des DEFM hommes (%) | BH2: Part des DEFM femmes (%) | BI2: Part des DEFM catégorie ABC (tenus de faire une recherche d'emploi active) | BJ2: Part des DEFM ABC de moins de 26 ans (%) | BK2: Part des DEFM ABC de niveau ≤ au BAC dans les DEFM ABC (%) | BL2: Part des DEFM ABC au chômage depuis plus de 2 ans parmi les DEFM ABC (%) | BM2: Part des DEFM ABC au chômage depuis plus de 2 ans dans l'ensemble des chômeurs inscrits à PE (%) | BN2: Part des DEFM ABC bénéficiaires du RSA parmi les DEFM ABC (%) | BO2: Part des DEFM ABC bénéficiaires du RSA parmi l'ensemble des inscrits à PE (%)
A3: OUEST | B3: FRESNOY MACKELLERIE | C3: Mackellerie | D3: 425 | E3: 236 | F3: 193 | G3: 394 | H3: 219 | I3: 170 | J3: 150 | K3: 123 | L3: 70 | M3: 40 | N3: 38 | O3: 227 | P3: 129 | Q3: 101 | R3: 97 | S3: 53 | T3: 39 | U3: 268 | V3: 122 | W3: 109 | X3: 55 | Y3: 58 | Z3: 131 | AA3: 80 | AB3: 47 | AC3: 75 | AD3: 39 | AE3: 39 | AF3: 74 | AG3: 48 | AH3: 30 | AI3: 184 | AJ3: 94 | AK3: 87 | AL3: 68 | AM3: 33 | AN3: 32 | AO3: 76 | AP3: 40 | AQ3: 31 | AR3: 70 | AS3: 48 | AT3: 25 | AU3: 32 | AV3: 28 | AW3: 60 | AX3: 19 | AY3: 255 | AZ3: 196 | BA3: 108 | BB3: 84 | BC3: 276 | BD3: 0.32 | BE3: 2501 | BF3: 17 | BG3: 9.4 | BH3: 7.7 | BI3: 92.7 | BJ3: 17.8 | BK3: 79.9 | BL3: 17.8 | BM3: 16.5 | BN3: 49.7 | BO3: 46.1
A4: OUEST | B4: ARMENTIERES | C4: Fresnoy | D4: 612 | E4: 344 | F4: 272 | G4: 551 | H4: 307 | I4: 240 | J4: 194 | K4: 145 | L4: 82 | M4: 38 | N4: 51 | O4: 325 | P4: 190 | Q4: 140 | R4: 133 | S4: 79 | T4: 57 | U4: 436 | V4: 119 | W4: 115 | X4: 62 | Y4: 57 | Z4: 178 | AA4: 103 | AB4: 71 | AC4: 108 | AD4: 58 | AE4: 54 | AF4: 153 | AG4: 88 | AH4: 62 | AI4: 211 | AJ4: 116 | AK4: 91 | AL4: 117 | AM4: 69 | AN4: 52 | AO4: 116 | AP4: 67 | AQ4: 52 | AR4: 104 | AS4: 59 | AT4: 49 | AU4: 29 | AV4: 37 | AW4: 81 | AX4: 33 | AY4: 372 | AZ4: 231 | BA4: 118 | BB4: 109 | BC4: 343 | BD4: 0.53 | BE4: 4280 | BF4: 14.3 | BG4: 8 | BH4: 6.4 | BI4: 90 | BJ4: 14.9 | BK4: 72.8 | BL4: 18.9 | BM4: 17 | BN4: 41.9 | BO4: 37.7
A5: NORD | B5: FOSSE AUX CHENES | C5: Fosse aux Chênes | D5: 556 | E5: 309 | F5: 252 | G5: 516 | H5: 281 | I5: 238 | J5: 190 | K5: 169 | L5: 67 | M5: 35 | N5: 36 | O5: 309 | P5: 164 | Q5: 141 | R5: 139 | S5: 82 | T5: 53 | U5: 362 | V5: 158 | W5: 140 | X5: 69 | Y5: 67 | Z5: 172 | AA5: 112 | AB5: 57 | AC5: 115 | AD5: 58 | AE5: 60 | AF5: 86 | AG5: 38 | AH5: 51 | AI5: 237 | AJ5: 127 | AK5: 105 | AL5: 87 | AM5: 51 | AN5: 41 | AO5: 85 | AP5: 43 | AQ5: 46 | AR5: 102 | AS5: 65 | AT5: 42 | AU5: 23 | AV5: 30 | AW5: 71 | AX5: 21 | AY5: 370 | AZ5: 271 | BA5: 142 | BB5: 125 | BC5: 354 | BD5: 0.41 | BE5: 2843 | BF5: 19.6 | BG5: 10.9 | BH5: 8.9 | BI5: 92.8 | BJ5: 13 | BK5: 82.8 | BL5: 19.8 | BM5: 18.3 | BN5: 52.5 | BO5: 48.7
A6: NORD | B6: ALMA GARE | C6: Alma Sud | D6: 205 | E6: 122 | F6: 78 | G6: 183 | H6: 112 | I6: 74 | J6: 80 | K6: 49 | L6: 19 | M6: 16 | N6: 6 | O6: 105 | P6: 69 | Q6: 42 | R6: 56 | S6: 29 | T6: 34 | U6: 117 | V6: 69 | W6: 51 | X6: 26 | Y6: 30 | Z6: 72 | AA6: 45 | AB6: 24 | AC6: 54 | AD6: 33 | AE6: 17 | AF6: 17 | AG6: 6 | AH6: 7 | AI6: 65 | AJ6: 39 | AK6: 30 | AL6: 36 | AM6: 22 | AN6: 11 | AO6: 42 | AP6: 28 | AQ6: 19 | AR6: 43 | AS6: 20 | AT6: 19 | AU6: 13 | AV6: 5 | AW6: 28 | AX6: 11 | AY6: 125 | AZ6: 90 | BA6: 51 | BB6: 44 | BC6: 126 | BD6: 0.09 | BE6: 1529 | BF6: 13.4 | BG6: 8 | BH6: 5.1 | BI6: 89.3 | BJ6: 10.4 | BK6: 96.7 | BL6: 23.5 | BM6: 21 | BN6: 49.2 | BO6: 43.9
A7: NORD | B7: ALMA GARE | C7: Alma Nord | D7: 265 | E7: 160 | F7: 110 | G7: 241 | H7: 138 | I7: 99 | J7: 107 | K7: 65 | L7: 41 | M7: 27 | N7: 17 | O7: 139 | P7: 81 | Q7: 62 | R7: 62 | S7: 36 | T7: 21 | U7: 166 | V7: 70 | W7: 51 | X7: 27 | Y7: 29 | Z7: 90 | AA7: 64 | AB7: 22 | AC7: 58 | AD7: 33 | AE7: 19 | AF7: 39 | AG7: 21 | AH7: 23 | AI7: 100 | AJ7: 64 | AK7: 41 | AL7: 45 | AM7: 28 | AN7: 13 | AO7: 45 | AP7: 25 | AQ7: 16 | AR7: 47 | AS7: 25 | AT7: 25 | AU7: 14 | AV7: 17 | AW7: 29 | AX7: 9 | AY7: 162 | AZ7: 123 | BA7: 72 | BB7: 56 | BC7: 176 | BD7: 0.42 | BE7: 1613 | BF7: 16.4 | BG7: 9.9 | BH7: 6.8 | BI7: 90.9 | BJ7: 17 | BK7: 82.6 | BL7: 19.5 | BM7: 17.7 | BN7: 51 | BO7: 46.4
A8: NORD | B8: ENTREPONT | C8: Entrepont-Cartigny | D8: 421 | E8: 238 | F8: 186 | G8: 366 | H8: 217 | I8: 155 | J8: 150 | K8: 115 | L8: 69 | M8: 41 | N8: 32 | O8: 209 | P8: 121 | Q8: 91 | R8: 90 | S8: 53 | T8: 33 | U8: 273 | V8: 98 | W8: 95 | X8: 49 | Y8: 49 | Z8: 131 | AA8: 90 | AB8: 37 | AC8: 90 | AD8: 45 | AE8: 49 | AF8: 56 | AG8: 34 | AH8: 26 | AI8: 180 | AJ8: 100 | AK8: 76 | AL8: 73 | AM8: 42 | AN8: 26 | AO8: 61 | AP8: 30 | AQ8: 27 | AR8: 58 | AS8: 38 | AT8: 24 | AU8: 24 | AV8: 27 | AW8: 53 | AX8: 24 | AY8: 241 | AZ8: 179 | BA8: 105 | BB8: 77 | BC8: 269 | BD8: 0.85 | BE8: 2372 | BF8: 17.8 | BG8: 10 | BH8: 7.8 | BI8: 86.9 | BJ8: 18.9 | BK8: 86.3 | BL8: 15.8 | BM8: 13.8 | BN8: 48.9 | BO8: 42.5
A9: NORD | B9: HUTIN - ORAN - CARTIGNY | C9: Hutin-Oran | D9: 391 | E9: 213 | F9: 174 | G9: 360 | H9: 195 | I9: 168 | J9: 125 | K9: 120 | L9: 56 | M9: 19 | N9: 33 | O9: 206 | P9: 116 | Q9: 94 | R9: 107 | S9: 61 | T9: 41 | U9: 282 | V9: 82 | W9: 80 | X9: 45 | Y9: 40 | Z9: 128 | AA9: 77 | AB9: 46 | AC9: 82 | AD9: 43 | AE9: 44 | AF9: 57 | AG9: 28 | AH9: 33 | AI9: 138 | AJ9: 83 | AK9: 58 | AL9: 68 | AM9: 32 | AN9: 32 | AO9: 75 | AP9: 42 | AQ9: 37 | AR9: 83 | AS9: 42 | AT9: 44 | AU9: 22 | AV9: 37 | AW9: 37 | AX9: 32 | AY9: 240 | AZ9: 154 | BA9: 79 | BB9: 71 | BC9: 238 | BD9: 0.42 | BE9: 2166 | BF9: 18 | BG9: 9.8 | BH9: 8 | BI9: 92.1 | BJ9: 15.6 | BK9: 80.6 | BL9: 23.1 | BM9: 21.2 | BN9: 42.8 | BO9: 39.4
A10: NORD | B10: CUL DE FOUR | C10: Cul de Four | D10: 534 | E10: 304 | F10: 233 | G10: 483 | H10: 272 | I10: 216 | J10: 189 | K10: 153 | L10: 77 | M10: 38 | N10: 36 | O10: 266 | P10: 144 | Q10: 118 | R10: 140 | S10: 90 | T10: 53 | U10: 336 | V10: 152 | W10: 144 | X10: 73 | Y10: 65 | Z10: 177 | AA10: 113 | AB10: 67 | AC10: 91 | AD10: 45 | AE10: 42 | AF10: 67 | AG10: 37 | AH10: 26 | AI10: 186 | AJ10: 102 | AK10: 79 | AL10: 105 | AM10: 73 | AN10: 39 | AO10: 100 | AP10: 41 | AQ10: 54 | AR10: 95 | AS10: 61 | AT10: 39 | AU10: 36 | AV10: 26 | AW10: 56 | AX10: 21 | AY10: 343 | AZ10: 266 | BA10: 139 | BB10: 131 | BC10: 346 | BD10: 0.56 | BE10: 3471 | BF10: 15.4 | BG10: 8.8 | BH10: 6.7 | BI10: 90.4 | BJ10: 15.9 | BK10: 85.3 | BL10: 19.7 | BM10: 17.8 | BN10: 55.1 | BO10: 49.8
A11: NORD | B11: HOMMELET | C11: Hommelet Nord | D11: 392 | E11: 219 | F11: 177 | G11: 360 | H11: 204 | I11: 161 | J11: 134 | K11: 123 | L11: 65 | M11: 40 | N11: 29 | O11: 217 | P11: 116 | Q11: 98 | R11: 85 | S11: 47 | T11: 34 | U11: 267 | V11: 98 | W11: 81 | X11: 50 | Y11: 35 | Z11: 137 | AA11: 79 | AB11: 55 | AC11: 94 | AD11: 54 | AE11: 45 | AF11: 46 | AG11: 28 | AH11: 24 | AI11: 173 | AJ11: 105 | AK11: 72 | AL11: 62 | AM11: 38 | AN11: 28 | AO11: 71 | AP11: 38 | AQ11: 37 | AR11: 51 | AS11: 27 | AT11: 27 | AU11: 23 | AV11: 20 | AW11: 46 | AX11: 23 | AY11: 247 | AZ11: 192 | BA11: 102 | BB11: 87 | BC11: 252 | BD11: 0.18 | BE11: 2308 | BF11: 17 | BG11: 9.5 | BH11: 7.7 | BI11: 91.8 | BJ11: 18.1 | BK11: 86.7 | BL11: 14.2 | BM11: 13 | BN11: 53.3 | BO11: 49
A12: NORD | B12: HOMMELET | C12: Hommelet Centre | D12: 738 | E12: 464 | F12: 277 | G12: 666 | H12: 421 | I12: 249 | J12: 298 | K12: 170 | L12: 87 | M12: 39 | N12: 52 | O12: 398 | P12: 261 | Q12: 140 | R12: 182 | S12: 131 | T12: 57 | U12: 482 | V12: 176 | W12: 175 | X12: 106 | Y12: 73 | Z12: 278 | AA12: 196 | AB12: 78 | AC12: 141 | AD12: 86 | AE12: 58 | AF12: 73 | AG12: 30 | AH12: 39 | AI12: 297 | AJ12: 187 | AK12: 114 | AL12: 125 | AM12: 73 | AN12: 48 | AO12: 118 | AP12: 69 | AQ12: 46 | AR12: 129 | AS12: 88 | AT12: 47 | AU12: 42 | AV12: 44 | AW12: 59 | AX12: 57 | AY12: 465 | AZ12: 381 | BA12: 250 | BB12: 135 | BC12: 473 | BD12: 0.28 | BE12: 2774 | BF12: 26.6 | BG12: 16.7 | BH12: 10 | BI12: 90.2 | BJ12: 13.1 | BK12: 89.2 | BL12: 19.4 | BM12: 17.5 | BN12: 57.2 | BO12: 51.6
A13: NORD | B13: HOMMELET | C13: Hommelet Sud | D13: 406 | E13: 235 | F13: 175 | G13: 374 | H13: 212 | I13: 158 | J13: 159 | K13: 106 | L13: 50 | M13: 26 | N13: 20 | O13: 210 | P13: 126 | Q13: 80 | R13: 122 | S13: 60 | T13: 58 | U13: 252 | V13: 125 | W13: 104 | X13: 57 | Y13: 51 | Z13: 128 | AA13: 82 | AB13: 52 | AC13: 71 | AD13: 42 | AE13: 34 | AF13: 65 | AG13: 28 | AH13: 32 | AI13: 168 | AJ13: 99 | AK13: 72 | AL13: 61 | AM13: 39 | AN13: 26 | AO13: 80 | AP13: 53 | AQ13: 30 | AR13: 70 | AS13: 32 | AT13: 33 | AU13: 18 | AV13: 28 | AW13: 40 | AX13: 22 | AY13: 264 | AZ13: 176 | BA13: 109 | BB13: 64 | BC13: 269 | BD13: 0.21 | BE13: 2353 | BF13: 17.3 | BG13: 10 | BH13: 7.4 | BI13: 92.1 | BJ13: 13.4 | BK13: 81 | BL13: 18.7 | BM13: 17.2 | BN13: 47.1 | BO13: 43.3
A14: OUEST | B14: EPEULE | C14: Épeule Nord | D14: 271 | E14: 142 | F14: 125 | G14: 248 | H14: 133 | I14: 119 | J14: 93 | K14: 81 | L14: 28 | M14: 11 | N14: 13 | O14: 151 | P14: 85 | Q14: 60 | R14: 70 | S14: 37 | T14: 36 | U14: 149 | V14: 95 | W14: 71 | X14: 40 | Y14: 34 | Z14: 82 | AA14: 52 | AB14: 33 | AC14: 39 | AD14: 24 | AE14: 19 | AF14: 51 | AG14: 20 | AH14: 26 | AI14: 101 | AJ14: 58 | AK14: 47 | AL14: 38 | AM14: 18 | AN14: 23 | AO14: 48 | AP14: 26 | AQ14: 27 | AR14: 50 | AS14: 27 | AT14: 27 | AU14: 12 | AV14: 22 | AW14: 33 | AX14: 12 | AY14: 169 | AZ14: 126 | BA14: 68 | BB14: 54 | BC14: 171 | BD14: 0.15 | BE14: 1947 | BF14: 13.9 | BG14: 7.3 | BH14: 6.4 | BI14: 91.5 | BJ14: 11.3 | BK14: 77.4 | BL14: 20.2 | BM14: 18.5 | BN14: 50.8 | BO14: 46.5
... A40: SUD | B40: HAUTS CHAMPS/PETITES HAIES | C40: Hauts Champs | D40: 456 | E40: 247 | F40: 212 | G40: 397 | H40: 211 | I40: 183 | J40: 142 | K40: 126 | L40: 55 | M40: 36 | N40: 22 | O40: 239 | P40: 135 | Q40: 108 | R40: 104 | S40: 48 | T40: 52 | U40: 302 | V40: 91 | W40: 85 | X40: 40 | Y40: 39 | Z40: 151 | AA40: 86 | AB40: 69 | AC40: 102 | AD40: 49 | AE40: 49 | AF40: 56 | AG40: 30 | AH40: 29 | AI40: 165 | AJ40: 84 | AK40: 84 | AL40: 62 | AM40: 35 | AN40: 23 | AO40: 84 | AP40: 43 | AQ40: 36 | AR40: 82 | AS40: 43 | AT40: 43 | AU40: 19 | AV40: 28 | AW40: 46 | AX40: 24 | AY40: 272 | AZ40: 191 | BA40: 88 | BB40: 99 | BC40: 264 | BD40: 0.31 | BE40: 2227 | BF40: 20.5 | BG40: 11.1 | BH40: 9.5 | BI40: 87.1 | BJ40: 13.9 | BK40: 85.1 | BL40: 20.7 | BM40: 18 | BN40: 48.1 | BO40: 41.9

Sheet RPLS 2025
A1: Répertoire du Parc Locatif Social (RPLS) | D1: =SUBTOTAL(9,D3:D40) | E1: =SUBTOTAL(9,E3:E40) | AL1: =SUBTOTAL(9,AL3:AL40)
A2: Mairies de quartiers | B2: Grands quartiers | C2: Libellé de l'Iris | D2: Nombre de logements du Parc Locatif Social | E2: Nombre de logements sociaux mis en service dans l’année | F2: Taux de vacance des logements sociaux | G2: Taux de vacance de plus de 3 mois des logements sociaux | H2: Taux de rotation des logements sociaux | I2: Part des logements sociaux collectifs | J2: Part des logements sociaux individuels | K2: Part des logements sociaux d’une pièce | L2: Part des logements sociaux de deux pièces | M2: Part des logements sociaux de trois pièces | N2: Part des logements sociaux de quatre pièces | O2: Part des logements sociaux de 5 pièces ou plus | P2: Part des logements sociaux de moins de 30 m² | Q2: Part des logements sociaux de 30 m² à moins de 40 m² | R2: Part des logements sociaux de 40 m² à moins de 60 m² | S2: Part des logements sociaux de 60 m² à moins de 80 m² | T2: Part des logements sociaux de 80 m² à moins de 100 m² | U2: Part des logements sociaux de 100 m² à moins de 120 m² | V2: Part des logements sociaux de plus de 120 m² | W2: Part des logements sociaux construits avant 1949 | X2: Part des logements sociaux construits entre 1949 et 1975 | Y2: Part des logements sociaux construits entre 1976 et 1988 | Z2: Part des logements sociaux construits entre 1989 et 2000 | AA2: Part des logements sociaux construits entre 2001 et 2013 | AB2: Part des logements sociaux construits après 2013 | AC2: Part des logements sociaux financés en PLAI | AD2: Part des logements sociaux financés en PLUS (avant 1977) | AE2: Part des logements sociaux financés en PLUS (après 1977) | AF2: Part des logements sociaux financés en PLS | AG2: Part des logements sociaux financés en PLI | AH2: Loyer par m² des logements sociaux - Moyenne | AI2: Loyer par m² des logements sociaux - 1er quartile | AJ2: Loyer par m² des logements sociaux - Médiane | AK2: Loyer par m² des logements sociaux - 3ème quartile | AL2: Superficie en km²
A3: OUEST | B3: FRESNOY MACKELLERIE | C3: Mackellerie | D3: 306 | E3: 43 | F3: 5.5 | G3: 0 | H3: 8.7 | I3: 86 | J3: 14 | K3: 29.2 | L3: 16.2 | M3: 31.8 | N3: 12.3 | O3: 10.4 | P3: 0 | Q3: 31.4 | R3: 12.5 | S3: 33.3 | T3: 18.3 | U3: 4.5 | V3: 0 | W3: 7.9 | X3: 22.1 | Y3: 25.2 | Z3: 4.5 | AA3: 25.8 | AB3: 14.5 | AC3: 4.1 | AD3: 48 | AE3: 48 | AF3: 0 | AG3: 0 | AH3: 6.11 | AI3: 5.52 | AJ3: 6.12 | AK3: 6.62 | AL3: 0.32
A4: OUEST | B4: ARMENTIERES | C4: Fresnoy | D4: 446 | E4: 105 | F4: 23.4 | G4: 23.1 | H4: 6.4 | I4: 64.7 | J4: 35.3 | K4: 25.3 | L4: 17.2 | M4: 18.8 | N4: 27.5 | O4: 11.2 | P4: 24 | Q4: 2.8 | R4: 15.7 | S4: 24 | T4: 30.7 | U4: 2.8 | V4: 0 | W4: 9.4 | X4: 6.8 | Y4: 4.8 | Z4: 15.7 | AA4: 40.2 | AB4: 23.1 | AC4: 10.9 | AD4: 4.6 | AE4: 51.9 | AF4: 29.8 | AG4: 2.7 | AH4: 6.79 | AI4: 6.14 | AJ4: 6.73 | AK4: 7.33 | AL4: 0.53
A5: NORD | B5: FOSSE AUX CHENES | C5: Fosse aux Chênes | D5: 702 | E5: 0 | F5: 0 | G5: 0 | H5: 5.3 | I5: 93.6 | J5: 6.4 | K5: 14.1 | L5: 20.7 | M5: 38.2 | N5: 17.9 | O5: 9.1 | P5: 0 | Q5: 8.3 | R5: 43.8 | S5: 32.4 | T5: 13.6 | U5: 1.9 | V5: 0 | W5: 2.5 | X5: 16.6 | Y5: 60.3 | Z5: 16.5 | AA5: 2.5 | AB5: 1.6 | AC5: 16.8 | AD5: 0 | AE5: 83.2 | AF5: 0 | AG5: 0 | AH5: 6.87 | AI5: 6.28 | AJ5: 6.79 | AK5: 7.38 | AL5: 0.41
A6: NORD | B6: ALMA GARE | C6: Alma Sud | D6: 566 | E6: 0 | F6: 0 | G6: 0 | H6: 0 | I6: 86.8 | J6: 13.2 | K6: 9.2 | L6: 21 | M6: 32.3 | N6: 25.3 | O6: 12.2 | P6: 2 | Q6: 7.1 | R6: 23.2 | S6: 31.6 | T6: 28.3 | U6: 5.6 | V6: 2.2 | W6: 0 | X6: 5.8 | Y6: 87.8 | Z6: 2.3 | AA6: 4.1 | AB6: 0 | AC6: 0 | AD6: 35.9 | AE6: 56.7 | AF6: 7.4 | AG6: 0 | AH6: 5.69 | AI6: 5.03 | AJ6: 5.56 | AK6: 6.37 | AL6: 0.09
A7: NORD | B7: ALMA GARE | C7: Alma Nord | D7: 326 | E7: 0 | F7: 0 | G7: 0 | H7: 0 | I7: 67.1 | J7: 32.9 | K7: 8.4 | L7: 25.9 | M7: 27 | N7: 28.5 | O7: 10.2 | P7: 0 | Q7: 4.6 | R7: 19.3 | S7: 42.8 | T7: 23.2 | U7: 6.7 | V7: 3.4 | W7: 0 | X7: 11.5 | Y7: 77.9 | Z7: 0 | AA7: 10.6 | AB7: 0 | AC7: 3.8 | AD7: 0 | AE7: 96.2 | AF7: 0 | AG7: 0 | AH7: 6.06 | AI7: 5.69 | AJ7: 6.23 | AK7: 6.64 | AL7: 0.42
A8: NORD | B8: ENTREPONT | C8: Entrepont-Cartigny | D8: 157 | E8: 0 | F8: 0 | G8: 0 | H8: 7.5 | I8: 70 | J8: 30 | K8: 0 | L8: 18.3 | M8: 34.1 | N8: 25.6 | O8: 22 | P8: 0 | Q8: 0 | R8: 17.3 | S8: 42.7 | T8: 22.7 | U8: 8.7 | V8: 8.7 | W8: 12.1 | X8: 7 | Y8: 0 | Z8: 7.6 | AA8: 41.4 | AB8: 31.8 | AC8: 19 | AD8: 0 | AE8: 73.2 | AF8: 0 | AG8: 7.7 | AH8: 6.26 | AI8: 5.5 | AJ8: 6.45 | AK8: 6.98 | AL8: 0.85
A9: NORD | B9: HUTIN - ORAN - CARTIGNY | C9: Hutin-Oran | D9: 487 | E9: 13 | F9: 4.6 | G9: 4.3 | H9: 9.7 | I9: 88 | J9: 12 | K9: 7.2 | L9: 34 | M9: 42 | N9: 9.7 | O9: 7 | P9: 0 | Q9: 14.3 | R9: 59 | S9: 8.7 | T9: 13.3 | U9: 2.2 | V9: 2.6 | W9: 3 | X9: 66.5 | Y9: 11.2 | Z9: 0 | AA9: 16.5 | AB9: 2.8 | AC9: 2.3 | AD9: 50 | AE9: 32.1 | AF9: 0 | AG9: 15.6 | AH9: 6.3 | AI9: 5.69 | AJ9: 6.31 | AK9: 6.83 | AL9: 0.42
A10: NORD | B10: CUL DE FOUR | C10: Cul de Four | D10: 439 | E10: 0 | F10: 3.5 | G10: 0 | H10: 7.7 | I10: 78.8 | J10: 21.2 | K10: 10.2 | L10: 24.4 | M10: 36.4 | N10: 18.1 | O10: 10.9 | P10: 0 | Q10: 5.3 | R10: 47.2 | S10: 20.1 | T10: 19.9 | U10: 5.1 | V10: 2.4 | W10: 13.2 | X10: 23.4 | Y10: 35.5 | Z10: 25.2 | AA10: 2.7 | AB10: 0 | AC10: 4 | AD10: 34.7 | AE10: 52.9 | AF10: 0 | AG10: 8.4 | AH10: 6.43 | AI10: 5.84 | AJ10: 6.32 | AK10: 6.94 | AL10: 0.56
A11: NORD | B11: HOMMELET | C11: Hommelet Nord | D11: 242 | E11: 0 | F11: 0 | G11: 0 | H11: 0 | I11: 68.9 | J11: 31.1 | K11: 0 | L11: 18.7 | M11: 58.6 | N11: 13.2 | O11: 9.5 | P11: 0 | Q11: 0 | R11: 52.6 | S11: 23.9 | T11: 15.4 | U11: 8.1 | V11: 0 | W11: 10.8 | X11: 29.2 | Y11: 13.6 | Z11: 0 | AA11: 16.8 | AB11: 29.6 | AC11: 15.8 | AD11: 32 | AE11: 52.2 | AF11: 0 | AG11: 0 | AH11: 6.14 | AI11: 5.81 | AJ11: 6.04 | AK11: 6.43 | AL11: 0.18
A12: NORD | B12: HOMMELET | C12: Hommelet Centre | D12: 470 | E12: 0 | F12: 0 | G12: 0 | H12: 6.5 | I12: 88.1 | J12: 11.9 | K12: 4.5 | L12: 26.9 | M12: 43.5 | N12: 21.3 | O12: 3.8 | P12: 0 | Q12: 2.6 | R12: 28.9 | S12: 34.6 | T12: 33.9 | U12: 0 | V12: 0 | W12: 4.1 | X12: 47.3 | Y12: 39.2 | Z12: 0 | AA12: 3.9 | AB12: 5.6 | AC12: 2.6 | AD12: 42.7 | AE12: 54.7 | AF12: 0 | AG12: 0 | AH12: 5.47 | AI12: 4.74 | AJ12: 5.18 | AK12: 6.14 | AL12: 0.28
A13: NORD | B13: HOMMELET | C13: Hommelet Sud | D13: 364 | E13: 0 | F13: 3.2 | G13: 3.4 | H13: 3.7 | I13: 90.8 | J13: 9.2 | K13: 4.7 | L13: 33.9 | M13: 47.1 | N13: 8.5 | O13: 5.8 | P13: 0 | Q13: 6.5 | R13: 37.6 | S13: 31.1 | T13: 18.4 | U13: 3.6 | V13: 2.8 | W13: 4.2 | X13: 44.5 | Y13: 51.3 | Z13: 0 | AA13: 0 | AB13: 0 | AC13: 0 | AD13: 32.6 | AE13: 67.4 | AF13: 0 | AG13: 0 | AH13: 6.38 | AI13: 5.95 | AJ13: 6.25 | AK13: 6.87 | AL13: 0.21
A14: OUEST | B14: EPEULE | C14: Épeule Nord | D14: 461 | E14: 0 | F14: 0 | G14: 0 | H14: 4.2 | I14: 97.7 | J14: 2.3 | K14: 7.4 | L14: 30.4 | M14: 44.9 | N14: 14.7 | O14: 2.6 | P14: 0 | Q14: 5.5 | R14: 36.8 | S14: 49.9 | T14: 5.5 | U14: 0 | V14: 2.3 | W14: 2.4 | X14: 54.4 | Y14: 43.3 | Z14: 0 | AA14: 0 | AB14: 0 | AC14: 0 | AD14: 100 | AE14: 0 | AF14: 0 | AG14: 0 | AH14: 5.57 | AI14: 5.2 | AJ14: 5.47 | AK14: 5.94 | AL14: 0.15
A15: OUEST | B15: EPEULE | C15: Épeule Centre | D15: 441 | E15: 0 | F15: 2.7 | G15: 0 | H15: 4.8 | I15: 84.9 | J15: 15.1 | K15: 5.7 | L15: 29.7 | M15: 42.4 | N15: 18.1 | O15: 4.1 | P15: 0 | Q15: 2.5 | R15: 32.8 | S15: 28.7 | T15: 32.3 | U15: 3.7 | V15: 0 | W15: 15 | X15: 72.8 | Y15: 2.4 | Z15: 0 | AA15: 0 | AB15: 9.8 | AC15: 10 | AD15: 70.7 | AE15: 16.2 | AF15: 0 | AG15: 3.1 | AH15: 5.42 | AI15: 4.88 | AJ15: 5.34 | AK15: 5.88 | AL15: 0.2
A16: OUEST | B16: EPEULE | C16: Épeule Sud | D16: 108 | E16: 0 | H16: 10.3 | J16: 13.3 | S16: 29.9 | T16: 34.2 | U16: 10.3 | W16: 17 | AC16: 12.9 | AD16: 8.9 | AF16: 0 | AG16: 0 | AH16: 6.05 | AI16: 5.51 | AJ16: 5.97 | AK16: 6.61 | AL16: 0.15
A17: OUEST | B17: TRICHON | C17: Trichon | D17: 358 | E17: 0 | F17: 0 | G17: 0 | H17: 4.8 | I17: 81.8 | J17: 18.2 | K17: 6.1 | L17: 24.9 | M17: 37.1 | N17: 16.3 | O17: 15.5 | P17: 0 | Q17: 3.4 | R17: 23.2 | S17: 38.7 | T17: 19.5 | U17: 12 | V17: 3.2 | W17: 6.2 | X17: 0 | Y17: 54.9 | Z17: 13.6 | AA17: 13.9 | AB17: 11.4 | AC17: 10.1 | AD17: 0 | AE17: 86.9 | AF17: 0 | AG17: 3.1 | AH17: 6.49 | AI17: 6.09 | AJ17: 6.63 | AK17: 6.91 | AL17: 0.33
A18: CENTRE | B18: ESPERANCE/CROUY/CENTRE VILLE | C18: Espérance Centre | D18: 453 | E18: 0 | F18: 5 | G18: 4.3 | H18: 5.7 | I18: 95.3 | J18: 4.7 | K18: 17.2 | L18: 23 | M18: 43.8 | N18: 10.2 | O18: 5.8 | P18: 4.8 | Q18: 13.7 | R18: 24.6 | S18: 41.8 | T18: 12 | U18: 3.1 | V18: 0 | W18: 5 | X18: 5.2 | Y18: 19.3 | Z18: 6 | AA18: 37.2 | AB18: 27.2 | AC18: 9.2 | AD18: 0 | AE18: 72.5 | AF18: 6.7 | AG18: 11.6 | AH18: 7.61 | AI18: 6.7 | AJ18: 7.28 | AK18: 8.32 | AL18: 0.45
A19: CENTRE | B19: NATIONS UNIES | C19: Nations Unies | D19: 797 | E19: 0 | F19: 2.2 | G19: 1.7 | H19: 5.7 | I19: 98.6 | J19: 1.4 | K19: 13.6 | L19: 37.7 | M19: 35.1 | N19: 7.7 | O19: 5.9 | P19: 11.1 | Q19: 11.6 | R19: 33.6 | S19: 30.5 | T19: 9.8 | U19: 3.3 | V19: 0 | W19: 0 | X19: 16.3 | Y19: 37.2 | Z19: 22.8 | AA19: 23.7 | AB19: 0 | AC19: 3.6 | AD19: 17 | AE19: 64.4 | AF19: 15 | AG19: 0 | AH19: 7.26 | AI19: 6.8 | AJ19: 7.22 | AK19: 7.66 | AL19: 0.32
A20: CENTRE | B20: ANSEELE MOTTE BOSSUT | C20: Anseele | D20: 1398 | E20: 0 | F20: 0 | G20: 0.9 | H20: 7.8 | I20: 100 | J20: 0 | K20: 6.2 | L20: 28.9 | M20: 44.3 | N20: 14.1 | O20: 6.6 | P20: 0.9 | Q20: 6.8 | R20: 24.8 | S20: 48.1 | T20: 17.3 | U20: 2 | V20: 0 | W20: 0 | X20: 93.9 | Y20: 0 | Z20: 0 | AA20: 0 | AB20: 6.1 | AC20: 0 | AD20: 75.8 | AE20: 10.5 | AF20: 0 | AG20: 13.7 | AH20: 6.71 | AI20: 6.07 | AJ20: 6.74 | AK20: 7.29 | AL20: 0.29
A21: CENTRE | B21: VAUBAN | C21: Barbieux-Vauban | D21: 95 | E21: 0 | H21: 10.9 | O21: 11.7 | U21: 12.9 | X21: 18.9 | Z21: 23.4 | AB21: 15.3 | AH21: 8.09 | AI21: 6.78 | AJ21: 7.55 | AK21: 10.3 | AL21: 0.91
A22: SUD | B22: BARBIEUX | C22: Barbieux Sud | D22: 90 | E22: 0 | H22: 12.6 | N22: 11.6 | AH22: 9.06 | AI22: 7.52 | AJ22: 10.07 | AK22: 10.35 | AL22: 0.56
A23: SUD | B23: EDOUARD VAILLANT | C23: Édouard Vaillant | D23: 418 | E23: 0 | F23: 4.1 | G23: 4.1 | H23: 7.3 | I23: 65.4 | J23: 34.6 | K23: 3.1 | L23: 33.1 | M23: 30 | N23: 30.7 | O23: 3.1 | P23: 0 | Q23: 3.3 | R23: 41.1 | S23: 32.7 | T23: 23 | U23: 0 | V23: 0 | W23: 2.8 | X23: 44.7 | Y23: 0 | Z23: 0 | AA23: 14.1 | AB23: 38.4 | AC23: 10.2 | AD23: 43.4 | AE23: 26.1 | AF23: 20.2 | AG23: 0 | AH23: 7.1 | AI23: 5.98 | AJ23: 6.81 | AK23: 8.02 | AL23: 0.53
A24: SUD | B24: MOULIN | C24: Moulin Nord | D24: 118 | E24: 0 | H24: 10.1 | I24: 16.8 | L24: 10.3 | M24: 12.1 | O24: 25 | P24: 0 | Q24: 0 | R24: 10.6 | S24: 11.3 | T24: 40.8 | U24: 28.9 | V24: 8.5 | AA24: 11.5 | AC24: 26.6 | AD24: 13.7 | AF24: 0 | AG24: 0 | AH24: 6.23 | AI24: 5.6 | AJ24: 6.08 | AK24: 7.09 | AL24: 0.16
A25: SUD | B25: MOULIN | C25: Moulin Sud | D25: 92 | E25: 0 | AH25: 6.32 | AI25: 5.41 | AJ25: 6.33 | AK25: 7.06 | AL25: 0.17
A26: SUD | B26: POTENNERIE | C26: Potennerie | D26: 562 | E26: 0 | F26: 0 | G26: 0 | H26: 7.7 | I26: 96 | J26: 4 | K26: 5.4 | L26: 41.8 | M26: 41.2 | N26: 8.9 | O26: 2.7 | P26: 2.6 | Q26: 7.9 | R26: 47.5 | S26: 39.8 | T26: 2.2 | U26: 0 | V26: 0 | W26: 2.6 | X26: 89.7 | Y26: 0 | Z26: 2 | AA26: 2.6 | AB26: 3.1 | AC26: 0 | AD26: 90.4 | AE26: 9.6 | AF26: 0 | AG26: 0 | AH26: 6.52 | AI26: 5.62 | AJ26: 6.53 | AK26: 6.84 | AL26: 0.37
A27: EST | B27: STE ELISABETH | C27: Sainte-Élisabeth Centre | D27: 148 | E27: 0 | F27: 0 | G27: 0 | H27: 6.5 | I27: 46.2 | J27: 53.8 | K27: 0 | L27: 23.8 | M27: 23.8 | N27: 31.2 | O27: 21.2 | P27: 0 | Q27: 6.8 | R27: 33.3 | S27: 21 | T27: 27.2 | U27: 11.7 | V27: 0 | W27: 25.1 | X27: 6 | Y27: 29.5 | Z27: 6.6 | AA27: 18 | AB27: 14.8 | AC27: 19.5 | AD27: 0 | AE27: 80.5 | AF27: 0 | AG27: 0 | AH27: 5.8 | AI27: 5.41 | AJ27: 5.7 | AK27: 6.19 | AL27: 0.16
A28: EST | B28: STE ELISABETH | C28: Sainte-Élisabeth Sud | D28: 249 | E28: 27 | F28: 0 | G28: 0 | H28: 0 | I28: 83.5 | J28: 16.5 | K28: 0 | L28: 5.4 | M28: 67.9 | N28: 21.7 | O28: 5 | P28: 0 | Q28: 0 | R28: 64.1 | S28: 24.7 | T28: 11.2 | U28: 0 | V28: 0 | W28: 5 | X28: 61.2 | Y28: 5.8 | Z28: 21.3 | AA28: 0 | AB28: 6.6 | AC28: 6.6 | AD28: 62.9 | AE28: 30.5 | AF28: 0 | AG28: 0 | AH28: 6.21 | AI28: 5.92 | AJ28: 6.03 | AK28: 6.26 | AL28: 0.14
A29: EST | B29: STE ELISABETH | C29: Sainte-Élisabeth Nord | D29: 470 | E29: 0 | F29: 0 | G29: 0 | H29: 6.5 | I29: 85.8 | J29: 14.2 | K29: 14.3 | L29: 33.4 | M29: 34.9 | N29: 10.6 | O29: 6.8 | P29: 2.5 | Q29: 8.1 | R29: 28.6 | S29: 42.6 | T29: 12.1 | U29: 2.8 | V29: 3.4 | W29: 10 | X29: 35.3 | Y29: 26.2 | Z29: 16.6 | AA29: 11.9 | AB29: 0 | AC29: 7.3 | AD29: 34 | AE29: 51.8 | AF29: 0 | AG29: 6.9 | AH29: 6.01 | AI29: 5.31 | AJ29: 5.7 | AK29: 6.48 | AL29: 0.22
A30: EST | B30: PILE | C30: Pile Est | D30: 190 | E30: 0 | F30: 0 | G30: 0 | H30: 7.1 | I30: 68.7 | J30: 31.3 | K30: 0 | L30: 32.8 | M30: 34.8 | N30: 15.7 | O30: 16.7 | P30: 0 | Q30: 0 | R30: 63.6 | S30: 16.6 | T30: 8 | U30: 11.8 | V30: 0 | W30: 10.7 | X30: 44.4 | Y30: 7.8 | Z30: 15.6 | AA30: 21.5 | AB30: 0 | AC30: 0 | AD30: 50.6 | AE30: 42.6 | AF30: 0 | AG30: 6.8 | AH30: 6.04 | AI30: 5.64 | AJ30: 6.14 | AK30: 6.4 | AL30: 0.2
A31: EST | B31: PILE | C31: Pile Centre | D31: 257 | E31: 0 | F31: 5 | G31: 0 | H31: 6.3 | I31: 55.4 | J31: 44.6 | K31: 0 | L31: 26.9 | M31: 33.9 | N31: 27.3 | O31: 12 | P31: 0 | Q31: 4.4 | R31: 23.5 | S31: 43 | T31: 21 | U31: 4 | V31: 4 | W31: 12 | X31: 6.8 | Y31: 16.4 | Z31: 14 | AA31: 26 | AB31: 24.8 | AC31: 9.3 | AD31: 0 | AE31: 85.3 | AF31: 0 | AG31: 5.4 | AH31: 6.24 | AI31: 5.79 | AJ31: 6.16 | AK31: 6.68 | AL31: 0.17
A32: EST | B32: PILE | C32: Pile Nord | D32: 71 | E32: 0 | AH32: 5.6 | AI32: 5.17 | AJ32: 5.65 | AK32: 5.93 | AL32: 0.33
A33: EST | B33: TROIS PONTS | C33: Trois Ponts Nord | D33: 188 | E33: 0 | F33: 7.9 | G33: 0 | H33: 8 | I33: 100 | J33: 0 | K33: 0 | L33: 23.4 | M33: 43.3 | N33: 33.3 | O33: 0 | P33: 0 | Q33: 7.1 | R33: 13.1 | S33: 60.1 | T33: 19.6 | U33: 0 | V33: 0 | W33: 0 | X33: 61.4 | Y33: 0 | Z33: 0 | AA33: 24 | AB33: 14.6 | AC33: 0 | AD33: 59 | AE33: 41 | AF33: 0 | AG33: 0 | AH33: 6.13 | AI33: 5.56 | AJ33: 5.98 | AK33: 6.54 | AL33: 0.1
A34: EST | B34: TROIS PONTS | C34: Trois Ponts Sud | D34: 761 | E34: 0 | F34: 0 | G34: 0 | H34: 5.3 | I34: 97.4 | J34: 2.6 | K34: 1.8 | L34: 18.7 | M34: 47.4 | N34: 30.7 | O34: 1.4 | P34: 0 | Q34: 1.6 | R34: 18.9 | S34: 61 | T34: 18.5 | U34: 0 | V34: 0 | W34: 0 | X34: 86.4 | Y34: 0 | Z34: 0 | AA34: 11.3 | AB34: 2.3 | AC34: 0 | AD34: 86.4 | AE34: 11.3 | AF34: 2.3 | AG34: 0 | AH34: 6.39 | AI34: 5.55 | AJ34: 6.35 | AK34: 6.97 | AL34: 0.18
A35: EST | B35: SARTEL CARIHEM | C35: Sartel | D35: 282 | E35: 0 | F35: 0 | G35: 0 | H35: 4.9 | I35: 89.7 | J35: 10.3 | K35: 10.7 | L35: 25.1 | M35: 27.8 | N35: 19.1 | O35: 17.4 | P35: 0 | Q35: 18.4 | R35: 39.6 | S35: 33.2 | T35: 8.8 | U35: 0 | V35: 0 | W35: 0 | X35: 78.5 | Y35: 13.5 | Z35: 8 | AA35: 0 | AB35: 0 | AC35: 8 | AD35: 78.2 | AE35: 13.8 | AF35: 0 | AG35: 0 | AH35: 6.41 | AI35: 5.88 | AJ35: 6.32 | AK35: 6.98 | AL35: 1
A36: SUD | B36: CHEMIN NEUF/LINNE | C36: Linné-Chemin Neuf | D36: 556 | E36: 0 | F36: 2.4 | G36: 0 | H36: 4.5 | I36: 85.8 | J36: 14.2 | K36: 2.8 | L36: 42 | M36: 37.5 | N36: 14.7 | O36: 3 | P36: 0 | Q36: 2.7 | R36: 65.7 | S36: 23.2 | T36: 6.2 | U36: 2.2 | V36: 0 | W36: 2.9 | X36: 72.6 | Y36: 13.7 | Z36: 4.2 | AA36: 2 | AB36: 4.6 | AC36: 4.9 | AD36: 63.5 | AE36: 20.7 | AF36: 2.8 | AG36: 8.1 | AH36: 6.69 | AI36: 6.14 | AJ36: 6.54 | AK36: 7.23 | AL36: 0.46
A37: SUD | B37: JUSTICE | C37: Justice | D37: 206 | E37: 0 | F37: 5.6 | G37: 0 | H37: 6.6 | I37: 29.4 | J37: 70.6 | K37: 0 | L37: 8.6 | M37: 26.9 | N37: 48.7 | O37: 15.7 | P37: 0 | Q37: 0 | R37: 16.1 | S37: 28.6 | T37: 44.2 | U37: 5.5 | V37: 5.5 | W37: 7.7 | X37: 58.7 | Y37: 0 | Z37: 17.3 | AA37: 16.3 | AB37: 0 | AC37: 0 | AD37: 61.6 | AE37: 38.4 | AF37: 0 | AG37: 0 | AH37: 6.03 | AI37: 5.24 | AJ37: 5.91 | AK37: 6.77 | AL37: 0.52
A38: EST | B38: FRATERNITE | C38: Fraternité | D38: 33 | E38: 0 | AH38: 5.48 | AL38: 0.41
A39: SUD | B39: NOUVEAU ROUBAIX | C39: Nouveau Roubaix | D39: 885 | E39: 0 | F39: 0 | G39: 0 | H39: 6.9 | I39: 80.5 | J39: 19.5 | K39: 6.4 | L39: 24.9 | M39: 40.7 | N39: 25.3 | O39: 2.7 | P39: 3 | Q39: 4.8 | R39: 36.8 | S39: 43.3 | T39: 12.2 | U39: 0 | V39: 0 | W39: 65.5 | X39: 32.2 | Y39: 0 | Z39: 0 | AA39: 2.3 | AB39: 0 | AC39: 0 | AD39: 97.6 | AE39: 2.4 | AF39: 0 | AG39: 0 | AH39: 6.59 | AI39: 6.02 | AJ39: 6.41 | AK39: 7.17 | AL39: 0.17
A40: SUD | B40: HAUTS CHAMPS/PETITES HAIES | C40: Hauts Champs | D40: 842 | E40: 0 | F40: 0 | G40: 0 | H40: 7.9 | I40: 82.1 | J40: 17.9 | K40: 0 | L40: 18.1 | M40: 54.3 | N40: 24.3 | O40: 3.2 | P40: 0 | Q40: 1.9 | R40: 61 | S40: 24.4 | T40: 11.4 | U40: 1.3 | V40: 0 | W40: 0 | X40: 97.2 | Y40: 0 | Z40: 0 | AA40: 2.8 | AB40: 0 | AC40: 0 | AD40: 92.4 | AE40: 7.6 | AF40: 0 | AG40: 0 | AH40: 6.45 | AI40: 5.91 | AJ40: 6.52 | AK40: 6.98 | AL40: 0.31
